Sorry: IndentationError: unexpected indent (indented_0.py, line 41)

<module>: Success: Equal

<module>.CaptchaSolverService: Success: Equal

<module>.CaptchaSolverService.__init__: Success: Equal

***<module>.CaptchaSolverService.solve_audio_captcha: Failure: Compilation Error

<module>.CaptchaSolverService.solve_audio_captcha_from_file: Success: Equal

***<module>.CaptchaSolverService.solve_audio_captcha_from_bytes: Failure: Compilation Error

***<module>.CaptchaSolverService._process_audio_file: Failure: Compilation Error

***<module>.CaptchaSolverService._convert_to_wav_16k_mono: Failure: Compilation Error

<module>.CaptchaSolverService._clean_captcha_result: Success: Equal



0 LOAD_CONST 0 ("\nService untuk menyelesaikan captcha menggunakan speech recognition\n")
2 STORE_NAME 0 (__doc__)

4 LOAD_CONST 1 (0)
6 LOAD_CONST 2 (None)
8 IMPORT_NAME 1 (speech_recognition)
10 STORE_NAME 2 (sr)

12 LOAD_CONST 1 (0)
14 LOAD_CONST 2 (None)
16 IMPORT_NAME 3 (requests)
18 STORE_NAME 3 (requests)

20 LOAD_CONST 1 (0)
22 LOAD_CONST 2 (None)
24 IMPORT_NAME 4 (tempfile)
26 STORE_NAME 4 (tempfile)

28 LOAD_CONST 1 (0)
30 LOAD_CONST 2 (None)
32 IMPORT_NAME 5 (os)
34 STORE_NAME 5 (os)

36 LOAD_CONST 1 (0)
38 LOAD_CONST 3 (('Optional',))
40 IMPORT_NAME 6 (typing)
42 IMPORT_FROM 7 (Optional)
44 STORE_NAME 7 (Optional)
46 POP_TOP

48 LOAD_CONST 1 (0)
50 LOAD_CONST 2 (None)
52 IMPORT_NAME 8 (logging)
54 STORE_NAME 8 (logging)

56 LOAD_CONST 1 (0)
58 LOAD_CONST 4 (('AudioFileClip',))
60 IMPORT_NAME 9 (moviepy.audio.io.AudioFileClip)
62 IMPORT_FROM 10 (AudioFileClip)
64 STORE_NAME 10 (AudioFileClip)
66 POP_TOP

68 LOAD_CONST 1 (0)
70 LOAD_CONST 2 (None)
72 IMPORT_NAME 11 (imageio_ffmpeg)
74 STORE_NAME 11 (imageio_ffmpeg)

76 LOAD_CONST 1 (0)
78 LOAD_CONST 2 (None)
80 IMPORT_NAME 12 (subprocess)
82 STORE_NAME 12 (subprocess)

84 LOAD_CONST 1 (0)
86 LOAD_CONST 2 (None)
88 IMPORT_NAME 13 (shlex)
90 STORE_NAME 13 (shlex)

92 LOAD_CONST 1 (0)
94 LOAD_CONST 2 (None)
96 IMPORT_NAME 14 (io)
98 STORE_NAME 14 (io)

100 PUSH_NULL
102 LOAD_NAME 8 (logging)
104 LOAD_ATTR 15 (getLogger)
106 LOAD_NAME 16 (__name__)
108 CALL 1
110 STORE_NAME 17 (logger)

112 PUSH_NULL
114 LOAD_BUILD_CLASS
116 LOAD_CONST 5 (code object CaptchaSolverService)
118 MAKE_FUNCTION 0 (No arguments)
120 LOAD_CONST 6 ("CaptchaSolverService")
122 CALL 2
124 STORE_NAME 18 (CaptchaSolverService)

126 LOAD_NAME 16 (__name__)
128 LOAD_CONST 7 ("__main__")
130 COMPARE_OP 2 (==)
132 POP_JUMP_FORWARD_IF_FALSE 45 (to 176)

134 PUSH_NULL
136 LOAD_NAME 18 (CaptchaSolverService)
138 CALL 0
140 STORE_NAME 19 (solver)

142 PUSH_NULL
144 LOAD_NAME 20 (print)
146 LOAD_CONST 8 ("CaptchaSolverService initialized successfully")
148 CALL 1
150 POP_TOP

152 PUSH_NULL
154 LOAD_NAME 20 (print)
156 LOAD_CONST 9 ("Use solve_audio_captcha(url) to solve captcha from URL")
158 CALL 1
160 POP_TOP

162 PUSH_NULL
164 LOAD_NAME 20 (print)
166 LOAD_CONST 10 ("Use solve_audio_captcha_from_file(path) to solve from local file")
168 CALL 1
170 POP_TOP
172 LOAD_CONST 2 (None)
174 RETURN_VALUE

176 LOAD_CONST 2 (None)
178 RETURN_VALUE


0 LOAD_NAME 0 (__name__)
2 STORE_NAME 1 (__module__)
4 LOAD_CONST 0 ("CaptchaSolverService")
6 STORE_NAME 2 (__qualname__)

8 LOAD_CONST 1 ("Service untuk menyelesaikan audio captcha menggunakan speech recognition")
10 STORE_NAME 3 (__doc__)

12 LOAD_CONST 2 (code object __init__)
14 MAKE_FUNCTION 0 (No arguments)
16 STORE_NAME 4 (__init__)

18 LOAD_CONST 3 ("audio_url")
20 LOAD_NAME 5 (str)
22 LOAD_CONST 4 ("return")
24 LOAD_NAME 6 (Optional)
26 LOAD_NAME 5 (str)
28 BINARY_SUBSCR
30 BUILD_TUPLE 4
32 LOAD_CONST 5 (code object solve_audio_captcha)
34 MAKE_FUNCTION 4 (annotation)
36 STORE_NAME 7 (solve_audio_captcha)

38 LOAD_CONST 6 ("file_path")
40 LOAD_NAME 5 (str)
42 LOAD_CONST 4 ("return")
44 LOAD_NAME 6 (Optional)
46 LOAD_NAME 5 (str)
48 BINARY_SUBSCR
50 BUILD_TUPLE 4
52 LOAD_CONST 7 (code object solve_audio_captcha_from_file)
54 MAKE_FUNCTION 4 (annotation)
56 STORE_NAME 8 (solve_audio_captcha_from_file)

58 NOP

60 LOAD_CONST 17 (('wav',))
62 LOAD_CONST 9 ("audio_bytes")
64 LOAD_NAME 9 (bytes)

66 LOAD_CONST 10 ("format")
68 LOAD_NAME 5 (str)

70 LOAD_CONST 4 ("return")
72 LOAD_NAME 6 (Optional)
74 LOAD_NAME 5 (str)
76 BINARY_SUBSCR

78 BUILD_TUPLE 6
80 LOAD_CONST 11 (code object solve_audio_captcha_from_bytes)
82 MAKE_FUNCTION 5 (default, annotation)
84 STORE_NAME 10 (solve_audio_captcha_from_bytes)

86 LOAD_CONST 6 ("file_path")
88 LOAD_NAME 5 (str)
90 LOAD_CONST 4 ("return")
92 LOAD_NAME 6 (Optional)
94 LOAD_NAME 5 (str)
96 BINARY_SUBSCR
98 BUILD_TUPLE 4
100 LOAD_CONST 12 (code object _process_audio_file)
102 MAKE_FUNCTION 4 (annotation)
104 STORE_NAME 11 (_process_audio_file)

106 LOAD_CONST 6 ("file_path")
108 LOAD_NAME 5 (str)
110 LOAD_CONST 4 ("return")
112 LOAD_NAME 5 (str)
114 BUILD_TUPLE 4
116 LOAD_CONST 13 (code object _convert_to_wav_16k_mono)
118 MAKE_FUNCTION 4 (annotation)
120 STORE_NAME 12 (_convert_to_wav_16k_mono)

122 LOAD_CONST 14 ("result")
124 LOAD_NAME 5 (str)
126 LOAD_CONST 4 ("return")
128 LOAD_NAME 5 (str)
130 BUILD_TUPLE 4
132 LOAD_CONST 15 (code object _clean_captcha_result)
134 MAKE_FUNCTION 4 (annotation)
136 STORE_NAME 13 (_clean_captcha_result)
138 LOAD_CONST 16 (None)
140 RETURN_VALUE


0 LOAD_GLOBAL 1 (NULL + sr)
2 LOAD_ATTR 1 (Recognizer)
4 CALL 0
6 LOAD_FAST 0 (self)
8 STORE_ATTR 2 (recognizer)

10 LOAD_CONST 1 (200)
12 LOAD_FAST 0 (self)
14 LOAD_ATTR 2 (recognizer)
16 STORE_ATTR 3 (energy_threshold)

18 LOAD_CONST 2 (True)
20 LOAD_FAST 0 (self)
22 LOAD_ATTR 2 (recognizer)
24 STORE_ATTR 4 (dynamic_energy_threshold)

26 LOAD_CONST 3 (0.5)
28 LOAD_FAST 0 (self)
30 LOAD_ATTR 2 (recognizer)
32 STORE_ATTR 5 (pause_threshold)

34 LOAD_CONST 4 (None)
36 LOAD_FAST 0 (self)
38 LOAD_ATTR 2 (recognizer)
40 STORE_ATTR 6 (operation_timeout)

42 LOAD_CONST 5 (0.2)
44 LOAD_FAST 0 (self)
46 LOAD_ATTR 2 (recognizer)
48 STORE_ATTR 7 (phrase_threshold)

50 LOAD_CONST 3 (0.5)
52 LOAD_FAST 0 (self)
54 LOAD_ATTR 2 (recognizer)
56 STORE_ATTR 8 (non_speaking_duration)
58 LOAD_CONST 4 (None)
60 RETURN_VALUE


0 NOP

2 LOAD_GLOBAL 1 (NULL + requests)
4 LOAD_ATTR 1 (get)
6 LOAD_FAST 1 (audio_url)
8 LOAD_CONST 1 (10)
10 KW_NAMES 2 (('timeout',))
12 CALL 2
14 STORE_FAST 2 (response)

16 LOAD_FAST 2 (response)
18 LOAD_METHOD 2 (raise_for_status)
20 CALL 0
22 POP_TOP

24 LOAD_GLOBAL 7 (NULL + tempfile)
26 LOAD_ATTR 4 (NamedTemporaryFile)
28 LOAD_CONST 3 (False)
30 LOAD_CONST 4 (".wav")
32 KW_NAMES 5 (('delete', 'suffix'))
34 CALL 2
36 BEFORE_WITH
38 STORE_FAST 3 (temp_file)

40 LOAD_FAST 3 (temp_file)
42 LOAD_METHOD 5 (write)
44 LOAD_FAST 2 (response)
46 LOAD_ATTR 6 (content)
48 CALL 1
50 POP_TOP

52 LOAD_FAST 3 (temp_file)
54 LOAD_ATTR 7 (name)
56 STORE_FAST 4 (temp_file_path)

58 LOAD_CONST 6 (None)
60 LOAD_CONST 6 (None)
62 LOAD_CONST 6 (None)
64 CALL 2
66 POP_TOP
68 JUMP_FORWARD 11 (to 92)
70 PUSH_EXC_INFO
72 WITH_EXCEPT_START
74 POP_JUMP_FORWARD_IF_TRUE 4 (to 84)
76 RERAISE 2
78 COPY 3
80 POP_EXCEPT
82 RERAISE 1
84 POP_TOP
86 POP_EXCEPT
88 POP_TOP
90 POP_TOP

92 NOP

94 LOAD_FAST 0 (self)
96 LOAD_METHOD 8 (_process_audio_file)
98 LOAD_FAST 4 (temp_file_path)
100 CALL 1
102 STORE_FAST 5 (result)

104 LOAD_FAST 5 (result)

106 LOAD_GLOBAL 18 (os)
108 LOAD_ATTR 10 (path)
110 LOAD_METHOD 11 (exists)
112 LOAD_FAST 4 (temp_file_path)
114 CALL 1
116 POP_JUMP_FORWARD_IF_FALSE 21 (to 130)

118 LOAD_GLOBAL 19 (NULL + os)
120 LOAD_ATTR 12 (unlink)
122 LOAD_FAST 4 (temp_file_path)
124 CALL 1
126 POP_TOP
128 RETURN_VALUE

130 RETURN_VALUE
132 PUSH_EXC_INFO
134 LOAD_GLOBAL 18 (os)
136 LOAD_ATTR 10 (path)
138 LOAD_METHOD 11 (exists)
140 LOAD_FAST 4 (temp_file_path)
142 CALL 1
144 POP_JUMP_FORWARD_IF_FALSE 21 (to 158)

146 LOAD_GLOBAL 19 (NULL + os)
148 LOAD_ATTR 12 (unlink)
150 LOAD_FAST 4 (temp_file_path)
152 CALL 1
154 POP_TOP
156 RERAISE 0

158 RERAISE 0
160 COPY 3
162 POP_EXCEPT
164 RERAISE 1
166 PUSH_EXC_INFO

168 LOAD_GLOBAL 0 (requests)
170 LOAD_ATTR 13 (RequestException)
172 CHECK_EXC_MATCH
174 POP_JUMP_FORWARD_IF_FALSE 40 (to 214)
176 STORE_FAST 6 (e)

178 LOAD_GLOBAL 28 (logger)
180 LOAD_METHOD 15 (error)
182 LOAD_CONST 7 ("Error downloading audio captcha: ")
184 LOAD_FAST 6 (e)
186 FORMAT_VALUE 0
188 BUILD_STRING 2
190 CALL 1
192 POP_TOP

194 POP_EXCEPT
196 LOAD_CONST 6 (None)
198 STORE_FAST 6 (e)
200 DELETE_FAST 6 (e)
202 LOAD_CONST 6 (None)
204 RETURN_VALUE
206 LOAD_CONST 6 (None)
208 STORE_FAST 6 (e)
210 DELETE_FAST 6 (e)
212 RERAISE 1

214 LOAD_GLOBAL 32 (Exception)
216 CHECK_EXC_MATCH
218 POP_JUMP_FORWARD_IF_FALSE 40 (to 258)
220 STORE_FAST 6 (e)

222 LOAD_GLOBAL 28 (logger)
224 LOAD_METHOD 15 (error)
226 LOAD_CONST 8 ("Error solving audio captcha: ")
228 LOAD_FAST 6 (e)
230 FORMAT_VALUE 0
232 BUILD_STRING 2
234 CALL 1
236 POP_TOP

238 POP_EXCEPT
240 LOAD_CONST 6 (None)
242 STORE_FAST 6 (e)
244 DELETE_FAST 6 (e)
246 LOAD_CONST 6 (None)
248 RETURN_VALUE
250 LOAD_CONST 6 (None)
252 STORE_FAST 6 (e)
254 DELETE_FAST 6 (e)
256 RERAISE 1

258 RERAISE 0
260 COPY 3
262 POP_EXCEPT
264 RERAISE 1


0 NOP

2 LOAD_GLOBAL 0 (os)
4 LOAD_ATTR 1 (path)
6 LOAD_METHOD 2 (exists)
8 LOAD_FAST 1 (file_path)
10 CALL 1
12 POP_JUMP_FORWARD_IF_TRUE 31 (to 34)

14 LOAD_GLOBAL 6 (logger)
16 LOAD_METHOD 4 (error)
18 LOAD_CONST 1 ("Audio file not found: ")
20 LOAD_FAST 1 (file_path)
22 FORMAT_VALUE 0
24 BUILD_STRING 2
26 CALL 1
28 POP_TOP

30 LOAD_CONST 2 (None)
32 RETURN_VALUE

34 LOAD_FAST 0 (self)
36 LOAD_METHOD 5 (_process_audio_file)
38 LOAD_FAST 1 (file_path)
40 CALL 1
42 RETURN_VALUE
44 PUSH_EXC_INFO

46 LOAD_GLOBAL 12 (Exception)
48 CHECK_EXC_MATCH
50 POP_JUMP_FORWARD_IF_FALSE 40 (to 90)
52 STORE_FAST 2 (e)

54 LOAD_GLOBAL 6 (logger)
56 LOAD_METHOD 4 (error)
58 LOAD_CONST 3 ("Error solving audio captcha from file: ")
60 LOAD_FAST 2 (e)
62 FORMAT_VALUE 0
64 BUILD_STRING 2
66 CALL 1
68 POP_TOP

70 POP_EXCEPT
72 LOAD_CONST 2 (None)
74 STORE_FAST 2 (e)
76 DELETE_FAST 2 (e)
78 LOAD_CONST 2 (None)
80 RETURN_VALUE
82 LOAD_CONST 2 (None)
84 STORE_FAST 2 (e)
86 DELETE_FAST 2 (e)
88 RERAISE 1

90 RERAISE 0
92 COPY 3
94 POP_EXCEPT
96 RERAISE 1


0 NOP

2 LOAD_GLOBAL 1 (NULL + tempfile)
4 LOAD_ATTR 1 (NamedTemporaryFile)
6 LOAD_CONST 1 (False)
8 LOAD_CONST 2 (".")
10 LOAD_FAST 2 (format)
12 FORMAT_VALUE 0
14 BUILD_STRING 2
16 KW_NAMES 3 (('delete', 'suffix'))
18 CALL 2
20 BEFORE_WITH
22 STORE_FAST 3 (temp_file)

24 LOAD_FAST 3 (temp_file)
26 LOAD_METHOD 2 (write)
28 LOAD_FAST 1 (audio_bytes)
30 CALL 1
32 POP_TOP

34 LOAD_FAST 3 (temp_file)
36 LOAD_ATTR 3 (name)
38 STORE_FAST 4 (temp_file_path)

40 LOAD_CONST 4 (None)
42 LOAD_CONST 4 (None)
44 LOAD_CONST 4 (None)
46 CALL 2
48 POP_TOP
50 JUMP_FORWARD 11 (to 74)
52 PUSH_EXC_INFO
54 WITH_EXCEPT_START
56 POP_JUMP_FORWARD_IF_TRUE 4 (to 66)
58 RERAISE 2
60 COPY 3
62 POP_EXCEPT
64 RERAISE 1
66 POP_TOP
68 POP_EXCEPT
70 POP_TOP
72 POP_TOP

74 NOP

76 LOAD_FAST 0 (self)
78 LOAD_METHOD 4 (_process_audio_file)
80 LOAD_FAST 4 (temp_file_path)
82 CALL 1
84 STORE_FAST 5 (result)

86 LOAD_FAST 5 (result)

88 LOAD_GLOBAL 10 (os)
90 LOAD_ATTR 6 (path)
92 LOAD_METHOD 7 (exists)
94 LOAD_FAST 4 (temp_file_path)
96 CALL 1
98 POP_JUMP_FORWARD_IF_FALSE 21 (to 112)

100 LOAD_GLOBAL 11 (NULL + os)
102 LOAD_ATTR 8 (unlink)
104 LOAD_FAST 4 (temp_file_path)
106 CALL 1
108 POP_TOP
110 RETURN_VALUE

112 RETURN_VALUE
114 PUSH_EXC_INFO
116 LOAD_GLOBAL 10 (os)
118 LOAD_ATTR 6 (path)
120 LOAD_METHOD 7 (exists)
122 LOAD_FAST 4 (temp_file_path)
124 CALL 1
126 POP_JUMP_FORWARD_IF_FALSE 21 (to 140)

128 LOAD_GLOBAL 11 (NULL + os)
130 LOAD_ATTR 8 (unlink)
132 LOAD_FAST 4 (temp_file_path)
134 CALL 1
136 POP_TOP
138 RERAISE 0

140 RERAISE 0
142 COPY 3
144 POP_EXCEPT
146 RERAISE 1
148 PUSH_EXC_INFO

150 LOAD_GLOBAL 18 (Exception)
152 CHECK_EXC_MATCH
154 POP_JUMP_FORWARD_IF_FALSE 40 (to 194)
156 STORE_FAST 6 (e)

158 LOAD_GLOBAL 20 (logger)
160 LOAD_METHOD 11 (error)
162 LOAD_CONST 5 ("Error solving audio captcha from bytes: ")
164 LOAD_FAST 6 (e)
166 FORMAT_VALUE 0
168 BUILD_STRING 2
170 CALL 1
172 POP_TOP

174 POP_EXCEPT
176 LOAD_CONST 4 (None)
178 STORE_FAST 6 (e)
180 DELETE_FAST 6 (e)
182 LOAD_CONST 4 (None)
184 RETURN_VALUE
186 LOAD_CONST 4 (None)
188 STORE_FAST 6 (e)
190 DELETE_FAST 6 (e)
192 RERAISE 1

194 RERAISE 0
196 COPY 3
198 POP_EXCEPT
200 RERAISE 1


0 NOP

2 LOAD_FAST 0 (self)
4 LOAD_METHOD 0 (_convert_to_wav_16k_mono)
6 LOAD_FAST 1 (file_path)
8 CALL 1
10 STORE_FAST 2 (wav_path)

12 LOAD_GLOBAL 3 (NULL + sr)
14 LOAD_ATTR 2 (AudioFile)
16 LOAD_FAST 2 (wav_path)
18 CALL 1
20 BEFORE_WITH
22 STORE_FAST 3 (source)

24 LOAD_FAST 0 (self)
26 LOAD_ATTR 3 (recognizer)
28 LOAD_METHOD 4 (adjust_for_ambient_noise)
30 LOAD_FAST 3 (source)
32 LOAD_CONST 1 (0.05)
34 KW_NAMES 2 (('duration',))
36 CALL 2
38 POP_TOP

40 LOAD_FAST 0 (self)
42 LOAD_ATTR 3 (recognizer)
44 LOAD_METHOD 5 (record)
46 LOAD_FAST 3 (source)
48 CALL 1
50 STORE_FAST 4 (audio)

52 LOAD_CONST 3 (None)
54 LOAD_CONST 3 (None)
56 LOAD_CONST 3 (None)
58 CALL 2
60 POP_TOP
62 JUMP_FORWARD 11 (to 86)
64 PUSH_EXC_INFO
66 WITH_EXCEPT_START
68 POP_JUMP_FORWARD_IF_TRUE 4 (to 78)
70 RERAISE 2
72 COPY 3
74 POP_EXCEPT
76 RERAISE 1
78 POP_TOP
80 POP_EXCEPT
82 POP_TOP
84 POP_TOP

86 NOP

88 LOAD_FAST 0 (self)
90 LOAD_ATTR 3 (recognizer)
92 LOAD_METHOD 6 (recognize_google)
94 LOAD_FAST 4 (audio)
96 LOAD_CONST 4 ("en-US")
98 KW_NAMES 5 (('language',))
100 CALL 2
102 STORE_FAST 5 (raw)

104 LOAD_FAST 5 (raw)
106 POP_JUMP_FORWARD_IF_FALSE 167 (to 238)

108 LOAD_FAST 0 (self)
110 LOAD_METHOD 7 (_clean_captcha_result)
112 LOAD_FAST 5 (raw)
114 CALL 1
116 STORE_FAST 6 (cleaned)

118 LOAD_GLOBAL 16 (logger)
120 LOAD_METHOD 9 (info)
122 LOAD_CONST 6 ("Google recognition raw='")
124 LOAD_FAST 5 (raw)
126 LOAD_CONST 3 (None)
128 LOAD_CONST 7 (80)
130 BUILD_SLICE 2
132 BINARY_SUBSCR
134 FORMAT_VALUE 0
136 LOAD_CONST 8 ("'")
138 BUILD_STRING 3
140 CALL 1
142 POP_TOP

144 LOAD_FAST 6 (cleaned)

146 NOP

148 LOAD_CONST 9 ("wav_path")
150 LOAD_GLOBAL 21 (NULL + locals)
152 CALL 0
154 CONTAINS_OP 0 (in)
156 POP_JUMP_FORWARD_IF_FALSE 71 (to 210)
158 LOAD_FAST 2 (wav_path)
160 POP_JUMP_FORWARD_IF_FALSE 70 (to 212)
162 LOAD_GLOBAL 22 (os)
164 LOAD_ATTR 12 (path)
166 LOAD_METHOD 13 (exists)
168 LOAD_FAST 2 (wav_path)
170 CALL 1
172 POP_JUMP_FORWARD_IF_FALSE 40 (to 214)

174 NOP

176 LOAD_GLOBAL 23 (NULL + os)
178 LOAD_ATTR 14 (unlink)
180 LOAD_FAST 2 (wav_path)
182 CALL 1
184 POP_TOP
186 RETURN_VALUE
188 PUSH_EXC_INFO

190 LOAD_GLOBAL 30 (Exception)
192 CHECK_EXC_MATCH
194 POP_JUMP_FORWARD_IF_FALSE 3 (to 202)
196 POP_TOP

198 POP_EXCEPT
200 RETURN_VALUE

202 RERAISE 0
204 COPY 3
206 POP_EXCEPT
208 RERAISE 1

210 RETURN_VALUE
212 RETURN_VALUE
214 RETURN_VALUE
216 PUSH_EXC_INFO

218 LOAD_GLOBAL 30 (Exception)
220 CHECK_EXC_MATCH
222 POP_JUMP_FORWARD_IF_FALSE 3 (to 230)
224 POP_TOP

226 POP_EXCEPT
228 RETURN_VALUE

230 RERAISE 0
232 COPY 3
234 POP_EXCEPT
236 RERAISE 1

238 JUMP_FORWARD 99 (to 318)
240 PUSH_EXC_INFO

242 LOAD_GLOBAL 2 (sr)
244 LOAD_ATTR 16 (UnknownValueError)
246 CHECK_EXC_MATCH
248 POP_JUMP_FORWARD_IF_FALSE 29 (to 266)
250 POP_TOP

252 LOAD_GLOBAL 16 (logger)
254 LOAD_METHOD 17 (debug)
256 LOAD_CONST 10 ("Google could not understand audio captcha")
258 CALL 1
260 POP_TOP
262 POP_EXCEPT
264 JUMP_FORWARD 56 (to 318)

266 LOAD_GLOBAL 2 (sr)
268 LOAD_ATTR 18 (RequestError)
270 CHECK_EXC_MATCH
272 POP_JUMP_FORWARD_IF_FALSE 39 (to 310)
274 STORE_FAST 7 (e)

276 LOAD_GLOBAL 16 (logger)
278 LOAD_METHOD 17 (debug)
280 LOAD_CONST 11 ("Google recognition error: ")
282 LOAD_FAST 7 (e)
284 FORMAT_VALUE 0
286 BUILD_STRING 2
288 CALL 1
290 POP_TOP
292 POP_EXCEPT
294 LOAD_CONST 3 (None)
296 STORE_FAST 7 (e)
298 DELETE_FAST 7 (e)
300 JUMP_FORWARD 8 (to 318)
302 LOAD_CONST 3 (None)
304 STORE_FAST 7 (e)
306 DELETE_FAST 7 (e)
308 RERAISE 1

310 RERAISE 0
312 COPY 3
314 POP_EXCEPT
316 RERAISE 1

318 NOP

320 NOP

322 LOAD_CONST 9 ("wav_path")
324 LOAD_GLOBAL 21 (NULL + locals)
326 CALL 0
328 CONTAINS_OP 0 (in)
330 POP_JUMP_FORWARD_IF_FALSE 73 (to 388)
332 LOAD_FAST 2 (wav_path)
334 POP_JUMP_FORWARD_IF_FALSE 73 (to 392)
336 LOAD_GLOBAL 22 (os)
338 LOAD_ATTR 12 (path)
340 LOAD_METHOD 13 (exists)
342 LOAD_FAST 2 (wav_path)
344 CALL 1
346 POP_JUMP_FORWARD_IF_FALSE 44 (to 396)

348 NOP

350 LOAD_GLOBAL 23 (NULL + os)
352 LOAD_ATTR 14 (unlink)
354 LOAD_FAST 2 (wav_path)
356 CALL 1
358 POP_TOP
360 LOAD_CONST 3 (None)
362 RETURN_VALUE
364 PUSH_EXC_INFO

366 LOAD_GLOBAL 30 (Exception)
368 CHECK_EXC_MATCH
370 POP_JUMP_FORWARD_IF_FALSE 4 (to 380)
372 POP_TOP

374 POP_EXCEPT
376 LOAD_CONST 3 (None)
378 RETURN_VALUE

380 RERAISE 0
382 COPY 3
384 POP_EXCEPT
386 RERAISE 1

388 LOAD_CONST 3 (None)
390 RETURN_VALUE
392 LOAD_CONST 3 (None)
394 RETURN_VALUE
396 LOAD_CONST 3 (None)
398 RETURN_VALUE
400 PUSH_EXC_INFO

402 LOAD_GLOBAL 30 (Exception)
404 CHECK_EXC_MATCH
406 POP_JUMP_FORWARD_IF_FALSE 4 (to 416)
408 POP_TOP

410 POP_EXCEPT
412 LOAD_CONST 3 (None)
414 RETURN_VALUE

416 RERAISE 0
418 COPY 3
420 POP_EXCEPT
422 RERAISE 1
424 PUSH_EXC_INFO

426 LOAD_GLOBAL 30 (Exception)
428 CHECK_EXC_MATCH
430 POP_JUMP_FORWARD_IF_FALSE 151 (to 570)
432 STORE_FAST 7 (e)

434 LOAD_GLOBAL 16 (logger)
436 LOAD_METHOD 19 (error)
438 LOAD_CONST 12 ("Error processing audio captcha: ")
440 LOAD_FAST 7 (e)
442 FORMAT_VALUE 0
444 BUILD_STRING 2
446 CALL 1
448 POP_TOP

450 POP_EXCEPT
452 LOAD_CONST 3 (None)
454 STORE_FAST 7 (e)
456 DELETE_FAST 7 (e)

458 NOP

460 LOAD_CONST 9 ("wav_path")
462 LOAD_GLOBAL 21 (NULL + locals)
464 CALL 0
466 CONTAINS_OP 0 (in)
468 POP_JUMP_FORWARD_IF_FALSE 73 (to 526)
470 LOAD_FAST 2 (wav_path)
472 POP_JUMP_FORWARD_IF_FALSE 73 (to 530)
474 LOAD_GLOBAL 22 (os)
476 LOAD_ATTR 12 (path)
478 LOAD_METHOD 13 (exists)
480 LOAD_FAST 2 (wav_path)
482 CALL 1
484 POP_JUMP_FORWARD_IF_FALSE 44 (to 534)

486 NOP

488 LOAD_GLOBAL 23 (NULL + os)
490 LOAD_ATTR 14 (unlink)
492 LOAD_FAST 2 (wav_path)
494 CALL 1
496 POP_TOP
498 LOAD_CONST 3 (None)
500 RETURN_VALUE
502 PUSH_EXC_INFO

504 LOAD_GLOBAL 30 (Exception)
506 CHECK_EXC_MATCH
508 POP_JUMP_FORWARD_IF_FALSE 4 (to 518)
510 POP_TOP

512 POP_EXCEPT
514 LOAD_CONST 3 (None)
516 RETURN_VALUE

518 RERAISE 0
520 COPY 3
522 POP_EXCEPT
524 RERAISE 1

526 LOAD_CONST 3 (None)
528 RETURN_VALUE
530 LOAD_CONST 3 (None)
532 RETURN_VALUE
534 LOAD_CONST 3 (None)
536 RETURN_VALUE
538 PUSH_EXC_INFO

540 LOAD_GLOBAL 30 (Exception)
542 CHECK_EXC_MATCH
544 POP_JUMP_FORWARD_IF_FALSE 4 (to 554)
546 POP_TOP

548 POP_EXCEPT
550 LOAD_CONST 3 (None)
552 RETURN_VALUE

554 RERAISE 0
556 COPY 3
558 POP_EXCEPT
560 RERAISE 1
562 LOAD_CONST 3 (None)
564 STORE_FAST 7 (e)
566 DELETE_FAST 7 (e)
568 RERAISE 1

570 RERAISE 0
572 COPY 3
574 POP_EXCEPT
576 RERAISE 1
578 PUSH_EXC_INFO

580 NOP

582 LOAD_CONST 9 ("wav_path")
584 LOAD_GLOBAL 21 (NULL + locals)
586 CALL 0
588 CONTAINS_OP 0 (in)
590 POP_JUMP_FORWARD_IF_FALSE 71 (to 644)
592 LOAD_FAST 2 (wav_path)
594 POP_JUMP_FORWARD_IF_FALSE 70 (to 646)
596 LOAD_GLOBAL 22 (os)
598 LOAD_ATTR 12 (path)
600 LOAD_METHOD 13 (exists)
602 LOAD_FAST 2 (wav_path)
604 CALL 1
606 POP_JUMP_FORWARD_IF_FALSE 40 (to 648)

608 NOP

610 LOAD_GLOBAL 23 (NULL + os)
612 LOAD_ATTR 14 (unlink)
614 LOAD_FAST 2 (wav_path)
616 CALL 1
618 POP_TOP
620 RERAISE 0
622 PUSH_EXC_INFO

624 LOAD_GLOBAL 30 (Exception)
626 CHECK_EXC_MATCH
628 POP_JUMP_FORWARD_IF_FALSE 3 (to 636)
630 POP_TOP

632 POP_EXCEPT
634 RERAISE 0

636 RERAISE 0
638 COPY 3
640 POP_EXCEPT
642 RERAISE 1

644 RERAISE 0
646 RERAISE 0
648 RERAISE 0
650 PUSH_EXC_INFO

652 LOAD_GLOBAL 30 (Exception)
654 CHECK_EXC_MATCH
656 POP_JUMP_FORWARD_IF_FALSE 3 (to 664)
658 POP_TOP

660 POP_EXCEPT
662 RERAISE 0

664 RERAISE 0
666 COPY 3
668 POP_EXCEPT
670 RERAISE 1
672 COPY 3
674 POP_EXCEPT
676 RERAISE 1


0 LOAD_GLOBAL 0 (os)
2 LOAD_ATTR 1 (path)
4 LOAD_METHOD 2 (splitext)
6 LOAD_FAST 1 (file_path)
8 CALL 1
10 UNPACK_SEQUENCE 2
12 STORE_FAST 2 (base)
14 STORE_FAST 3 (_)

16 LOAD_FAST 2 (base)
18 LOAD_CONST 1 ("_16kmono.wav")
20 BINARY_OP 0
22 STORE_FAST 4 (out_path)

24 NOP

26 LOAD_GLOBAL 7 (NULL + imageio_ffmpeg)
28 LOAD_ATTR 4 (get_ffmpeg_exe)
30 CALL 0
32 STORE_FAST 5 (ffmpeg_exe)

34 LOAD_FAST 5 (ffmpeg_exe)

36 LOAD_CONST 2 ("-y")
38 LOAD_CONST 3 ("-i")
40 LOAD_FAST 1 (file_path)

42 LOAD_CONST 4 ("-ac")

44 LOAD_CONST 5 ("1")
46 LOAD_CONST 6 ("-ar")

48 LOAD_CONST 7 ("16000")
50 LOAD_CONST 8 ("-acodec")

52 LOAD_CONST 9 ("pcm_s16le")
54 LOAD_FAST 4 (out_path)

56 BUILD_LIST 11
58 STORE_FAST 6 (cmd)

60 LOAD_GLOBAL 11 (NULL + getattr)
62 LOAD_GLOBAL 12 (subprocess)
64 LOAD_CONST 10 ("CREATE_NO_WINDOW")
66 LOAD_CONST 11 (0)
68 CALL 3
70 STORE_FAST 7 (creationflags)

72 LOAD_GLOBAL 13 (NULL + subprocess)
74 LOAD_ATTR 7 (run)

76 LOAD_FAST 6 (cmd)

78 LOAD_GLOBAL 12 (subprocess)
80 LOAD_ATTR 8 (DEVNULL)

82 LOAD_GLOBAL 12 (subprocess)
84 LOAD_ATTR 8 (DEVNULL)

86 LOAD_CONST 12 (True)

88 LOAD_FAST 7 (creationflags)

90 KW_NAMES 13 (('stdout', 'stderr', 'check', 'creationflags'))
92 CALL 5
94 POP_TOP

96 LOAD_GLOBAL 0 (os)
98 LOAD_ATTR 1 (path)
100 LOAD_METHOD 9 (exists)
102 LOAD_FAST 4 (out_path)
104 CALL 1
106 POP_JUMP_FORWARD_IF_FALSE 37 (to 128)
108 LOAD_GLOBAL 0 (os)
110 LOAD_ATTR 1 (path)
112 LOAD_METHOD 10 (getsize)
114 LOAD_FAST 4 (out_path)
116 CALL 1
118 LOAD_CONST 11 (0)
120 COMPARE_OP 4 (>)
122 POP_JUMP_FORWARD_IF_FALSE 2 (to 128)

124 LOAD_FAST 4 (out_path)
126 RETURN_VALUE

128 LOAD_GLOBAL 23 (NULL + RuntimeError)
130 LOAD_CONST 14 ("ffmpeg produced empty output")
132 CALL 1
134 RAISE_VARARGS 1 (exception instance)
136 PUSH_EXC_INFO

138 LOAD_GLOBAL 24 (Exception)
140 CHECK_EXC_MATCH
142 POP_JUMP_FORWARD_IF_FALSE 293 (to 372)
144 STORE_FAST 8 (e_ff)

146 LOAD_GLOBAL 26 (logger)
148 LOAD_METHOD 14 (warning)
150 LOAD_CONST 15 ("ffmpeg convert error: ")
152 LOAD_FAST 8 (e_ff)
154 FORMAT_VALUE 0
156 LOAD_CONST 16 (". Falling back to moviepy.")
158 BUILD_STRING 3
160 CALL 1
162 POP_TOP

164 NOP

166 LOAD_GLOBAL 31 (NULL + AudioFileClip)
168 LOAD_FAST 1 (file_path)
170 CALL 1
172 STORE_FAST 9 (clip)

174 NOP

176 LOAD_FAST 9 (clip)
178 LOAD_METHOD 16 (write_audiofile)
180 LOAD_FAST 4 (out_path)
182 LOAD_CONST 17 (16000)
184 LOAD_CONST 18 (2)
186 LOAD_CONST 9 ("pcm_s16le")
188 KW_NAMES 19 (('fps', 'nbytes', 'codec'))
190 CALL 4
192 POP_TOP

194 NOP

196 LOAD_FAST 9 (clip)
198 LOAD_METHOD 17 (close)
200 CALL 0
202 POP_TOP
204 JUMP_FORWARD 58 (to 270)
206 PUSH_EXC_INFO

208 LOAD_GLOBAL 24 (Exception)
210 CHECK_EXC_MATCH
212 POP_JUMP_FORWARD_IF_FALSE 3 (to 220)
214 POP_TOP

216 POP_EXCEPT
218 JUMP_FORWARD 46 (to 270)

220 RERAISE 0
222 COPY 3
224 POP_EXCEPT
226 RERAISE 1
228 PUSH_EXC_INFO

230 NOP

232 LOAD_FAST 9 (clip)
234 LOAD_METHOD 17 (close)
236 CALL 0
238 POP_TOP
240 RERAISE 0
242 PUSH_EXC_INFO

244 LOAD_GLOBAL 24 (Exception)
246 CHECK_EXC_MATCH
248 POP_JUMP_FORWARD_IF_FALSE 3 (to 256)
250 POP_TOP

252 POP_EXCEPT
254 RERAISE 0

256 RERAISE 0
258 COPY 3
260 POP_EXCEPT
262 RERAISE 1
264 COPY 3
266 POP_EXCEPT
268 RERAISE 1

270 LOAD_GLOBAL 0 (os)
272 LOAD_ATTR 1 (path)
274 LOAD_METHOD 9 (exists)
276 LOAD_FAST 4 (out_path)
278 CALL 1
280 POP_JUMP_FORWARD_IF_FALSE 42 (to 312)
282 LOAD_GLOBAL 0 (os)
284 LOAD_ATTR 1 (path)
286 LOAD_METHOD 10 (getsize)
288 LOAD_FAST 4 (out_path)
290 CALL 1
292 LOAD_CONST 11 (0)
294 COMPARE_OP 4 (>)
296 POP_JUMP_FORWARD_IF_FALSE 7 (to 312)

298 LOAD_FAST 4 (out_path)
300 SWAP 2
302 POP_EXCEPT
304 LOAD_CONST 20 (None)
306 STORE_FAST 8 (e_ff)
308 DELETE_FAST 8 (e_ff)
310 RETURN_VALUE

312 LOAD_GLOBAL 23 (NULL + RuntimeError)
314 LOAD_CONST 21 ("moviepy produced empty output")
316 CALL 1
318 RAISE_VARARGS 1 (exception instance)
320 PUSH_EXC_INFO

322 LOAD_GLOBAL 24 (Exception)
324 CHECK_EXC_MATCH
326 POP_JUMP_FORWARD_IF_FALSE 35 (to 356)
328 STORE_FAST 10 (e_mv)

330 LOAD_GLOBAL 26 (logger)
332 LOAD_METHOD 18 (error)
334 LOAD_CONST 22 ("moviepy fallback failed: ")
336 LOAD_FAST 10 (e_mv)
338 FORMAT_VALUE 0
340 BUILD_STRING 2
342 CALL 1
344 POP_TOP

346 RAISE_VARARGS 0 (reraise)
348 LOAD_CONST 20 (None)
350 STORE_FAST 10 (e_mv)
352 DELETE_FAST 10 (e_mv)
354 RERAISE 1

356 RERAISE 0
358 COPY 3
360 POP_EXCEPT
362 RERAISE 1
364 LOAD_CONST 20 (None)
366 STORE_FAST 8 (e_ff)
368 DELETE_FAST 8 (e_ff)
370 RERAISE 1

372 RERAISE 0
374 COPY 3
376 POP_EXCEPT
378 RERAISE 1


0 LOAD_FAST 1 (result)
2 JUMP_IF_TRUE_OR_POP 1 (to 6)
4 LOAD_CONST 1 ("")
6 LOAD_METHOD 0 (strip)
8 CALL 0
10 RETURN_VALUE