Python Code - Decompilation Success


0 SETUP_ANNOTATIONS
2 LOAD_CONST 0 ("\nConstants untuk aplikasi Auto Cloud Skill Registration\nGanti nilai sesuai kebutuhan sebelum build dengan Nuitka\n")
4 STORE_NAME 0 (__doc__)

6 LOAD_CONST 1 ("https://sinyormx.vercel.app")
8 STORE_NAME 1 (BASE_URL)
10 LOAD_NAME 2 (str)
12 LOAD_NAME 3 (__annotations__)
14 LOAD_CONST 2 ("BASE_URL")
16 STORE_SUBSCR

18 LOAD_CONST 3 ("accsb")
20 STORE_NAME 4 (PRODUCT_CODE)
22 LOAD_NAME 2 (str)
24 LOAD_NAME 3 (__annotations__)
26 LOAD_CONST 4 ("PRODUCT_CODE")
28 STORE_SUBSCR

30 LOAD_CONST 5 ("your_api_key_here")
32 STORE_NAME 5 (FIREFOX_RELAY_API_KEY)

34 LOAD_CONST 6 ("https://relay.firefox.com")
36 STORE_NAME 6 (FIREFOX_RELAY_PRODUCTION_URL)

38 LOAD_CONST 7 ("https://dev.fxprivaterelay.nonprod.cloudops.mozgcp.net")
40 STORE_NAME 7 (FIREFOX_RELAY_DEV_URL)

42 LOAD_NAME 6 (FIREFOX_RELAY_PRODUCTION_URL)
44 STORE_NAME 8 (FIREFOX_RELAY_BASE_URL)

46 LOAD_CONST 8 ("https://randomuser.me/api/")
48 STORE_NAME 9 (RANDOMUSER_API_URL)

50 LOAD_CONST 9 (False)
52 STORE_NAME 10 (DEBUG)

54 LOAD_CONST 10 (True)
56 STORE_NAME 11 (AUTO_SAVE_LOGS)

58 LOAD_CONST 9 (False)
60 STORE_NAME 12 (PLAYWRIGHT_HEADLESS)

62 LOAD_CONST 11 (30000)
64 STORE_NAME 13 (PLAYWRIGHT_TIMEOUT)

66 LOAD_CONST 12 ("https://www.cloudskillsboost.google/users/sign_up")
68 STORE_NAME 14 (CLOUDSKILL_REGISTER_URL)

70 LOAD_CONST 13 ("INFO")
72 STORE_NAME 15 (LOG_LEVEL)

74 LOAD_CONST 14 ("autocloudskill.log")
76 STORE_NAME 16 (LOG_FILE)

78 LOAD_CONST 15 ("female")
80 STORE_NAME 17 (DEFAULT_GENDER)

82 LOAD_CONST 16 ("gb,us,es")
84 STORE_NAME 18 (DEFAULT_NATIONALITIES)

86 LOAD_CONST 17 (12)
88 STORE_NAME 19 (DEFAULT_PASSWORD_LENGTH)

90 LOAD_CONST 18 ("Mozilla/5.0 (Windows NT 10.0; Win64; x64) AppleWebKit/537.36 (KHTML, like Gecko) Chrome/120.0.0.0 Safari/537.36")
92 STORE_NAME 20 (BROWSER_USER_AGENT)

94 LOAD_CONST 19 ("1.2.0")
96 STORE_NAME 21 (VERSION)

98 LOAD_CONST 20 ("Auto Cloud Skill")
100 STORE_NAME 22 (APP_NAME)

102 LOAD_CONST 21 ("SinyoRMX")
104 STORE_NAME 23 (AUTHOR)

106 LOAD_CONST 22 ("return")
108 LOAD_NAME 24 (bool)
110 BUILD_TUPLE 2
112 LOAD_CONST 23 (code object validate_config)
114 MAKE_FUNCTION 4 (annotation)
116 STORE_NAME 25 (validate_config)
118 LOAD_CONST 24 (None)
120 RETURN_VALUE


0 LOAD_CONST 1 (True)
2 RETURN_VALUE