Python Code - Decompilation Success


0 LOAD_CONST 0 ("\nKonfigurasi aplikasi - menggunakan constants untuk build dengan Nuitka\n")
2 STORE_NAME 0 (__doc__)

4 LOAD_CONST 1 (0)
6 LOAD_CONST 2 (('*',))
8 IMPORT_NAME 1 (config.constants)
10 IMPORT_STAR

12 PUSH_NULL
14 LOAD_BUILD_CLASS
16 LOAD_CONST 3 (code object Settings)
18 MAKE_FUNCTION 0 (No arguments)
20 LOAD_CONST 4 ("Settings")
22 CALL 2
24 STORE_NAME 2 (Settings)

26 PUSH_NULL
28 LOAD_NAME 2 (Settings)
30 CALL 0
32 STORE_NAME 3 (settings)
34 LOAD_CONST 5 (None)
36 RETURN_VALUE


0 LOAD_NAME 0 (__name__)
2 STORE_NAME 1 (__module__)
4 LOAD_CONST 0 ("Settings")
6 STORE_NAME 2 (__qualname__)

8 LOAD_CONST 1 ("Konfigurasi aplikasi menggunakan constants")
10 STORE_NAME 3 (__doc__)

12 LOAD_NAME 4 (FIREFOX_RELAY_API_KEY)
14 STORE_NAME 4 (FIREFOX_RELAY_API_KEY)

16 LOAD_NAME 5 (FIREFOX_RELAY_BASE_URL)
18 STORE_NAME 5 (FIREFOX_RELAY_BASE_URL)

20 LOAD_NAME 6 (RANDOMUSER_API_URL)
22 STORE_NAME 6 (RANDOMUSER_API_URL)

24 LOAD_NAME 7 (DEBUG)
26 STORE_NAME 7 (DEBUG)

28 LOAD_NAME 8 (AUTO_SAVE_LOGS)
30 STORE_NAME 8 (AUTO_SAVE_LOGS)

32 LOAD_NAME 9 (PLAYWRIGHT_HEADLESS)
34 STORE_NAME 9 (PLAYWRIGHT_HEADLESS)

36 LOAD_NAME 10 (PLAYWRIGHT_TIMEOUT)
38 STORE_NAME 10 (PLAYWRIGHT_TIMEOUT)

40 LOAD_NAME 11 (CLOUDSKILL_REGISTER_URL)
42 STORE_NAME 11 (CLOUDSKILL_REGISTER_URL)

44 LOAD_NAME 12 (LOG_LEVEL)
46 STORE_NAME 12 (LOG_LEVEL)

48 LOAD_NAME 13 (LOG_FILE)
50 STORE_NAME 13 (LOG_FILE)

52 LOAD_NAME 14 (DEFAULT_GENDER)
54 STORE_NAME 14 (DEFAULT_GENDER)

56 LOAD_NAME 15 (DEFAULT_NATIONALITIES)
58 STORE_NAME 15 (DEFAULT_NATIONALITIES)

60 LOAD_NAME 16 (DEFAULT_PASSWORD_LENGTH)
62 STORE_NAME 16 (DEFAULT_PASSWORD_LENGTH)

64 LOAD_NAME 17 (BROWSER_USER_AGENT)
66 STORE_NAME 17 (BROWSER_USER_AGENT)

68 LOAD_NAME 18 (VERSION)
70 STORE_NAME 18 (VERSION)

72 LOAD_NAME 19 (APP_NAME)
74 STORE_NAME 19 (APP_NAME)

76 LOAD_NAME 20 (AUTHOR)
78 STORE_NAME 20 (AUTHOR)

80 LOAD_NAME 21 (classmethod)

82 LOAD_CONST 2 ("return")
84 LOAD_NAME 22 (bool)
86 BUILD_TUPLE 2
88 LOAD_CONST 3 (code object validate_config)
90 MAKE_FUNCTION 4 (annotation)

92 CALL 0

94 STORE_NAME 23 (validate_config)

96 LOAD_NAME 21 (classmethod)

98 LOAD_CONST 2 ("return")
100 LOAD_NAME 24 (dict)
102 BUILD_TUPLE 2
104 LOAD_CONST 4 (code object get_browser_options)
106 MAKE_FUNCTION 4 (annotation)

108 CALL 0

110 STORE_NAME 25 (get_browser_options)
112 LOAD_CONST 5 (None)
114 RETURN_VALUE


0 LOAD_GLOBAL 1 (NULL + validate_config)
2 CALL 0
4 RETURN_VALUE


0 LOAD_GLOBAL 1 (NULL + get_browser_options)
2 CALL 0
4 RETURN_VALUE