Python Code - Decompilation Success

0 LOAD_CONST 0 ("\nMain entry point untuk aplikasi Auto Cloud Skill Registration\n")
2 STORE_NAME 0 (__doc__)

4 LOAD_CONST 1 (0)
6 LOAD_CONST 2 (None)
8 IMPORT_NAME 1 (sys)
10 STORE_NAME 1 (sys)

12 LOAD_CONST 1 (0)
14 LOAD_CONST 2 (None)
16 IMPORT_NAME 2 (os)
18 STORE_NAME 2 (os)

20 LOAD_CONST 1 (0)
22 LOAD_CONST 2 (None)
24 IMPORT_NAME 3 (traceback)
26 STORE_NAME 3 (traceback)

28 LOAD_CONST 1 (0)
30 LOAD_CONST 3 (('Path',))
32 IMPORT_NAME 4 (pathlib)
34 IMPORT_FROM 5 (Path)
36 STORE_NAME 5 (Path)
38 POP_TOP

40 PUSH_NULL
42 LOAD_NAME 5 (Path)
44 LOAD_NAME 6 (__file__)
46 CALL 1
48 LOAD_ATTR 7 (parent)
50 STORE_NAME 8 (project_root)

52 LOAD_NAME 1 (sys)
54 LOAD_ATTR 9 (path)
56 LOAD_METHOD 10 (insert)
58 LOAD_CONST 1 (0)
60 PUSH_NULL
62 LOAD_NAME 11 (str)
64 LOAD_NAME 8 (project_root)
66 CALL 1
68 CALL 2
70 POP_TOP

72 NOP

74 LOAD_CONST 1 (0)
76 LOAD_CONST 4 (('MainWindow',))
78 IMPORT_NAME 12 (gui.main_window)
80 IMPORT_FROM 13 (MainWindow)
82 STORE_NAME 13 (MainWindow)
84 POP_TOP

86 LOAD_CONST 1 (0)
88 LOAD_CONST 5 (('settings',))
90 IMPORT_NAME 14 (config.settings)
92 IMPORT_FROM 15 (settings)
94 STORE_NAME 15 (settings)
96 POP_TOP

98 LOAD_CONST 1 (0)
100 LOAD_CONST 6 (('setup_logger', 'main_logger'))
102 IMPORT_NAME 16 (utils.logger)
104 IMPORT_FROM 17 (setup_logger)
106 STORE_NAME 17 (setup_logger)
108 IMPORT_FROM 18 (main_logger)
110 STORE_NAME 18 (main_logger)
112 POP_TOP

114 LOAD_CONST 7 (code object main)
116 MAKE_FUNCTION 0 (No arguments)
118 STORE_NAME 19 (main)

120 LOAD_NAME 20 (__name__)
122 LOAD_CONST 8 ("__main__")
124 COMPARE_OP 2 (==)
126 POP_JUMP_FORWARD_IF_FALSE 26 (to 148)

128 PUSH_NULL
130 LOAD_NAME 1 (sys)
132 LOAD_ATTR 21 (exit)
134 PUSH_NULL
136 LOAD_NAME 19 (main)
138 CALL 0
140 CALL 1
142 POP_TOP
144 LOAD_CONST 2 (None)
146 RETURN_VALUE

148 LOAD_CONST 2 (None)
150 RETURN_VALUE
152 PUSH_EXC_INFO

154 LOAD_NAME 22 (ImportError)
156 CHECK_EXC_MATCH
158 POP_JUMP_FORWARD_IF_FALSE 85 (to 250)
160 STORE_NAME 23 (e)

162 PUSH_NULL
164 LOAD_NAME 24 (print)
166 LOAD_CONST 9 ("❌ Import error: ")
168 LOAD_NAME 23 (e)
170 FORMAT_VALUE 0
172 BUILD_STRING 2
174 CALL 1
176 POP_TOP

178 PUSH_NULL
180 LOAD_NAME 24 (print)
182 LOAD_CONST 10 ("\nPastikan semua dependencies sudah diinstall:")
184 CALL 1
186 POP_TOP

188 PUSH_NULL
190 LOAD_NAME 24 (print)
192 LOAD_CONST 11 ("pip install -r requirements.txt")
194 CALL 1
196 POP_TOP

198 PUSH_NULL
200 LOAD_NAME 24 (print)
202 LOAD_CONST 12 ("\nDan pastikan Playwright browser sudah diinstall:")
204 CALL 1
206 POP_TOP

208 PUSH_NULL
210 LOAD_NAME 24 (print)
212 LOAD_CONST 13 ("playwright install chromium")
214 CALL 1
216 POP_TOP

218 PUSH_NULL
220 LOAD_NAME 1 (sys)
222 LOAD_ATTR 21 (exit)
224 LOAD_CONST 14 (1)
226 CALL 1
228 POP_TOP
230 POP_EXCEPT
232 LOAD_CONST 2 (None)
234 STORE_NAME 23 (e)
236 DELETE_NAME 23 (e)
238 LOAD_CONST 2 (None)
240 RETURN_VALUE
242 LOAD_CONST 2 (None)
244 STORE_NAME 23 (e)
246 DELETE_NAME 23 (e)
248 RERAISE 1

250 LOAD_NAME 25 (Exception)
252 CHECK_EXC_MATCH
254 POP_JUMP_FORWARD_IF_FALSE 68 (to 328)
256 STORE_NAME 23 (e)

258 PUSH_NULL
260 LOAD_NAME 24 (print)
262 LOAD_CONST 15 ("❌ Fatal error: ")
264 LOAD_NAME 23 (e)
266 FORMAT_VALUE 0
268 BUILD_STRING 2
270 CALL 1
272 POP_TOP

274 PUSH_NULL
276 LOAD_NAME 24 (print)
278 LOAD_CONST 16 ("Traceback: ")
280 PUSH_NULL
282 LOAD_NAME 3 (traceback)
284 LOAD_ATTR 26 (format_exc)
286 CALL 0
288 FORMAT_VALUE 0
290 BUILD_STRING 2
292 CALL 1
294 POP_TOP

296 PUSH_NULL
298 LOAD_NAME 1 (sys)
300 LOAD_ATTR 21 (exit)
302 LOAD_CONST 14 (1)
304 CALL 1
306 POP_TOP
308 POP_EXCEPT
310 LOAD_CONST 2 (None)
312 STORE_NAME 23 (e)
314 DELETE_NAME 23 (e)
316 LOAD_CONST 2 (None)
318 RETURN_VALUE
320 LOAD_CONST 2 (None)
322 STORE_NAME 23 (e)
324 DELETE_NAME 23 (e)
326 RERAISE 1

328 RERAISE 0
330 COPY 3
332 POP_EXCEPT
334 RERAISE 1


0 LOAD_GLOBAL 1 (NULL + setup_logger)
2 LOAD_CONST 1 ("Main")
4 CALL 1
6 STORE_FAST 0 (logger)

8 NOP

10 LOAD_FAST 0 (logger)
12 LOAD_METHOD 1 (info)
14 LOAD_CONST 2 ("Starting Auto Cloud Skill Registration application")
16 CALL 1
18 POP_TOP

20 LOAD_FAST 0 (logger)
22 LOAD_METHOD 1 (info)
24 LOAD_CONST 3 ("Skipping config validation - API key will be input via GUI")
26 CALL 1
28 POP_TOP

30 LOAD_GLOBAL 5 (NULL + MainWindow)
32 CALL 0
34 STORE_FAST 1 (app)

36 LOAD_FAST 1 (app)
38 LOAD_METHOD 3 (run)
40 CALL 0
42 POP_TOP

44 LOAD_FAST 0 (logger)
46 LOAD_METHOD 1 (info)
48 LOAD_CONST 4 ("Application terminated normally")
50 CALL 1
52 POP_TOP

54 LOAD_CONST 5 (0)
56 RETURN_VALUE
58 PUSH_EXC_INFO

60 LOAD_GLOBAL 8 (KeyboardInterrupt)
62 CHECK_EXC_MATCH
64 POP_JUMP_FORWARD_IF_FALSE 25 (to 84)
66 POP_TOP

68 LOAD_FAST 0 (logger)
70 LOAD_METHOD 1 (info)
72 LOAD_CONST 6 ("Application interrupted by user")
74 CALL 1
76 POP_TOP

78 POP_EXCEPT
80 LOAD_CONST 5 (0)
82 RETURN_VALUE

84 LOAD_GLOBAL 10 (Exception)
86 CHECK_EXC_MATCH
88 POP_JUMP_FORWARD_IF_FALSE 109 (to 170)
90 STORE_FAST 2 (e)

92 LOAD_FAST 0 (logger)
94 LOAD_METHOD 6 (error)
96 LOAD_CONST 7 ("Unexpected error: ")
98 LOAD_FAST 2 (e)
100 FORMAT_VALUE 0
102 BUILD_STRING 2
104 CALL 1
106 POP_TOP

108 LOAD_FAST 0 (logger)
110 LOAD_METHOD 6 (error)
112 LOAD_CONST 8 ("Traceback: ")
114 LOAD_GLOBAL 15 (NULL + traceback)
116 LOAD_ATTR 8 (format_exc)
118 CALL 0
120 FORMAT_VALUE 0
122 BUILD_STRING 2
124 CALL 1
126 POP_TOP

128 LOAD_GLOBAL 19 (NULL + print)
130 LOAD_CONST 9 ("\n❌ Unexpected error: ")
132 LOAD_FAST 2 (e)
134 FORMAT_VALUE 0
136 BUILD_STRING 2
138 CALL 1
140 POP_TOP

142 LOAD_GLOBAL 19 (NULL + print)
144 LOAD_CONST 10 ("Check logs for more details.")
146 CALL 1
148 POP_TOP

150 POP_EXCEPT
152 LOAD_CONST 11 (None)
154 STORE_FAST 2 (e)
156 DELETE_FAST 2 (e)
158 LOAD_CONST 12 (1)
160 RETURN_VALUE
162 LOAD_CONST 11 (None)
164 STORE_FAST 2 (e)
166 DELETE_FAST 2 (e)
168 RERAISE 1

170 RERAISE 0
172 COPY 3
174 POP_EXCEPT
176 RERAISE 1