Sorry: IndentationError: unindent does not match any outer indentation level (indented_0.py, line 89)

<module>: Success: Equal

***<module>.start_lab: Failure: Compilation Error

***<module>.open_cloud_console: Failure: Compilation Error

***<module>.handle_gcloud_terms: Failure: Compilation Error

***<module>.enable_genai_and_create_api_key: Failure: Compilation Error





0 LOAD_CONST 0 ('\nFlow minimal untuk Start Lab:\n- Navigate ke lab_url\n- Klik "Start Lab" (by role exact/regex -> locator teks -> keyword scan)\n- Klik natural (tanpa force, tanpa evaluate JS)\n- Cek reCAPTCHA terlihat; jika ya, panggil handle_captcha()\n\nTambahan utilitas porting dari test_start_lab:\n- open_cloud_console\n- handle_gcloud_terms\n- enable_genai_and_create_api_key\n')
2 STORE_NAME 0 (__doc__)

4 LOAD_CONST 1 (0)
6 LOAD_CONST 2 (('Awaitable', 'Callable', 'Optional', 'Tuple'))
8 IMPORT_NAME 1 (typing)
10 IMPORT_FROM 2 (Awaitable)
12 STORE_NAME 2 (Awaitable)
14 IMPORT_FROM 3 (Callable)
16 STORE_NAME 3 (Callable)
18 IMPORT_FROM 4 (Optional)
20 STORE_NAME 4 (Optional)
22 IMPORT_FROM 5 (Tuple)
24 STORE_NAME 5 (Tuple)
26 POP_TOP

28 LOAD_CONST 1 (0)
30 LOAD_CONST 3 (None)
32 IMPORT_NAME 6 (re)
34 STORE_NAME 6 (re)

36 LOAD_CONST 1 (0)
38 LOAD_CONST 3 (None)
40 IMPORT_NAME 7 (asyncio)
42 STORE_NAME 7 (asyncio)

44 LOAD_CONST 1 (0)
46 LOAD_CONST 4 (('urlparse',))
48 IMPORT_NAME 8 (urllib.parse)
50 IMPORT_FROM 9 (urlparse)
52 STORE_NAME 9 (urlparse)
54 POP_TOP

56 LOAD_CONST 1 (0)
58 LOAD_CONST 5 (('Page', 'Browser', 'BrowserContext'))
60 IMPORT_NAME 10 (playwright.async_api)
62 IMPORT_FROM 11 (Page)
64 STORE_NAME 11 (Page)
66 IMPORT_FROM 12 (Browser)
68 STORE_NAME 12 (Browser)
70 IMPORT_FROM 13 (BrowserContext)
72 STORE_NAME 13 (BrowserContext)
74 POP_TOP

76 LOAD_CONST 1 (0)
78 LOAD_CONST 6 (('log_automation_step',))
80 IMPORT_NAME 14 (utils.logger)
82 IMPORT_FROM 15 (log_automation_step)
84 STORE_NAME 15 (log_automation_step)
86 POP_TOP

88 NOP

90 LOAD_CONST 24 ((True,))

92 LOAD_CONST 8 ("page")
94 LOAD_NAME 11 (Page)

96 LOAD_CONST 9 ("handle_captcha")
98 LOAD_NAME 3 (Callable)
100 BUILD_LIST 0
102 LOAD_NAME 2 (Awaitable)
104 LOAD_NAME 16 (bool)
106 BINARY_SUBSCR
108 BUILD_TUPLE 2
110 BINARY_SUBSCR

112 LOAD_CONST 10 ("lab_url")
114 LOAD_NAME 17 (str)

116 LOAD_CONST 11 ("wait_networkidle")
118 LOAD_NAME 16 (bool)

120 LOAD_CONST 12 ("return")
122 LOAD_NAME 18 (dict)

124 BUILD_TUPLE 10
126 LOAD_CONST 13 (code object start_lab)
128 MAKE_FUNCTION 5 (default, annotation)
130 STORE_NAME 19 (start_lab)

132 LOAD_CONST 25 ((400,))
134 LOAD_CONST 8 ("page")
136 LOAD_NAME 11 (Page)
138 LOAD_CONST 15 ("browser")
140 LOAD_NAME 12 (Browser)
142 LOAD_CONST 16 ("timeout_sec")
144 LOAD_NAME 20 (int)
146 LOAD_CONST 12 ("return")
148 LOAD_NAME 5 (Tuple)
150 LOAD_NAME 18 (dict)
152 LOAD_NAME 4 (Optional)
154 LOAD_NAME 13 (BrowserContext)
156 BINARY_SUBSCR
158 LOAD_NAME 4 (Optional)
160 LOAD_NAME 11 (Page)
162 BINARY_SUBSCR
164 BUILD_TUPLE 3
166 BINARY_SUBSCR
168 BUILD_TUPLE 8
170 LOAD_CONST 17 (code object open_cloud_console)
172 MAKE_FUNCTION 5 (default, annotation)
174 STORE_NAME 21 (open_cloud_console)

176 LOAD_CONST 26 ((120,))
178 LOAD_CONST 19 ("inc_page")
180 LOAD_NAME 4 (Optional)
182 LOAD_NAME 11 (Page)
184 BINARY_SUBSCR
186 LOAD_CONST 16 ("timeout_sec")
188 LOAD_NAME 20 (int)
190 LOAD_CONST 12 ("return")
192 LOAD_NAME 18 (dict)
194 BUILD_TUPLE 6
196 LOAD_CONST 20 (code object handle_gcloud_terms)
198 MAKE_FUNCTION 5 (default, annotation)
200 STORE_NAME 22 (handle_gcloud_terms)

202 LOAD_CONST 27 ((180,))
204 LOAD_CONST 19 ("inc_page")
206 LOAD_NAME 11 (Page)
208 LOAD_CONST 22 ("project_id")
210 LOAD_NAME 17 (str)
212 LOAD_CONST 16 ("timeout_sec")
214 LOAD_NAME 20 (int)
216 LOAD_CONST 12 ("return")
218 LOAD_NAME 18 (dict)
220 BUILD_TUPLE 8
222 LOAD_CONST 23 (code object enable_genai_and_create_api_key)
224 MAKE_FUNCTION 5 (default, annotation)
226 STORE_NAME 23 (enable_genai_and_create_api_key)

228 LOAD_NAME 21 (open_cloud_console)
230 STORE_NAME 24 (_open_cloud_console)

232 LOAD_NAME 22 (handle_gcloud_terms)
234 STORE_NAME 25 (_handle_gcloud_terms)

236 LOAD_NAME 23 (enable_genai_and_create_api_key)
238 STORE_NAME 26 (_enable_genai_and_create_api_key)
240 LOAD_CONST 3 (None)
242 RETURN_VALUE


0 RETURN_GENERATOR
2 POP_TOP

4 LOAD_GLOBAL 1 (NULL + log_automation_step)
6 LOAD_FAST 1 (logger)
8 LOAD_CONST 1 ("LAB_START")
10 LOAD_CONST 2 ("START")
12 LOAD_CONST 3 ("url")
14 LOAD_FAST 3 (lab_url)
16 BUILD_MAP 1
18 CALL 4
20 POP_TOP

22 LOAD_FAST 0 (page)
24 LOAD_METHOD 1 (goto)
26 LOAD_FAST 3 (lab_url)
28 CALL 1
30 GET_AWAITABLE 0
32 LOAD_CONST 4 (None)
34 SEND 3 (to 40)
36 YIELD_VALUE
38 JUMP_BACKWARD_NO_INTERRUPT 4 (to 34)
40 POP_TOP

42 LOAD_FAST 0 (page)
44 LOAD_METHOD 2 (wait_for_load_state)
46 LOAD_CONST 5 ("domcontentloaded")
48 CALL 1
50 GET_AWAITABLE 0
52 LOAD_CONST 4 (None)
54 SEND 3 (to 60)
56 YIELD_VALUE
58 JUMP_BACKWARD_NO_INTERRUPT 4 (to 54)
60 POP_TOP

62 LOAD_FAST 4 (wait_networkidle)
64 POP_JUMP_FORWARD_IF_FALSE 45 (to 112)

66 NOP

68 LOAD_FAST 0 (page)
70 LOAD_METHOD 2 (wait_for_load_state)
72 LOAD_CONST 6 ("networkidle")
74 CALL 1
76 GET_AWAITABLE 0
78 LOAD_CONST 4 (None)
80 SEND 3 (to 86)
82 YIELD_VALUE
84 JUMP_BACKWARD_NO_INTERRUPT 4 (to 80)
86 POP_TOP
88 JUMP_FORWARD 16 (to 112)
90 PUSH_EXC_INFO

92 LOAD_GLOBAL 6 (Exception)
94 CHECK_EXC_MATCH
96 POP_JUMP_FORWARD_IF_FALSE 3 (to 104)
98 POP_TOP

100 POP_EXCEPT
102 JUMP_FORWARD 4 (to 112)

104 RERAISE 0
106 COPY 3
108 POP_EXCEPT
110 RERAISE 1

112 LOAD_GLOBAL 1 (NULL + log_automation_step)
114 LOAD_FAST 1 (logger)
116 LOAD_CONST 1 ("LAB_START")
118 LOAD_CONST 7 ("NAVIGATED")
120 LOAD_CONST 3 ("url")
122 LOAD_FAST 0 (page)
124 LOAD_ATTR 4 (url)
126 BUILD_MAP 1
128 CALL 4
130 POP_TOP

132 BUILD_LIST 0
134 LOAD_CONST 8 (('Mulai Lab', 'Start Lab', 'Mulai lab', 'Start lab', 'MULAI LAB', 'START LAB', 'Begin Lab', 'Mulai', 'Start', 'Begin', 'Mulai Lab, dan Anda memiliki', 'Start Lab, and you have'))
136 LIST_EXTEND 1
138 STORE_FAST 5 (start_button_texts)

140 LOAD_CONST 9 (False)
142 STORE_FAST 6 (clicked)

144 LOAD_GLOBAL 11 (NULL + range)
146 LOAD_CONST 10 (3)
148 CALL 1
150 GET_ITER
152 FOR_ITER 749 (to 862)
154 STORE_FAST 7 (attempt)

156 LOAD_FAST 6 (clicked)
158 POP_JUMP_FORWARD_IF_FALSE 3 (to 164)

160 POP_TOP
162 JUMP_FORWARD 743 (to 862)

164 LOAD_FAST 7 (attempt)
166 LOAD_CONST 11 (0)
168 COMPARE_OP 4 (>)
170 POP_JUMP_FORWARD_IF_FALSE 68 (to 240)

172 LOAD_GLOBAL 1 (NULL + log_automation_step)
174 LOAD_FAST 1 (logger)
176 LOAD_CONST 1 ("LAB_START")
178 LOAD_CONST 12 ("RETRY_FIND_BUTTON")
180 LOAD_CONST 13 ("attempt")
182 LOAD_FAST 7 (attempt)
184 LOAD_CONST 14 (1)
186 BINARY_OP 0
188 BUILD_MAP 1
190 CALL 4
192 POP_TOP

194 NOP

196 LOAD_FAST 0 (page)
198 LOAD_METHOD 6 (wait_for_timeout)
200 LOAD_CONST 15 (2000)
202 CALL 1
204 GET_AWAITABLE 0
206 LOAD_CONST 4 (None)
208 SEND 3 (to 214)
210 YIELD_VALUE
212 JUMP_BACKWARD_NO_INTERRUPT 4 (to 208)
214 POP_TOP
216 JUMP_FORWARD 16 (to 240)
218 PUSH_EXC_INFO

220 LOAD_GLOBAL 6 (Exception)
222 CHECK_EXC_MATCH
224 POP_JUMP_FORWARD_IF_FALSE 3 (to 232)
226 POP_TOP

228 POP_EXCEPT
230 JUMP_FORWARD 4 (to 240)

232 RERAISE 0
234 COPY 3
236 POP_EXCEPT
238 RERAISE 1

240 LOAD_FAST 5 (start_button_texts)
242 GET_ITER
244 FOR_ITER 275 (to 478)
246 STORE_FAST 8 (text)

248 LOAD_FAST 6 (clicked)
250 POP_JUMP_FORWARD_IF_FALSE 3 (to 256)

252 POP_TOP
254 JUMP_FORWARD 269 (to 478)

256 NOP

258 LOAD_FAST 0 (page)
260 LOAD_METHOD 7 (get_by_role)
262 LOAD_CONST 16 ("button")
264 LOAD_FAST 8 (text)
266 KW_NAMES 17 (('name',))
268 CALL 2
270 STORE_FAST 9 (loc)

272 LOAD_FAST 9 (loc)
274 LOAD_METHOD 8 (is_visible)
276 LOAD_CONST 18 (1000)
278 KW_NAMES 19 (('timeout',))
280 CALL 1
282 GET_AWAITABLE 0
284 LOAD_CONST 4 (None)
286 SEND 3 (to 292)
288 YIELD_VALUE
290 JUMP_BACKWARD_NO_INTERRUPT 4 (to 286)
292 POP_JUMP_FORWARD_IF_FALSE 50 (to 338)

294 LOAD_FAST 9 (loc)
296 LOAD_METHOD 9 (click)
298 CALL 0
300 GET_AWAITABLE 0
302 LOAD_CONST 4 (None)
304 SEND 3 (to 310)
306 YIELD_VALUE
308 JUMP_BACKWARD_NO_INTERRUPT 4 (to 304)
310 POP_TOP

312 LOAD_CONST 20 (True)
314 STORE_FAST 6 (clicked)

316 LOAD_GLOBAL 1 (NULL + log_automation_step)
318 LOAD_FAST 1 (logger)
320 LOAD_CONST 1 ("LAB_START")
322 LOAD_CONST 21 ("BUTTON_CLICKED_ROLE")
324 LOAD_CONST 22 ("text")
326 LOAD_FAST 8 (text)
328 BUILD_MAP 1
330 CALL 4
332 POP_TOP

334 POP_TOP
336 JUMP_FORWARD 167 (to 478)

338 JUMP_FORWARD 16 (to 362)
340 PUSH_EXC_INFO

342 LOAD_GLOBAL 6 (Exception)
344 CHECK_EXC_MATCH
346 POP_JUMP_FORWARD_IF_FALSE 3 (to 354)
348 POP_TOP

350 POP_EXCEPT
352 JUMP_FORWARD 4 (to 362)

354 RERAISE 0
356 COPY 3
358 POP_EXCEPT
360 RERAISE 1

362 NOP

364 LOAD_FAST 0 (page)
366 LOAD_METHOD 7 (get_by_role)
368 LOAD_CONST 16 ("button")
370 LOAD_GLOBAL 21 (NULL + re)
372 LOAD_ATTR 11 (compile)
374 LOAD_FAST 8 (text)
376 LOAD_GLOBAL 20 (re)
378 LOAD_ATTR 12 (IGNORECASE)
380 CALL 2
382 KW_NAMES 17 (('name',))
384 CALL 2
386 STORE_FAST 9 (loc)

388 LOAD_FAST 9 (loc)
390 LOAD_METHOD 8 (is_visible)
392 LOAD_CONST 18 (1000)
394 KW_NAMES 19 (('timeout',))
396 CALL 1
398 GET_AWAITABLE 0
400 LOAD_CONST 4 (None)
402 SEND 3 (to 408)
404 YIELD_VALUE
406 JUMP_BACKWARD_NO_INTERRUPT 4 (to 402)
408 POP_JUMP_FORWARD_IF_FALSE 50 (to 454)

410 LOAD_FAST 9 (loc)
412 LOAD_METHOD 9 (click)
414 CALL 0
416 GET_AWAITABLE 0
418 LOAD_CONST 4 (None)
420 SEND 3 (to 426)
422 YIELD_VALUE
424 JUMP_BACKWARD_NO_INTERRUPT 4 (to 420)
426 POP_TOP

428 LOAD_CONST 20 (True)
430 STORE_FAST 6 (clicked)

432 LOAD_GLOBAL 1 (NULL + log_automation_step)
434 LOAD_FAST 1 (logger)
436 LOAD_CONST 1 ("LAB_START")
438 LOAD_CONST 23 ("BUTTON_CLICKED_ROLE_REGEX")
440 LOAD_CONST 22 ("text")
442 LOAD_FAST 8 (text)
444 BUILD_MAP 1
446 CALL 4
448 POP_TOP

450 POP_TOP
452 JUMP_FORWARD 19 (to 478)

454 JUMP_BACKWARD 260 (to 244)
456 PUSH_EXC_INFO

458 LOAD_GLOBAL 6 (Exception)
460 CHECK_EXC_MATCH
462 POP_JUMP_FORWARD_IF_FALSE 4 (to 470)
464 POP_TOP

466 POP_EXCEPT
468 JUMP_BACKWARD 273 (to 244)

470 RERAISE 0
472 COPY 3
474 POP_EXCEPT
476 RERAISE 1

478 LOAD_FAST 6 (clicked)
480 POP_JUMP_FORWARD_IF_FALSE 3 (to 486)

482 POP_TOP
484 JUMP_FORWARD 385 (to 862)

486 LOAD_FAST 5 (start_button_texts)
488 GET_ITER
490 FOR_ITER 126 (to 612)
492 STORE_FAST 8 (text)

494 LOAD_FAST 6 (clicked)
496 POP_JUMP_FORWARD_IF_FALSE 2 (to 502)

498 POP_TOP
500 JUMP_FORWARD 121 (to 612)

502 NOP

504 LOAD_FAST 0 (page)
506 LOAD_METHOD 13 (locator)
508 LOAD_CONST 24 ('button:has-text("')
510 LOAD_FAST 8 (text)
512 FORMAT_VALUE 0
514 LOAD_CONST 25 ('")')
516 BUILD_STRING 3
518 CALL 1
520 STORE_FAST 9 (loc)

522 LOAD_FAST 9 (loc)
524 LOAD_METHOD 8 (is_visible)
526 LOAD_CONST 18 (1000)
528 KW_NAMES 19 (('timeout',))
530 CALL 1
532 GET_AWAITABLE 0
534 LOAD_CONST 4 (None)
536 SEND 3 (to 542)
538 YIELD_VALUE
540 JUMP_BACKWARD_NO_INTERRUPT 4 (to 536)
542 POP_JUMP_FORWARD_IF_FALSE 50 (to 588)

544 LOAD_FAST 9 (loc)
546 LOAD_METHOD 9 (click)
548 CALL 0
550 GET_AWAITABLE 0
552 LOAD_CONST 4 (None)
554 SEND 3 (to 560)
556 YIELD_VALUE
558 JUMP_BACKWARD_NO_INTERRUPT 4 (to 554)
560 POP_TOP

562 LOAD_CONST 20 (True)
564 STORE_FAST 6 (clicked)

566 LOAD_GLOBAL 1 (NULL + log_automation_step)
568 LOAD_FAST 1 (logger)
570 LOAD_CONST 1 ("LAB_START")
572 LOAD_CONST 26 ("BUTTON_CLICKED_TEXT")
574 LOAD_CONST 22 ("text")
576 LOAD_FAST 8 (text)
578 BUILD_MAP 1
580 CALL 4
582 POP_TOP

584 POP_TOP
586 JUMP_FORWARD 17 (to 612)

588 JUMP_BACKWARD 111 (to 490)
590 PUSH_EXC_INFO

592 LOAD_GLOBAL 6 (Exception)
594 CHECK_EXC_MATCH
596 POP_JUMP_FORWARD_IF_FALSE 3 (to 604)
598 POP_TOP

600 POP_EXCEPT
602 JUMP_BACKWARD 123 (to 490)

604 RERAISE 0
606 COPY 3
608 POP_EXCEPT
610 RERAISE 1

612 LOAD_FAST 6 (clicked)
614 POP_JUMP_FORWARD_IF_FALSE 2 (to 620)

616 POP_TOP
618 JUMP_FORWARD 252 (to 862)

620 NOP

622 LOAD_FAST 0 (page)
624 LOAD_METHOD 13 (locator)
626 LOAD_CONST 16 ("button")
628 CALL 1
630 LOAD_METHOD 14 (all)
632 CALL 0
634 STORE_FAST 10 (buttons)

636 LOAD_FAST 10 (buttons)
638 GET_ITER
640 FOR_ITER 190 (to 838)
642 STORE_FAST 11 (btn)

644 LOAD_FAST 6 (clicked)
646 POP_JUMP_FORWARD_IF_FALSE 2 (to 652)

648 POP_TOP
650 JUMP_FORWARD 185 (to 838)

652 NOP

654 LOAD_FAST 11 (btn)
656 LOAD_METHOD 15 (text_content)
658 CALL 0
660 GET_AWAITABLE 0
662 LOAD_CONST 4 (None)
664 SEND 3 (to 670)
666 YIELD_VALUE
668 JUMP_BACKWARD_NO_INTERRUPT 4 (to 664)
670 JUMP_IF_TRUE_OR_POP 1 (to 674)
672 LOAD_CONST 27 ("")
674 LOAD_METHOD 16 (lower)
676 CALL 0
678 STORE_FAST 12 (btn_text)
680 JUMP_FORWARD 18 (to 708)
682 PUSH_EXC_INFO

684 LOAD_GLOBAL 6 (Exception)
686 CHECK_EXC_MATCH
688 POP_JUMP_FORWARD_IF_FALSE 5 (to 700)
690 POP_TOP

692 LOAD_CONST 27 ("")
694 STORE_FAST 12 (btn_text)
696 POP_EXCEPT
698 JUMP_FORWARD 4 (to 708)

700 RERAISE 0
702 COPY 3
704 POP_EXCEPT
706 RERAISE 1

708 LOAD_CONST 28 ("start")
710 LOAD_FAST 12 (btn_text)
712 CONTAINS_OP 0 (in)
714 POP_JUMP_FORWARD_IF_TRUE 4 (to 724)
716 LOAD_CONST 29 ("mulai")
718 LOAD_FAST 12 (btn_text)
720 CONTAINS_OP 0 (in)
722 POP_JUMP_FORWARD_IF_FALSE 110 (to 836)
724 LOAD_CONST 30 ("lab")
726 LOAD_FAST 12 (btn_text)
728 CONTAINS_OP 0 (in)
730 POP_JUMP_FORWARD_IF_FALSE 106 (to 836)

732 NOP

734 LOAD_FAST 11 (btn)
736 LOAD_METHOD 8 (is_visible)
738 CALL 0
740 GET_AWAITABLE 0
742 LOAD_CONST 4 (None)
744 SEND 3 (to 750)
746 YIELD_VALUE
748 JUMP_BACKWARD_NO_INTERRUPT 4 (to 744)
750 STORE_FAST 13 (vis)
752 JUMP_FORWARD 18 (to 780)
754 PUSH_EXC_INFO

756 LOAD_GLOBAL 6 (Exception)
758 CHECK_EXC_MATCH
760 POP_JUMP_FORWARD_IF_FALSE 5 (to 772)
762 POP_TOP

764 LOAD_CONST 9 (False)
766 STORE_FAST 13 (vis)
768 POP_EXCEPT
770 JUMP_FORWARD 4 (to 780)

772 RERAISE 0
774 COPY 3
776 POP_EXCEPT
778 RERAISE 1

780 LOAD_FAST 13 (vis)
782 POP_JUMP_FORWARD_IF_FALSE 58 (to 836)

784 LOAD_FAST 11 (btn)
786 LOAD_METHOD 9 (click)
788 CALL 0
790 GET_AWAITABLE 0
792 LOAD_CONST 4 (None)
794 SEND 3 (to 800)
796 YIELD_VALUE
798 JUMP_BACKWARD_NO_INTERRUPT 4 (to 794)
800 POP_TOP

802 LOAD_CONST 20 (True)
804 STORE_FAST 6 (clicked)

806 LOAD_GLOBAL 1 (NULL + log_automation_step)
808 LOAD_FAST 1 (logger)
810 LOAD_CONST 1 ("LAB_START")
812 LOAD_CONST 31 ("BUTTON_CLICKED_KEYWORD")
814 LOAD_CONST 22 ("text")
816 LOAD_FAST 12 (btn_text)
818 LOAD_CONST 4 (None)
820 LOAD_CONST 32 (50)
822 BUILD_SLICE 2
824 BINARY_SUBSCR
826 BUILD_MAP 1
828 CALL 4
830 POP_TOP

832 POP_TOP
834 JUMP_FORWARD 1 (to 838)
836 JUMP_BACKWARD 191 (to 640)
838 JUMP_BACKWARD 734 (to 152)
840 PUSH_EXC_INFO

842 LOAD_GLOBAL 6 (Exception)
844 CHECK_EXC_MATCH
846 POP_JUMP_FORWARD_IF_FALSE 4 (to 854)
848 POP_TOP

850 POP_EXCEPT
852 JUMP_BACKWARD 747 (to 152)

854 RERAISE 0
856 COPY 3
858 POP_EXCEPT
860 RERAISE 1

862 LOAD_FAST 6 (clicked)
864 POP_JUMP_FORWARD_IF_TRUE 5 (to 876)

866 LOAD_CONST 9 (False)
868 LOAD_CONST 33 ("Start Lab button not found")
870 LOAD_CONST 34 (('success', 'error'))
872 BUILD_CONST_KEY_MAP 2
874 RETURN_VALUE

876 LOAD_FAST 4 (wait_networkidle)
878 POP_JUMP_FORWARD_IF_FALSE 45 (to 926)

880 NOP

882 LOAD_FAST 0 (page)
884 LOAD_METHOD 2 (wait_for_load_state)
886 LOAD_CONST 6 ("networkidle")
888 CALL 1
890 GET_AWAITABLE 0
892 LOAD_CONST 4 (None)
894 SEND 3 (to 900)
896 YIELD_VALUE
898 JUMP_BACKWARD_NO_INTERRUPT 4 (to 894)
900 POP_TOP
902 JUMP_FORWARD 16 (to 926)
904 PUSH_EXC_INFO

906 LOAD_GLOBAL 6 (Exception)
908 CHECK_EXC_MATCH
910 POP_JUMP_FORWARD_IF_FALSE 3 (to 918)
912 POP_TOP

914 POP_EXCEPT
916 JUMP_FORWARD 4 (to 926)

918 RERAISE 0
920 COPY 3
922 POP_EXCEPT
924 RERAISE 1

926 LOAD_GLOBAL 1 (NULL + log_automation_step)
928 LOAD_FAST 1 (logger)
930 LOAD_CONST 1 ("LAB_START")
932 LOAD_CONST 35 ("BUTTON_CLICKED")
934 CALL 3
936 POP_TOP

938 NOP

940 LOAD_FAST 0 (page)
942 LOAD_METHOD 6 (wait_for_timeout)
944 LOAD_CONST 36 (3000)
946 CALL 1
948 GET_AWAITABLE 0
950 LOAD_CONST 4 (None)
952 SEND 3 (to 958)
954 YIELD_VALUE
956 JUMP_BACKWARD_NO_INTERRUPT 4 (to 952)
958 POP_TOP
960 JUMP_FORWARD 16 (to 984)
962 PUSH_EXC_INFO

964 LOAD_GLOBAL 6 (Exception)
966 CHECK_EXC_MATCH
968 POP_JUMP_FORWARD_IF_FALSE 3 (to 976)
970 POP_TOP

972 POP_EXCEPT
974 JUMP_FORWARD 4 (to 984)

976 RERAISE 0
978 COPY 3
980 POP_EXCEPT
982 RERAISE 1

984 LOAD_GLOBAL 1 (NULL + log_automation_step)
986 LOAD_FAST 1 (logger)
988 LOAD_CONST 37 ("RECAPTCHA")
990 LOAD_CONST 38 ("START_DETECTION")
992 CALL 3
994 POP_TOP

996 LOAD_CONST 9 (False)
998 STORE_FAST 14 (found_checkbox)

1000 LOAD_CONST 9 (False)
1002 STORE_FAST 15 (clicked_checkbox)

1004 LOAD_CONST 4 (None)
1006 STORE_FAST 16 (target_frame)

1008 NOP

1010 NOP

1012 LOAD_FAST 0 (page)
1014 LOAD_METHOD 13 (locator)
1016 LOAD_CONST 39 ("ql-lab-control-panel")
1018 CALL 1
1020 LOAD_METHOD 17 (scroll_into_view_if_needed)
1022 CALL 0
1024 GET_AWAITABLE 0
1026 LOAD_CONST 4 (None)
1028 SEND 3 (to 1034)
1030 YIELD_VALUE
1032 JUMP_BACKWARD_NO_INTERRUPT 4 (to 1028)
1034 POP_TOP
1036 JUMP_FORWARD 16 (to 1060)
1038 PUSH_EXC_INFO

1040 LOAD_GLOBAL 6 (Exception)
1042 CHECK_EXC_MATCH
1044 POP_JUMP_FORWARD_IF_FALSE 3 (to 1052)
1046 POP_TOP

1048 POP_EXCEPT
1050 JUMP_FORWARD 4 (to 1060)

1052 RERAISE 0
1054 COPY 3
1056 POP_EXCEPT
1058 RERAISE 1

1060 LOAD_FAST 0 (page)
1062 LOAD_METHOD 18 (frame_locator)
1064 LOAD_CONST 40 ("iframe[title*='reCAPTCHA'], iframe[title*='recaptcha']")
1066 CALL 1
1068 STORE_FAST 17 (fl)

1070 LOAD_FAST 17 (fl)
1072 LOAD_METHOD 13 (locator)
1074 LOAD_CONST 41 ("#recaptcha-anchor")
1076 CALL 1
1078 STORE_FAST 18 (anc)

1080 NOP

1082 LOAD_FAST 18 (anc)
1084 LOAD_METHOD 8 (is_visible)
1086 LOAD_CONST 42 (4000)
1088 KW_NAMES 19 (('timeout',))
1090 CALL 1
1092 GET_AWAITABLE 0
1094 LOAD_CONST 4 (None)
1096 SEND 3 (to 1102)
1098 YIELD_VALUE
1100 JUMP_BACKWARD_NO_INTERRUPT 4 (to 1096)
1102 POP_JUMP_FORWARD_IF_FALSE 68 (to 1174)

1104 LOAD_CONST 20 (True)
1106 STORE_FAST 14 (found_checkbox)

1108 NOP

1110 LOAD_FAST 18 (anc)
1112 LOAD_METHOD 9 (click)
1114 CALL 0
1116 GET_AWAITABLE 0
1118 LOAD_CONST 4 (None)
1120 SEND 3 (to 1126)
1122 YIELD_VALUE
1124 JUMP_BACKWARD_NO_INTERRUPT 4 (to 1120)
1126 POP_TOP

1128 LOAD_CONST 20 (True)
1130 STORE_FAST 15 (clicked_checkbox)

1132 LOAD_GLOBAL 1 (NULL + log_automation_step)
1134 LOAD_FAST 1 (logger)
1136 LOAD_CONST 1 ("LAB_START")
1138 LOAD_CONST 43 ("CAPTCHA_CHECKBOX_CLICKED")
1140 LOAD_CONST 44 ("via")
1142 LOAD_CONST 45 ("frame_locator")
1144 BUILD_MAP 1
1146 CALL 4
1148 POP_TOP
1150 JUMP_FORWARD 16 (to 1174)
1152 PUSH_EXC_INFO

1154 LOAD_GLOBAL 6 (Exception)
1156 CHECK_EXC_MATCH
1158 POP_JUMP_FORWARD_IF_FALSE 3 (to 1166)
1160 POP_TOP

1162 POP_EXCEPT
1164 JUMP_FORWARD 4 (to 1174)

1166 RERAISE 0
1168 COPY 3
1170 POP_EXCEPT
1172 RERAISE 1
1174 JUMP_FORWARD 16 (to 1198)
1176 PUSH_EXC_INFO

1178 LOAD_GLOBAL 6 (Exception)
1180 CHECK_EXC_MATCH
1182 POP_JUMP_FORWARD_IF_FALSE 3 (to 1190)
1184 POP_TOP

1186 POP_EXCEPT
1188 JUMP_FORWARD 4 (to 1198)

1190 RERAISE 0
1192 COPY 3
1194 POP_EXCEPT
1196 RERAISE 1
1198 JUMP_FORWARD 16 (to 1222)
1200 PUSH_EXC_INFO

1202 LOAD_GLOBAL 6 (Exception)
1204 CHECK_EXC_MATCH
1206 POP_JUMP_FORWARD_IF_FALSE 3 (to 1214)
1208 POP_TOP

1210 POP_EXCEPT
1212 JUMP_FORWARD 4 (to 1222)

1214 RERAISE 0
1216 COPY 3
1218 POP_EXCEPT
1220 RERAISE 1

1222 LOAD_FAST 15 (clicked_checkbox)
1224 POP_JUMP_FORWARD_IF_TRUE 596 (to 1852)

1226 NOP

1228 LOAD_CONST 46 (30)
1230 STORE_FAST 19 (tries)

1232 LOAD_GLOBAL 11 (NULL + range)
1234 LOAD_FAST 19 (tries)
1236 CALL 1
1238 GET_ITER
1240 FOR_ITER 139 (to 1408)
1242 STORE_FAST 20 (_)

1244 NOP

1246 LOAD_FAST 0 (page)
1248 LOAD_ATTR 19 (frames)
1250 GET_ITER
1252 FOR_ITER 61 (to 1326)
1254 STORE_FAST 21 (fr)

1256 NOP

1258 LOAD_FAST 21 (fr)
1260 LOAD_ATTR 4 (url)
1262 JUMP_IF_TRUE_OR_POP 1 (to 1266)
1264 LOAD_CONST 27 ("")
1266 LOAD_METHOD 16 (lower)
1268 CALL 0
1270 STORE_FAST 22 (url_lc)
1272 JUMP_FORWARD 18 (to 1300)
1274 PUSH_EXC_INFO

1276 LOAD_GLOBAL 6 (Exception)
1278 CHECK_EXC_MATCH
1280 POP_JUMP_FORWARD_IF_FALSE 5 (to 1292)
1282 POP_TOP

1284 LOAD_CONST 27 ("")
1286 STORE_FAST 22 (url_lc)
1288 POP_EXCEPT
1290 JUMP_FORWARD 4 (to 1300)

1292 RERAISE 0
1294 COPY 3
1296 POP_EXCEPT
1298 RERAISE 1

1300 LOAD_CONST 47 ("recaptcha")
1302 LOAD_FAST 22 (url_lc)
1304 CONTAINS_OP 0 (in)
1306 POP_JUMP_FORWARD_IF_FALSE 8 (to 1324)
1308 LOAD_CONST 48 ("/anchor")
1310 LOAD_FAST 22 (url_lc)
1312 CONTAINS_OP 0 (in)
1314 POP_JUMP_FORWARD_IF_FALSE 4 (to 1324)

1316 LOAD_FAST 21 (fr)
1318 STORE_FAST 16 (target_frame)

1320 POP_TOP
1322 JUMP_FORWARD 1 (to 1326)
1324 JUMP_BACKWARD 62 (to 1252)
1326 JUMP_FORWARD 18 (to 1354)
1328 PUSH_EXC_INFO

1330 LOAD_GLOBAL 6 (Exception)
1332 CHECK_EXC_MATCH
1334 POP_JUMP_FORWARD_IF_FALSE 5 (to 1346)
1336 POP_TOP

1338 LOAD_CONST 4 (None)
1340 STORE_FAST 16 (target_frame)
1342 POP_EXCEPT
1344 JUMP_FORWARD 4 (to 1354)

1346 RERAISE 0
1348 COPY 3
1350 POP_EXCEPT
1352 RERAISE 1

1354 LOAD_FAST 16 (target_frame)
1356 POP_JUMP_FORWARD_IF_FALSE 2 (to 1362)

1358 POP_TOP
1360 JUMP_FORWARD 45 (to 1408)

1362 NOP

1364 LOAD_FAST 0 (page)
1366 LOAD_METHOD 6 (wait_for_timeout)
1368 LOAD_CONST 49 (500)
1370 CALL 1
1372 GET_AWAITABLE 0
1374 LOAD_CONST 4 (None)
1376 SEND 3 (to 1382)
1378 YIELD_VALUE
1380 JUMP_BACKWARD_NO_INTERRUPT 4 (to 1376)
1382 POP_TOP
1384 JUMP_BACKWARD 124 (to 1240)
1386 PUSH_EXC_INFO

1388 LOAD_GLOBAL 6 (Exception)
1390 CHECK_EXC_MATCH
1392 POP_JUMP_FORWARD_IF_FALSE 3 (to 1400)
1394 POP_TOP

1396 POP_EXCEPT
1398 JUMP_BACKWARD 136 (to 1240)

1400 RERAISE 0
1402 COPY 3
1404 POP_EXCEPT
1406 RERAISE 1

1408 LOAD_FAST 16 (target_frame)
1410 POP_JUMP_FORWARD_IF_FALSE 418 (to 1828)

1412 NOP

1414 LOAD_FAST 16 (target_frame)
1416 LOAD_METHOD 13 (locator)
1418 LOAD_CONST 41 ("#recaptcha-anchor")
1420 CALL 1
1422 STORE_FAST 23 (anc2)

1424 LOAD_FAST 23 (anc2)
1426 LOAD_METHOD 8 (is_visible)
1428 LOAD_CONST 42 (4000)
1430 KW_NAMES 19 (('timeout',))
1432 CALL 1
1434 GET_AWAITABLE 0
1436 LOAD_CONST 4 (None)
1438 SEND 3 (to 1444)
1440 YIELD_VALUE
1442 JUMP_BACKWARD_NO_INTERRUPT 4 (to 1438)
1444 POP_JUMP_FORWARD_IF_FALSE 350 (to 1804)

1446 LOAD_CONST 20 (True)
1448 STORE_FAST 14 (found_checkbox)

1450 NOP

1452 LOAD_FAST 23 (anc2)
1454 LOAD_METHOD 9 (click)
1456 CALL 0
1458 GET_AWAITABLE 0
1460 LOAD_CONST 4 (None)
1462 SEND 3 (to 1468)
1464 YIELD_VALUE
1466 JUMP_BACKWARD_NO_INTERRUPT 4 (to 1462)
1468 POP_TOP
1470 JUMP_FORWARD 16 (to 1494)
1472 PUSH_EXC_INFO

1474 LOAD_GLOBAL 6 (Exception)
1476 CHECK_EXC_MATCH
1478 POP_JUMP_FORWARD_IF_FALSE 3 (to 1486)
1480 POP_TOP

1482 POP_EXCEPT
1484 JUMP_FORWARD 4 (to 1494)

1486 RERAISE 0
1488 COPY 3
1490 POP_EXCEPT
1492 RERAISE 1

1494 NOP

1496 NOP

1498 LOAD_FAST 16 (target_frame)
1500 LOAD_METHOD 13 (locator)
1502 LOAD_CONST 50 (".recaptcha-checkbox")
1504 CALL 1
1506 LOAD_METHOD 9 (click)
1508 LOAD_CONST 51 (1500)
1510 KW_NAMES 19 (('timeout',))
1512 CALL 1
1514 GET_AWAITABLE 0
1516 LOAD_CONST 4 (None)
1518 SEND 3 (to 1524)
1520 YIELD_VALUE
1522 JUMP_BACKWARD_NO_INTERRUPT 4 (to 1518)
1524 POP_TOP
1526 JUMP_FORWARD 81 (to 1604)
1528 PUSH_EXC_INFO

1530 LOAD_GLOBAL 6 (Exception)
1532 CHECK_EXC_MATCH
1534 POP_JUMP_FORWARD_IF_FALSE 68 (to 1596)
1536 POP_TOP

1538 NOP

1540 LOAD_FAST 16 (target_frame)
1542 LOAD_METHOD 13 (locator)
1544 LOAD_CONST 52 (".recaptcha-checkbox-border")
1546 CALL 1
1548 LOAD_METHOD 9 (click)
1550 LOAD_CONST 51 (1500)
1552 KW_NAMES 19 (('timeout',))
1554 CALL 1
1556 GET_AWAITABLE 0
1558 LOAD_CONST 4 (None)
1560 SEND 3 (to 1566)
1562 YIELD_VALUE
1564 JUMP_BACKWARD_NO_INTERRUPT 4 (to 1560)
1566 POP_TOP
1568 JUMP_FORWARD 16 (to 1592)
1570 PUSH_EXC_INFO

1572 LOAD_GLOBAL 6 (Exception)
1574 CHECK_EXC_MATCH
1576 POP_JUMP_FORWARD_IF_FALSE 3 (to 1584)
1578 POP_TOP

1580 POP_EXCEPT
1582 JUMP_FORWARD 4 (to 1592)

1584 RERAISE 0
1586 COPY 3
1588 POP_EXCEPT
1590 RERAISE 1
1592 POP_EXCEPT
1594 JUMP_FORWARD 4 (to 1604)

1596 RERAISE 0
1598 COPY 3
1600 POP_EXCEPT
1602 RERAISE 1

1604 NOP

1606 LOAD_FAST 23 (anc2)
1608 LOAD_METHOD 20 (get_attribute)
1610 LOAD_CONST 53 ("aria-checked")
1612 CALL 1
1614 GET_AWAITABLE 0
1616 LOAD_CONST 4 (None)
1618 SEND 3 (to 1624)
1620 YIELD_VALUE
1622 JUMP_BACKWARD_NO_INTERRUPT 4 (to 1618)
1624 STORE_FAST 24 (checked)
1626 JUMP_FORWARD 18 (to 1654)
1628 PUSH_EXC_INFO

1630 LOAD_GLOBAL 6 (Exception)
1632 CHECK_EXC_MATCH
1634 POP_JUMP_FORWARD_IF_FALSE 5 (to 1646)
1636 POP_TOP

1638 LOAD_CONST 4 (None)
1640 STORE_FAST 24 (checked)
1642 POP_EXCEPT
1644 JUMP_FORWARD 4 (to 1654)

1646 RERAISE 0
1648 COPY 3
1650 POP_EXCEPT
1652 RERAISE 1

1654 LOAD_CONST 9 (False)
1656 STORE_FAST 25 (challenge_open)

1658 NOP

1660 LOAD_FAST 16 (target_frame)
1662 LOAD_ATTR 21 (page)
1664 LOAD_ATTR 19 (frames)
1666 GET_ITER
1668 FOR_ITER 61 (to 1742)
1670 STORE_FAST 26 (fr2)

1672 NOP

1674 LOAD_FAST 26 (fr2)
1676 LOAD_ATTR 4 (url)
1678 JUMP_IF_TRUE_OR_POP 1 (to 1682)
1680 LOAD_CONST 27 ("")
1682 LOAD_METHOD 16 (lower)
1684 CALL 0
1686 STORE_FAST 27 (u2)
1688 JUMP_FORWARD 18 (to 1716)
1690 PUSH_EXC_INFO

1692 LOAD_GLOBAL 6 (Exception)
1694 CHECK_EXC_MATCH
1696 POP_JUMP_FORWARD_IF_FALSE 5 (to 1708)
1698 POP_TOP

1700 LOAD_CONST 27 ("")
1702 STORE_FAST 27 (u2)
1704 POP_EXCEPT
1706 JUMP_FORWARD 4 (to 1716)

1708 RERAISE 0
1710 COPY 3
1712 POP_EXCEPT
1714 RERAISE 1

1716 LOAD_CONST 47 ("recaptcha")
1718 LOAD_FAST 27 (u2)
1720 CONTAINS_OP 0 (in)
1722 POP_JUMP_FORWARD_IF_FALSE 8 (to 1740)
1724 LOAD_CONST 54 ("/bframe")
1726 LOAD_FAST 27 (u2)
1728 CONTAINS_OP 0 (in)
1730 POP_JUMP_FORWARD_IF_FALSE 4 (to 1740)

1732 LOAD_CONST 20 (True)
1734 STORE_FAST 25 (challenge_open)

1736 POP_TOP
1738 JUMP_FORWARD 1 (to 1742)
1740 JUMP_BACKWARD 62 (to 1668)
1742 JUMP_FORWARD 18 (to 1770)
1744 PUSH_EXC_INFO

1746 LOAD_GLOBAL 6 (Exception)
1748 CHECK_EXC_MATCH
1750 POP_JUMP_FORWARD_IF_FALSE 5 (to 1762)
1752 POP_TOP

1754 LOAD_CONST 9 (False)
1756 STORE_FAST 25 (challenge_open)
1758 POP_EXCEPT
1760 JUMP_FORWARD 4 (to 1770)

1762 RERAISE 0
1764 COPY 3
1766 POP_EXCEPT
1768 RERAISE 1

1770 LOAD_FAST 24 (checked)
1772 LOAD_CONST 55 ("true")
1774 COMPARE_OP 2 (==)
1776 POP_JUMP_FORWARD_IF_TRUE 2 (to 1782)
1778 LOAD_FAST 25 (challenge_open)
1780 POP_JUMP_FORWARD_IF_FALSE 22 (to 1804)

1782 LOAD_CONST 20 (True)
1784 STORE_FAST 15 (clicked_checkbox)

1786 LOAD_GLOBAL 1 (NULL + log_automation_step)
1788 LOAD_FAST 1 (logger)
1790 LOAD_CONST 1 ("LAB_START")
1792 LOAD_CONST 43 ("CAPTCHA_CHECKBOX_CLICKED")
1794 LOAD_CONST 44 ("via")
1796 LOAD_CONST 56 ("anchor_frame")
1798 BUILD_MAP 1
1800 CALL 4
1802 POP_TOP
1804 JUMP_FORWARD 16 (to 1828)
1806 PUSH_EXC_INFO

1808 LOAD_GLOBAL 6 (Exception)
1810 CHECK_EXC_MATCH
1812 POP_JUMP_FORWARD_IF_FALSE 3 (to 1820)
1814 POP_TOP

1816 POP_EXCEPT
1818 JUMP_FORWARD 4 (to 1828)

1820 RERAISE 0
1822 COPY 3
1824 POP_EXCEPT
1826 RERAISE 1
1828 JUMP_FORWARD 16 (to 1852)
1830 PUSH_EXC_INFO

1832 LOAD_GLOBAL 6 (Exception)
1834 CHECK_EXC_MATCH
1836 POP_JUMP_FORWARD_IF_FALSE 3 (to 1844)
1838 POP_TOP

1840 POP_EXCEPT
1842 JUMP_FORWARD 4 (to 1852)

1844 RERAISE 0
1846 COPY 3
1848 POP_EXCEPT
1850 RERAISE 1

1852 LOAD_FAST 15 (clicked_checkbox)
1854 POP_JUMP_FORWARD_IF_TRUE 620 (to 2470)

1856 NOP

1858 LOAD_FAST 0 (page)
1860 LOAD_ATTR 19 (frames)
1862 GET_ITER
1864 FOR_ITER 593 (to 2446)
1866 STORE_FAST 21 (fr)

1868 NOP

1870 LOAD_FAST 21 (fr)
1872 LOAD_ATTR 4 (url)
1874 JUMP_IF_TRUE_OR_POP 1 (to 1878)
1876 LOAD_CONST 27 ("")
1878 LOAD_METHOD 16 (lower)
1880 CALL 0
1882 STORE_FAST 28 (url)
1884 JUMP_FORWARD 18 (to 1912)
1886 PUSH_EXC_INFO

1888 LOAD_GLOBAL 6 (Exception)
1890 CHECK_EXC_MATCH
1892 POP_JUMP_FORWARD_IF_FALSE 5 (to 1904)
1894 POP_TOP

1896 LOAD_CONST 27 ("")
1898 STORE_FAST 28 (url)
1900 POP_EXCEPT
1902 JUMP_FORWARD 4 (to 1912)

1904 RERAISE 0
1906 COPY 3
1908 POP_EXCEPT
1910 RERAISE 1

1912 LOAD_CONST 47 ("recaptcha")
1914 LOAD_FAST 28 (url)
1916 CONTAINS_OP 1 (not in)
1918 POP_JUMP_FORWARD_IF_FALSE 1 (to 1922)

1920 JUMP_BACKWARD 55 (to 1864)

1922 NOP

1924 LOAD_FAST 21 (fr)
1926 LOAD_METHOD 13 (locator)
1928 LOAD_CONST 41 ("#recaptcha-anchor")
1930 CALL 1
1932 STORE_FAST 29 (anc3)

1934 LOAD_FAST 29 (anc3)
1936 LOAD_METHOD 8 (is_visible)
1938 LOAD_CONST 15 (2000)
1940 KW_NAMES 19 (('timeout',))
1942 CALL 1
1944 GET_AWAITABLE 0
1946 LOAD_CONST 4 (None)
1948 SEND 3 (to 1954)
1950 YIELD_VALUE
1952 JUMP_BACKWARD_NO_INTERRUPT 4 (to 1948)
1954 POP_JUMP_FORWARD_IF_FALSE 351 (to 2316)

1956 LOAD_CONST 20 (True)
1958 STORE_FAST 14 (found_checkbox)

1960 NOP

1962 LOAD_FAST 29 (anc3)
1964 LOAD_METHOD 9 (click)
1966 CALL 0
1968 GET_AWAITABLE 0
1970 LOAD_CONST 4 (None)
1972 SEND 3 (to 1978)
1974 YIELD_VALUE
1976 JUMP_BACKWARD_NO_INTERRUPT 4 (to 1972)
1978 POP_TOP
1980 JUMP_FORWARD 16 (to 2004)
1982 PUSH_EXC_INFO

1984 LOAD_GLOBAL 6 (Exception)
1986 CHECK_EXC_MATCH
1988 POP_JUMP_FORWARD_IF_FALSE 3 (to 1996)
1990 POP_TOP

1992 POP_EXCEPT
1994 JUMP_FORWARD 4 (to 2004)

1996 RERAISE 0
1998 COPY 3
2000 POP_EXCEPT
2002 RERAISE 1

2004 NOP

2006 LOAD_FAST 21 (fr)
2008 LOAD_METHOD 13 (locator)
2010 LOAD_CONST 50 (".recaptcha-checkbox")
2012 CALL 1
2014 LOAD_METHOD 9 (click)
2016 LOAD_CONST 51 (1500)
2018 KW_NAMES 19 (('timeout',))
2020 CALL 1
2022 GET_AWAITABLE 0
2024 LOAD_CONST 4 (None)
2026 SEND 3 (to 2032)
2028 YIELD_VALUE
2030 JUMP_BACKWARD_NO_INTERRUPT 4 (to 2026)
2032 POP_TOP
2034 JUMP_FORWARD 81 (to 2112)
2036 PUSH_EXC_INFO

2038 LOAD_GLOBAL 6 (Exception)
2040 CHECK_EXC_MATCH
2042 POP_JUMP_FORWARD_IF_FALSE 68 (to 2104)
2044 POP_TOP

2046 NOP

2048 LOAD_FAST 21 (fr)
2050 LOAD_METHOD 13 (locator)
2052 LOAD_CONST 52 (".recaptcha-checkbox-border")
2054 CALL 1
2056 LOAD_METHOD 9 (click)
2058 LOAD_CONST 51 (1500)
2060 KW_NAMES 19 (('timeout',))
2062 CALL 1
2064 GET_AWAITABLE 0
2066 LOAD_CONST 4 (None)
2068 SEND 3 (to 2074)
2070 YIELD_VALUE
2072 JUMP_BACKWARD_NO_INTERRUPT 4 (to 2068)
2074 POP_TOP
2076 JUMP_FORWARD 16 (to 2100)
2078 PUSH_EXC_INFO

2080 LOAD_GLOBAL 6 (Exception)
2082 CHECK_EXC_MATCH
2084 POP_JUMP_FORWARD_IF_FALSE 3 (to 2092)
2086 POP_TOP

2088 POP_EXCEPT
2090 JUMP_FORWARD 4 (to 2100)

2092 RERAISE 0
2094 COPY 3
2096 POP_EXCEPT
2098 RERAISE 1
2100 POP_EXCEPT
2102 JUMP_FORWARD 4 (to 2112)

2104 RERAISE 0
2106 COPY 3
2108 POP_EXCEPT
2110 RERAISE 1

2112 NOP

2114 LOAD_FAST 29 (anc3)
2116 LOAD_METHOD 20 (get_attribute)
2118 LOAD_CONST 53 ("aria-checked")
2120 CALL 1
2122 GET_AWAITABLE 0
2124 LOAD_CONST 4 (None)
2126 SEND 3 (to 2132)
2128 YIELD_VALUE
2130 JUMP_BACKWARD_NO_INTERRUPT 4 (to 2126)
2132 STORE_FAST 24 (checked)
2134 JUMP_FORWARD 18 (to 2162)
2136 PUSH_EXC_INFO

2138 LOAD_GLOBAL 6 (Exception)
2140 CHECK_EXC_MATCH
2142 POP_JUMP_FORWARD_IF_FALSE 5 (to 2154)
2144 POP_TOP

2146 LOAD_CONST 4 (None)
2148 STORE_FAST 24 (checked)
2150 POP_EXCEPT
2152 JUMP_FORWARD 4 (to 2162)

2154 RERAISE 0
2156 COPY 3
2158 POP_EXCEPT
2160 RERAISE 1

2162 LOAD_CONST 9 (False)
2164 STORE_FAST 25 (challenge_open)

2166 NOP

2168 LOAD_FAST 21 (fr)
2170 LOAD_ATTR 21 (page)
2172 LOAD_ATTR 19 (frames)
2174 GET_ITER
2176 FOR_ITER 61 (to 2250)
2178 STORE_FAST 26 (fr2)

2180 NOP

2182 LOAD_FAST 26 (fr2)
2184 LOAD_ATTR 4 (url)
2186 JUMP_IF_TRUE_OR_POP 1 (to 2190)
2188 LOAD_CONST 27 ("")
2190 LOAD_METHOD 16 (lower)
2192 CALL 0
2194 STORE_FAST 27 (u2)
2196 JUMP_FORWARD 18 (to 2224)
2198 PUSH_EXC_INFO

2200 LOAD_GLOBAL 6 (Exception)
2202 CHECK_EXC_MATCH
2204 POP_JUMP_FORWARD_IF_FALSE 5 (to 2216)
2206 POP_TOP

2208 LOAD_CONST 27 ("")
2210 STORE_FAST 27 (u2)
2212 POP_EXCEPT
2214 JUMP_FORWARD 4 (to 2224)

2216 RERAISE 0
2218 COPY 3
2220 POP_EXCEPT
2222 RERAISE 1

2224 LOAD_CONST 47 ("recaptcha")
2226 LOAD_FAST 27 (u2)
2228 CONTAINS_OP 0 (in)
2230 POP_JUMP_FORWARD_IF_FALSE 8 (to 2248)
2232 LOAD_CONST 54 ("/bframe")
2234 LOAD_FAST 27 (u2)
2236 CONTAINS_OP 0 (in)
2238 POP_JUMP_FORWARD_IF_FALSE 4 (to 2248)

2240 LOAD_CONST 20 (True)
2242 STORE_FAST 25 (challenge_open)

2244 POP_TOP
2246 JUMP_FORWARD 1 (to 2250)
2248 JUMP_BACKWARD 62 (to 2176)
2250 JUMP_FORWARD 18 (to 2278)
2252 PUSH_EXC_INFO

2254 LOAD_GLOBAL 6 (Exception)
2256 CHECK_EXC_MATCH
2258 POP_JUMP_FORWARD_IF_FALSE 5 (to 2270)
2260 POP_TOP

2262 LOAD_CONST 9 (False)
2264 STORE_FAST 25 (challenge_open)
2266 POP_EXCEPT
2268 JUMP_FORWARD 4 (to 2278)

2270 RERAISE 0
2272 COPY 3
2274 POP_EXCEPT
2276 RERAISE 1

2278 LOAD_FAST 24 (checked)
2280 LOAD_CONST 55 ("true")
2282 COMPARE_OP 2 (==)
2284 POP_JUMP_FORWARD_IF_TRUE 2 (to 2290)
2286 LOAD_FAST 25 (challenge_open)
2288 POP_JUMP_FORWARD_IF_FALSE 24 (to 2316)

2290 LOAD_CONST 20 (True)
2292 STORE_FAST 15 (clicked_checkbox)

2294 LOAD_GLOBAL 1 (NULL + log_automation_step)
2296 LOAD_FAST 1 (logger)
2298 LOAD_CONST 1 ("LAB_START")
2300 LOAD_CONST 43 ("CAPTCHA_CHECKBOX_CLICKED")
2302 LOAD_CONST 44 ("via")
2304 LOAD_CONST 57 ("frame_anchor_fallback")
2306 BUILD_MAP 1
2308 CALL 4
2310 POP_TOP

2312 POP_TOP
2314 JUMP_FORWARD 138 (to 2446)
2316 JUMP_FORWARD 16 (to 2340)
2318 PUSH_EXC_INFO

2320 LOAD_GLOBAL 6 (Exception)
2322 CHECK_EXC_MATCH
2324 POP_JUMP_FORWARD_IF_FALSE 3 (to 2332)
2326 POP_TOP

2328 POP_EXCEPT
2330 JUMP_FORWARD 4 (to 2340)

2332 RERAISE 0
2334 COPY 3
2336 POP_EXCEPT
2338 RERAISE 1

2340 NOP

2342 LOAD_FAST 21 (fr)
2344 LOAD_METHOD 22 (get_by_label)
2346 LOAD_CONST 58 ("I'm not a robot")
2348 CALL 1
2350 STORE_FAST 30 (cb)

2352 LOAD_FAST 30 (cb)
2354 LOAD_METHOD 8 (is_visible)
2356 LOAD_CONST 15 (2000)
2358 KW_NAMES 19 (('timeout',))
2360 CALL 1
2362 GET_AWAITABLE 0
2364 LOAD_CONST 4 (None)
2366 SEND 3 (to 2372)
2368 YIELD_VALUE
2370 JUMP_BACKWARD_NO_INTERRUPT 4 (to 2366)
2372 POP_JUMP_FORWARD_IF_FALSE 52 (to 2422)

2374 LOAD_CONST 20 (True)
2376 STORE_FAST 14 (found_checkbox)

2378 LOAD_FAST 30 (cb)
2380 LOAD_METHOD 9 (click)
2382 CALL 0
2384 GET_AWAITABLE 0
2386 LOAD_CONST 4 (None)
2388 SEND 3 (to 2394)
2390 YIELD_VALUE
2392 JUMP_BACKWARD_NO_INTERRUPT 4 (to 2388)
2394 POP_TOP

2396 LOAD_CONST 20 (True)
2398 STORE_FAST 15 (clicked_checkbox)

2400 LOAD_GLOBAL 1 (NULL + log_automation_step)
2402 LOAD_FAST 1 (logger)
2404 LOAD_CONST 1 ("LAB_START")
2406 LOAD_CONST 43 ("CAPTCHA_CHECKBOX_CLICKED")
2408 LOAD_CONST 44 ("via")
2410 LOAD_CONST 59 ("frame_label_fallback")
2412 BUILD_MAP 1
2414 CALL 4
2416 POP_TOP

2418 POP_TOP
2420 JUMP_FORWARD 19 (to 2446)

2422 JUMP_BACKWARD 578 (to 1864)
2424 PUSH_EXC_INFO

2426 LOAD_GLOBAL 6 (Exception)
2428 CHECK_EXC_MATCH
2430 POP_JUMP_FORWARD_IF_FALSE 4 (to 2438)
2432 POP_TOP

2434 POP_EXCEPT
2436 JUMP_BACKWARD 591 (to 1864)

2438 RERAISE 0
2440 COPY 3
2442 POP_EXCEPT
2444 RERAISE 1
2446 JUMP_FORWARD 16 (to 2470)
2448 PUSH_EXC_INFO

2450 LOAD_GLOBAL 6 (Exception)
2452 CHECK_EXC_MATCH
2454 POP_JUMP_FORWARD_IF_FALSE 3 (to 2462)
2456 POP_TOP

2458 POP_EXCEPT
2460 JUMP_FORWARD 4 (to 2470)

2462 RERAISE 0
2464 COPY 3
2466 POP_EXCEPT
2468 RERAISE 1

2470 LOAD_FAST 14 (found_checkbox)
2472 POP_JUMP_FORWARD_IF_FALSE 24 (to 2500)
2474 LOAD_FAST 15 (clicked_checkbox)
2476 POP_JUMP_FORWARD_IF_TRUE 22 (to 2500)

2478 LOAD_GLOBAL 1 (NULL + log_automation_step)
2480 LOAD_FAST 1 (logger)
2482 LOAD_CONST 1 ("LAB_START")
2484 LOAD_CONST 60 ("CAPTCHA_CHECKBOX_NOT_CLICKED")
2486 CALL 3
2488 POP_TOP

2490 LOAD_CONST 9 (False)
2492 LOAD_CONST 61 ("reCAPTCHA checkbox detected but could not be clicked")
2494 LOAD_CONST 34 (('success', 'error'))
2496 BUILD_CONST_KEY_MAP 2
2498 RETURN_VALUE

2500 LOAD_FAST 15 (clicked_checkbox)
2502 POP_JUMP_FORWARD_IF_FALSE 125 (to 2642)

2504 LOAD_CONST 9 (False)
2506 STORE_FAST 31 (ok)

2508 NOP

2510 PUSH_NULL
2512 LOAD_FAST 2 (handle_captcha)
2514 CALL 0
2516 GET_AWAITABLE 0
2518 LOAD_CONST 4 (None)
2520 SEND 3 (to 2526)
2522 YIELD_VALUE
2524 JUMP_BACKWARD_NO_INTERRUPT 4 (to 2520)
2526 STORE_FAST 31 (ok)
2528 JUMP_FORWARD 64 (to 2604)
2530 PUSH_EXC_INFO

2532 LOAD_GLOBAL 6 (Exception)
2534 CHECK_EXC_MATCH
2536 POP_JUMP_FORWARD_IF_FALSE 51 (to 2596)
2538 STORE_FAST 32 (e)

2540 LOAD_GLOBAL 1 (NULL + log_automation_step)
2542 LOAD_FAST 1 (logger)
2544 LOAD_CONST 1 ("LAB_START")
2546 LOAD_CONST 62 ("CAPTCHA_ERROR")
2548 LOAD_CONST 63 ("error")
2550 LOAD_GLOBAL 47 (NULL + str)
2552 LOAD_FAST 32 (e)
2554 CALL 1
2556 BUILD_MAP 1
2558 CALL 4
2560 POP_TOP

2562 LOAD_CONST 9 (False)
2564 LOAD_CONST 64 ("Captcha handler error: ")
2566 LOAD_FAST 32 (e)
2568 FORMAT_VALUE 0
2570 BUILD_STRING 2
2572 LOAD_CONST 34 (('success', 'error'))
2574 BUILD_CONST_KEY_MAP 2
2576 SWAP 2
2578 POP_EXCEPT
2580 LOAD_CONST 4 (None)
2582 STORE_FAST 32 (e)
2584 DELETE_FAST 32 (e)
2586 RETURN_VALUE
2588 LOAD_CONST 4 (None)
2590 STORE_FAST 32 (e)
2592 DELETE_FAST 32 (e)
2594 RERAISE 1

2596 RERAISE 0
2598 COPY 3
2600 POP_EXCEPT
2602 RERAISE 1

2604 LOAD_FAST 31 (ok)
2606 POP_JUMP_FORWARD_IF_TRUE 22 (to 2630)

2608 LOAD_GLOBAL 1 (NULL + log_automation_step)
2610 LOAD_FAST 1 (logger)
2612 LOAD_CONST 1 ("LAB_START")
2614 LOAD_CONST 65 ("CAPTCHA_FAILED")
2616 CALL 3
2618 POP_TOP

2620 LOAD_CONST 9 (False)
2622 LOAD_CONST 66 ("Captcha not solved")
2624 LOAD_CONST 34 (('success', 'error'))
2626 BUILD_CONST_KEY_MAP 2
2628 RETURN_VALUE

2630 LOAD_GLOBAL 1 (NULL + log_automation_step)
2632 LOAD_FAST 1 (logger)
2634 LOAD_CONST 1 ("LAB_START")
2636 LOAD_CONST 67 ("CAPTCHA_HANDLED")
2638 CALL 3
2640 POP_TOP

2642 NOP

2644 LOAD_FAST 0 (page)
2646 LOAD_ATTR 4 (url)
2648 STORE_FAST 33 (current_url)
2650 JUMP_FORWARD 18 (to 2678)
2652 PUSH_EXC_INFO

2654 LOAD_GLOBAL 6 (Exception)
2656 CHECK_EXC_MATCH
2658 POP_JUMP_FORWARD_IF_FALSE 5 (to 2670)
2660 POP_TOP

2662 LOAD_CONST 27 ("")
2664 STORE_FAST 33 (current_url)
2666 POP_EXCEPT
2668 JUMP_FORWARD 4 (to 2678)

2670 RERAISE 0
2672 COPY 3
2674 POP_EXCEPT
2676 RERAISE 1

2678 LOAD_GLOBAL 1 (NULL + log_automation_step)
2680 LOAD_FAST 1 (logger)
2682 LOAD_CONST 1 ("LAB_START")
2684 LOAD_CONST 68 ("SUCCESS")
2686 LOAD_CONST 3 ("url")
2688 LOAD_FAST 33 (current_url)
2690 BUILD_MAP 1
2692 CALL 4
2694 POP_TOP

2696 LOAD_CONST 20 (True)
2698 LOAD_FAST 33 (current_url)
2700 LOAD_CONST 69 (('success', 'url'))
2702 BUILD_CONST_KEY_MAP 2
2704 RETURN_VALUE


0 RETURN_GENERATOR
2 POP_TOP

4 NOP

6 LOAD_FAST 0 (page)
8 LOAD_METHOD 0 (locator)
10 LOAD_CONST 1 ("ql-lab-control-panel")
12 CALL 1
14 LOAD_METHOD 1 (scroll_into_view_if_needed)
16 CALL 0
18 GET_AWAITABLE 0
20 LOAD_CONST 2 (None)
22 SEND 3 (to 28)
24 YIELD_VALUE
26 JUMP_BACKWARD_NO_INTERRUPT 4 (to 22)
28 POP_TOP
30 JUMP_FORWARD 16 (to 54)
32 PUSH_EXC_INFO

34 LOAD_GLOBAL 4 (Exception)
36 CHECK_EXC_MATCH
38 POP_JUMP_FORWARD_IF_FALSE 3 (to 46)
40 POP_TOP

42 POP_EXCEPT
44 JUMP_FORWARD 4 (to 54)

46 RERAISE 0
48 COPY 3
50 POP_EXCEPT
52 RERAISE 1

54 BUILD_LIST 0
56 LOAD_CONST 3 (('Open Google Cloud console', 'Open Google Cloud Console', 'Open Cloud Console', 'Buka Google Cloud console', 'Open Console'))
58 LIST_EXTEND 1
60 STORE_FAST 4 (texts)

62 LOAD_GLOBAL 7 (NULL + asyncio)
64 LOAD_ATTR 4 (get_event_loop)
66 CALL 0
68 LOAD_METHOD 5 (time)
70 CALL 0
72 LOAD_GLOBAL 13 (NULL + max)
74 LOAD_CONST 4 (5)
76 LOAD_FAST 3 (timeout_sec)
78 CALL 2
80 BINARY_OP 0
82 STORE_FAST 5 (deadline)

84 LOAD_CONST 5 (0)
86 STORE_FAST 6 (attempt)

88 LOAD_GLOBAL 7 (NULL + asyncio)
90 LOAD_ATTR 4 (get_event_loop)
92 CALL 0
94 LOAD_METHOD 5 (time)
96 CALL 0
98 LOAD_FAST 5 (deadline)
100 COMPARE_OP 0 (<)
102 POP_JUMP_FORWARD_IF_FALSE 2406 (to 2306)

104 LOAD_FAST 6 (attempt)
106 LOAD_CONST 6 (1)
108 BINARY_OP 13
110 STORE_FAST 6 (attempt)

112 LOAD_GLOBAL 15 (NULL + log_automation_step)
114 LOAD_FAST 1 (logger)
116 LOAD_CONST 7 ("OPEN_CONSOLE")
118 LOAD_CONST 8 ("SEARCH")
120 LOAD_FAST 6 (attempt)
122 LOAD_FAST 0 (page)
124 LOAD_ATTR 8 (url)
126 LOAD_CONST 9 (('attempt', 'url'))
128 BUILD_CONST_KEY_MAP 2
130 CALL 4
132 POP_TOP

134 LOAD_FAST 4 (texts)
136 GET_ITER
138 FOR_ITER 1373 (to 1406)
140 STORE_FAST 7 (t)

142 NOP

144 LOAD_FAST 0 (page)
146 LOAD_METHOD 9 (get_by_role)
148 LOAD_CONST 10 ("button")
150 LOAD_FAST 7 (t)
152 KW_NAMES 11 (('name',))
154 CALL 2
156 STORE_FAST 8 (loc)

158 LOAD_FAST 8 (loc)
160 LOAD_METHOD 10 (is_visible)
162 LOAD_CONST 12 (800)
164 KW_NAMES 13 (('timeout',))
166 CALL 1
168 GET_AWAITABLE 0
170 LOAD_CONST 2 (None)
172 SEND 3 (to 178)
174 YIELD_VALUE
176 JUMP_BACKWARD_NO_INTERRUPT 4 (to 172)
178 POP_JUMP_FORWARD_IF_FALSE 615 (to 750)

180 LOAD_CONST 2 (None)
182 STORE_FAST 9 (href)

184 NOP

186 LOAD_FAST 8 (loc)
188 LOAD_METHOD 11 (get_attribute)
190 LOAD_CONST 14 ("href")
192 CALL 1
194 GET_AWAITABLE 0
196 LOAD_CONST 2 (None)
198 SEND 3 (to 204)
200 YIELD_VALUE
202 JUMP_BACKWARD_NO_INTERRUPT 4 (to 198)
204 STORE_FAST 9 (href)
206 JUMP_FORWARD 18 (to 234)
208 PUSH_EXC_INFO

210 LOAD_GLOBAL 4 (Exception)
212 CHECK_EXC_MATCH
214 POP_JUMP_FORWARD_IF_FALSE 5 (to 226)
216 POP_TOP

218 LOAD_CONST 2 (None)
220 STORE_FAST 9 (href)
222 POP_EXCEPT
224 JUMP_FORWARD 4 (to 234)

226 RERAISE 0
228 COPY 3
230 POP_EXCEPT
232 RERAISE 1

234 LOAD_FAST 9 (href)
236 POP_JUMP_FORWARD_IF_FALSE 142 (to 350)
238 LOAD_FAST 9 (href)
240 LOAD_METHOD 12 (strip)
242 CALL 0
244 POP_JUMP_FORWARD_IF_FALSE 122 (to 350)

246 LOAD_FAST 2 (browser)
248 LOAD_METHOD 13 (new_context)
250 LOAD_CONST 2 (None)
252 KW_NAMES 15 (('viewport',))
254 CALL 1
256 GET_AWAITABLE 0
258 LOAD_CONST 2 (None)
260 SEND 3 (to 266)
262 YIELD_VALUE
264 JUMP_BACKWARD_NO_INTERRUPT 4 (to 260)
266 STORE_FAST 10 (inc_ctx)

268 LOAD_FAST 10 (inc_ctx)
270 LOAD_METHOD 14 (new_page)
272 CALL 0
274 GET_AWAITABLE 0
276 LOAD_CONST 2 (None)
278 SEND 3 (to 284)
280 YIELD_VALUE
282 JUMP_BACKWARD_NO_INTERRUPT 4 (to 278)
284 STORE_FAST 11 (inc_page)

286 LOAD_FAST 11 (inc_page)
288 LOAD_METHOD 15 (goto)
290 LOAD_FAST 9 (href)
292 CALL 1
294 GET_AWAITABLE 0
296 LOAD_CONST 2 (None)
298 SEND 3 (to 304)
300 YIELD_VALUE
302 JUMP_BACKWARD_NO_INTERRUPT 4 (to 298)
304 POP_TOP

306 LOAD_GLOBAL 15 (NULL + log_automation_step)
308 LOAD_FAST 1 (logger)
310 LOAD_CONST 7 ("OPEN_CONSOLE")
312 LOAD_CONST 16 ("INCOGNITO_OPENED")
314 LOAD_CONST 17 ("url")
316 LOAD_FAST 11 (inc_page)
318 LOAD_ATTR 8 (url)
320 BUILD_MAP 1
322 CALL 4
324 POP_TOP

326 LOAD_CONST 18 (True)
328 LOAD_FAST 11 (inc_page)
330 LOAD_ATTR 8 (url)
332 LOAD_CONST 18 (True)
334 LOAD_CONST 19 (('opened', 'url', 'incognito'))
336 BUILD_CONST_KEY_MAP 3
338 LOAD_FAST 10 (inc_ctx)
340 LOAD_FAST 11 (inc_page)
342 BUILD_TUPLE 3
344 SWAP 2
346 POP_TOP
348 RETURN_VALUE

350 LOAD_CONST 2 (None)
352 STORE_FAST 12 (wait_task)

354 NOP

356 LOAD_GLOBAL 7 (NULL + asyncio)
358 LOAD_ATTR 16 (create_task)
360 LOAD_FAST 0 (page)
362 LOAD_ATTR 17 (context)
364 LOAD_METHOD 18 (wait_for_event)
366 LOAD_CONST 20 ("page")
368 CALL 1
370 CALL 1
372 STORE_FAST 12 (wait_task)
374 JUMP_FORWARD 16 (to 398)
376 PUSH_EXC_INFO

378 LOAD_GLOBAL 4 (Exception)
380 CHECK_EXC_MATCH
382 POP_JUMP_FORWARD_IF_FALSE 3 (to 390)
384 POP_TOP

386 POP_EXCEPT
388 JUMP_FORWARD 4 (to 398)

390 RERAISE 0
392 COPY 3
394 POP_EXCEPT
396 RERAISE 1

398 LOAD_FAST 8 (loc)
400 LOAD_METHOD 19 (click)
402 CALL 0
404 GET_AWAITABLE 0
406 LOAD_CONST 2 (None)
408 SEND 3 (to 414)
410 YIELD_VALUE
412 JUMP_BACKWARD_NO_INTERRUPT 4 (to 408)
414 POP_TOP

416 LOAD_CONST 21 ("")
418 STORE_FAST 13 (new_url)

420 LOAD_CONST 2 (None)
422 STORE_FAST 14 (new_page_obj)

424 LOAD_FAST 12 (wait_task)
426 POP_JUMP_FORWARD_IF_FALSE 100 (to 534)

428 NOP

430 LOAD_GLOBAL 7 (NULL + asyncio)
432 LOAD_ATTR 20 (wait_for)
434 LOAD_FAST 12 (wait_task)
436 LOAD_CONST 22 (8.0)
438 KW_NAMES 13 (('timeout',))
440 CALL 2
442 GET_AWAITABLE 0
444 LOAD_CONST 2 (None)
446 SEND 3 (to 452)
448 YIELD_VALUE
450 JUMP_BACKWARD_NO_INTERRUPT 4 (to 446)
452 STORE_FAST 14 (new_page_obj)

454 NOP

456 LOAD_FAST 14 (new_page_obj)
458 LOAD_METHOD 21 (wait_for_load_state)
460 LOAD_CONST 23 ("domcontentloaded")
462 CALL 1
464 GET_AWAITABLE 0
466 LOAD_CONST 2 (None)
468 SEND 3 (to 474)
470 YIELD_VALUE
472 JUMP_BACKWARD_NO_INTERRUPT 4 (to 468)
474 POP_TOP
476 JUMP_FORWARD 16 (to 500)
478 PUSH_EXC_INFO

480 LOAD_GLOBAL 4 (Exception)
482 CHECK_EXC_MATCH
484 POP_JUMP_FORWARD_IF_FALSE 3 (to 492)
486 POP_TOP

488 POP_EXCEPT
490 JUMP_FORWARD 4 (to 500)

492 RERAISE 0
494 COPY 3
496 POP_EXCEPT
498 RERAISE 1

500 LOAD_FAST 14 (new_page_obj)
502 LOAD_ATTR 8 (url)
504 STORE_FAST 13 (new_url)
506 JUMP_FORWARD 18 (to 534)
508 PUSH_EXC_INFO

510 LOAD_GLOBAL 4 (Exception)
512 CHECK_EXC_MATCH
514 POP_JUMP_FORWARD_IF_FALSE 5 (to 526)
516 POP_TOP

518 LOAD_CONST 2 (None)
520 STORE_FAST 14 (new_page_obj)
522 POP_EXCEPT
524 JUMP_FORWARD 4 (to 534)

526 RERAISE 0
528 COPY 3
530 POP_EXCEPT
532 RERAISE 1

534 LOAD_FAST 13 (new_url)
536 POP_JUMP_FORWARD_IF_TRUE 54 (to 594)

538 NOP

540 LOAD_FAST 0 (page)
542 LOAD_METHOD 21 (wait_for_load_state)
544 LOAD_CONST 23 ("domcontentloaded")
546 LOAD_CONST 24 (8000)
548 KW_NAMES 13 (('timeout',))
550 CALL 2
552 GET_AWAITABLE 0
554 LOAD_CONST 2 (None)
556 SEND 3 (to 562)
558 YIELD_VALUE
560 JUMP_BACKWARD_NO_INTERRUPT 4 (to 556)
562 POP_TOP
564 JUMP_FORWARD 16 (to 588)
566 PUSH_EXC_INFO

568 LOAD_GLOBAL 4 (Exception)
570 CHECK_EXC_MATCH
572 POP_JUMP_FORWARD_IF_FALSE 3 (to 580)
574 POP_TOP

576 POP_EXCEPT
578 JUMP_FORWARD 4 (to 588)

580 RERAISE 0
582 COPY 3
584 POP_EXCEPT
586 RERAISE 1

588 LOAD_FAST 0 (page)
590 LOAD_ATTR 8 (url)
592 STORE_FAST 13 (new_url)

594 LOAD_FAST 13 (new_url)
596 POP_JUMP_FORWARD_IF_FALSE 168 (to 750)

598 LOAD_FAST 2 (browser)
600 LOAD_METHOD 13 (new_context)
602 LOAD_CONST 2 (None)
604 KW_NAMES 15 (('viewport',))
606 CALL 1
608 GET_AWAITABLE 0
610 LOAD_CONST 2 (None)
612 SEND 3 (to 618)
614 YIELD_VALUE
616 JUMP_BACKWARD_NO_INTERRUPT 4 (to 612)
618 STORE_FAST 10 (inc_ctx)

620 LOAD_FAST 10 (inc_ctx)
622 LOAD_METHOD 14 (new_page)
624 CALL 0
626 GET_AWAITABLE 0
628 LOAD_CONST 2 (None)
630 SEND 3 (to 636)
632 YIELD_VALUE
634 JUMP_BACKWARD_NO_INTERRUPT 4 (to 630)
636 STORE_FAST 11 (inc_page)

638 LOAD_FAST 11 (inc_page)
640 LOAD_METHOD 15 (goto)
642 LOAD_FAST 13 (new_url)
644 CALL 1
646 GET_AWAITABLE 0
648 LOAD_CONST 2 (None)
650 SEND 3 (to 656)
652 YIELD_VALUE
654 JUMP_BACKWARD_NO_INTERRUPT 4 (to 650)
656 POP_TOP

658 LOAD_GLOBAL 15 (NULL + log_automation_step)
660 LOAD_FAST 1 (logger)
662 LOAD_CONST 7 ("OPEN_CONSOLE")
664 LOAD_CONST 16 ("INCOGNITO_OPENED")
666 LOAD_CONST 17 ("url")
668 LOAD_FAST 11 (inc_page)
670 LOAD_ATTR 8 (url)
672 BUILD_MAP 1
674 CALL 4
676 POP_TOP

678 NOP

680 LOAD_FAST 14 (new_page_obj)
682 POP_JUMP_FORWARD_IF_FALSE 26 (to 702)

684 LOAD_FAST 14 (new_page_obj)
686 LOAD_METHOD 22 (close)
688 CALL 0
690 GET_AWAITABLE 0
692 LOAD_CONST 2 (None)
694 SEND 3 (to 700)
696 YIELD_VALUE
698 JUMP_BACKWARD_NO_INTERRUPT 4 (to 694)
700 POP_TOP
702 JUMP_FORWARD 16 (to 726)
704 PUSH_EXC_INFO

706 LOAD_GLOBAL 4 (Exception)
708 CHECK_EXC_MATCH
710 POP_JUMP_FORWARD_IF_FALSE 3 (to 718)
712 POP_TOP

714 POP_EXCEPT
716 JUMP_FORWARD 4 (to 726)

718 RERAISE 0
720 COPY 3
722 POP_EXCEPT
724 RERAISE 1

726 LOAD_CONST 18 (True)
728 LOAD_FAST 11 (inc_page)
730 LOAD_ATTR 8 (url)
732 LOAD_CONST 18 (True)
734 LOAD_CONST 19 (('opened', 'url', 'incognito'))
736 BUILD_CONST_KEY_MAP 3
738 LOAD_FAST 10 (inc_ctx)
740 LOAD_FAST 11 (inc_page)
742 BUILD_TUPLE 3
744 SWAP 2
746 POP_TOP
748 RETURN_VALUE
750 JUMP_FORWARD 16 (to 774)
752 PUSH_EXC_INFO

754 LOAD_GLOBAL 4 (Exception)
756 CHECK_EXC_MATCH
758 POP_JUMP_FORWARD_IF_FALSE 3 (to 766)
760 POP_TOP

762 POP_EXCEPT
764 JUMP_FORWARD 4 (to 774)

766 RERAISE 0
768 COPY 3
770 POP_EXCEPT
772 RERAISE 1

774 NOP

776 LOAD_FAST 0 (page)
778 LOAD_METHOD 9 (get_by_role)
780 LOAD_CONST 25 ("link")
782 LOAD_FAST 7 (t)
784 KW_NAMES 11 (('name',))
786 CALL 2
788 STORE_FAST 8 (loc)

790 LOAD_FAST 8 (loc)
792 LOAD_METHOD 10 (is_visible)
794 LOAD_CONST 12 (800)
796 KW_NAMES 13 (('timeout',))
798 CALL 1
800 GET_AWAITABLE 0
802 LOAD_CONST 2 (None)
804 SEND 3 (to 810)
806 YIELD_VALUE
808 JUMP_BACKWARD_NO_INTERRUPT 4 (to 804)
810 POP_JUMP_FORWARD_IF_FALSE 615 (to 1382)

812 LOAD_CONST 2 (None)
814 STORE_FAST 9 (href)

816 NOP

818 LOAD_FAST 8 (loc)
820 LOAD_METHOD 11 (get_attribute)
822 LOAD_CONST 14 ("href")
824 CALL 1
826 GET_AWAITABLE 0
828 LOAD_CONST 2 (None)
830 SEND 3 (to 836)
832 YIELD_VALUE
834 JUMP_BACKWARD_NO_INTERRUPT 4 (to 830)
836 STORE_FAST 9 (href)
838 JUMP_FORWARD 18 (to 866)
840 PUSH_EXC_INFO

842 LOAD_GLOBAL 4 (Exception)
844 CHECK_EXC_MATCH
846 POP_JUMP_FORWARD_IF_FALSE 5 (to 858)
848 POP_TOP

850 LOAD_CONST 2 (None)
852 STORE_FAST 9 (href)
854 POP_EXCEPT
856 JUMP_FORWARD 4 (to 866)

858 RERAISE 0
860 COPY 3
862 POP_EXCEPT
864 RERAISE 1

866 LOAD_FAST 9 (href)
868 POP_JUMP_FORWARD_IF_FALSE 142 (to 982)
870 LOAD_FAST 9 (href)
872 LOAD_METHOD 12 (strip)
874 CALL 0
876 POP_JUMP_FORWARD_IF_FALSE 122 (to 982)

878 LOAD_FAST 2 (browser)
880 LOAD_METHOD 13 (new_context)
882 LOAD_CONST 2 (None)
884 KW_NAMES 15 (('viewport',))
886 CALL 1
888 GET_AWAITABLE 0
890 LOAD_CONST 2 (None)
892 SEND 3 (to 898)
894 YIELD_VALUE
896 JUMP_BACKWARD_NO_INTERRUPT 4 (to 892)
898 STORE_FAST 10 (inc_ctx)

900 LOAD_FAST 10 (inc_ctx)
902 LOAD_METHOD 14 (new_page)
904 CALL 0
906 GET_AWAITABLE 0
908 LOAD_CONST 2 (None)
910 SEND 3 (to 916)
912 YIELD_VALUE
914 JUMP_BACKWARD_NO_INTERRUPT 4 (to 910)
916 STORE_FAST 11 (inc_page)

918 LOAD_FAST 11 (inc_page)
920 LOAD_METHOD 15 (goto)
922 LOAD_FAST 9 (href)
924 CALL 1
926 GET_AWAITABLE 0
928 LOAD_CONST 2 (None)
930 SEND 3 (to 936)
932 YIELD_VALUE
934 JUMP_BACKWARD_NO_INTERRUPT 4 (to 930)
936 POP_TOP

938 LOAD_GLOBAL 15 (NULL + log_automation_step)
940 LOAD_FAST 1 (logger)
942 LOAD_CONST 7 ("OPEN_CONSOLE")
944 LOAD_CONST 16 ("INCOGNITO_OPENED")
946 LOAD_CONST 17 ("url")
948 LOAD_FAST 11 (inc_page)
950 LOAD_ATTR 8 (url)
952 BUILD_MAP 1
954 CALL 4
956 POP_TOP

958 LOAD_CONST 18 (True)
960 LOAD_FAST 11 (inc_page)
962 LOAD_ATTR 8 (url)
964 LOAD_CONST 18 (True)
966 LOAD_CONST 19 (('opened', 'url', 'incognito'))
968 BUILD_CONST_KEY_MAP 3
970 LOAD_FAST 10 (inc_ctx)
972 LOAD_FAST 11 (inc_page)
974 BUILD_TUPLE 3
976 SWAP 2
978 POP_TOP
980 RETURN_VALUE

982 LOAD_CONST 2 (None)
984 STORE_FAST 12 (wait_task)

986 NOP

988 LOAD_GLOBAL 7 (NULL + asyncio)
990 LOAD_ATTR 16 (create_task)
992 LOAD_FAST 0 (page)
994 LOAD_ATTR 17 (context)
996 LOAD_METHOD 18 (wait_for_event)
998 LOAD_CONST 20 ("page")
1000 CALL 1
1002 CALL 1
1004 STORE_FAST 12 (wait_task)
1006 JUMP_FORWARD 16 (to 1030)
1008 PUSH_EXC_INFO

1010 LOAD_GLOBAL 4 (Exception)
1012 CHECK_EXC_MATCH
1014 POP_JUMP_FORWARD_IF_FALSE 3 (to 1022)
1016 POP_TOP

1018 POP_EXCEPT
1020 JUMP_FORWARD 4 (to 1030)

1022 RERAISE 0
1024 COPY 3
1026 POP_EXCEPT
1028 RERAISE 1

1030 LOAD_FAST 8 (loc)
1032 LOAD_METHOD 19 (click)
1034 CALL 0
1036 GET_AWAITABLE 0
1038 LOAD_CONST 2 (None)
1040 SEND 3 (to 1046)
1042 YIELD_VALUE
1044 JUMP_BACKWARD_NO_INTERRUPT 4 (to 1040)
1046 POP_TOP

1048 LOAD_CONST 21 ("")
1050 STORE_FAST 13 (new_url)

1052 LOAD_CONST 2 (None)
1054 STORE_FAST 14 (new_page_obj)

1056 LOAD_FAST 12 (wait_task)
1058 POP_JUMP_FORWARD_IF_FALSE 100 (to 1166)

1060 NOP

1062 LOAD_GLOBAL 7 (NULL + asyncio)
1064 LOAD_ATTR 20 (wait_for)
1066 LOAD_FAST 12 (wait_task)
1068 LOAD_CONST 22 (8.0)
1070 KW_NAMES 13 (('timeout',))
1072 CALL 2
1074 GET_AWAITABLE 0
1076 LOAD_CONST 2 (None)
1078 SEND 3 (to 1084)
1080 YIELD_VALUE
1082 JUMP_BACKWARD_NO_INTERRUPT 4 (to 1078)
1084 STORE_FAST 14 (new_page_obj)

1086 NOP

1088 LOAD_FAST 14 (new_page_obj)
1090 LOAD_METHOD 21 (wait_for_load_state)
1092 LOAD_CONST 23 ("domcontentloaded")
1094 CALL 1
1096 GET_AWAITABLE 0
1098 LOAD_CONST 2 (None)
1100 SEND 3 (to 1106)
1102 YIELD_VALUE
1104 JUMP_BACKWARD_NO_INTERRUPT 4 (to 1100)
1106 POP_TOP
1108 JUMP_FORWARD 16 (to 1132)
1110 PUSH_EXC_INFO

1112 LOAD_GLOBAL 4 (Exception)
1114 CHECK_EXC_MATCH
1116 POP_JUMP_FORWARD_IF_FALSE 3 (to 1124)
1118 POP_TOP

1120 POP_EXCEPT
1122 JUMP_FORWARD 4 (to 1132)

1124 RERAISE 0
1126 COPY 3
1128 POP_EXCEPT
1130 RERAISE 1

1132 LOAD_FAST 14 (new_page_obj)
1134 LOAD_ATTR 8 (url)
1136 STORE_FAST 13 (new_url)
1138 JUMP_FORWARD 18 (to 1166)
1140 PUSH_EXC_INFO

1142 LOAD_GLOBAL 4 (Exception)
1144 CHECK_EXC_MATCH
1146 POP_JUMP_FORWARD_IF_FALSE 5 (to 1158)
1148 POP_TOP

1150 LOAD_CONST 2 (None)
1152 STORE_FAST 14 (new_page_obj)
1154 POP_EXCEPT
1156 JUMP_FORWARD 4 (to 1166)

1158 RERAISE 0
1160 COPY 3
1162 POP_EXCEPT
1164 RERAISE 1

1166 LOAD_FAST 13 (new_url)
1168 POP_JUMP_FORWARD_IF_TRUE 54 (to 1226)

1170 NOP

1172 LOAD_FAST 0 (page)
1174 LOAD_METHOD 21 (wait_for_load_state)
1176 LOAD_CONST 23 ("domcontentloaded")
1178 LOAD_CONST 24 (8000)
1180 KW_NAMES 13 (('timeout',))
1182 CALL 2
1184 GET_AWAITABLE 0
1186 LOAD_CONST 2 (None)
1188 SEND 3 (to 1194)
1190 YIELD_VALUE
1192 JUMP_BACKWARD_NO_INTERRUPT 4 (to 1188)
1194 POP_TOP
1196 JUMP_FORWARD 16 (to 1220)
1198 PUSH_EXC_INFO

1200 LOAD_GLOBAL 4 (Exception)
1202 CHECK_EXC_MATCH
1204 POP_JUMP_FORWARD_IF_FALSE 3 (to 1212)
1206 POP_TOP

1208 POP_EXCEPT
1210 JUMP_FORWARD 4 (to 1220)

1212 RERAISE 0
1214 COPY 3
1216 POP_EXCEPT
1218 RERAISE 1

1220 LOAD_FAST 0 (page)
1222 LOAD_ATTR 8 (url)
1224 STORE_FAST 13 (new_url)

1226 LOAD_FAST 13 (new_url)
1228 POP_JUMP_FORWARD_IF_FALSE 168 (to 1382)

1230 LOAD_FAST 2 (browser)
1232 LOAD_METHOD 13 (new_context)
1234 LOAD_CONST 2 (None)
1236 KW_NAMES 15 (('viewport',))
1238 CALL 1
1240 GET_AWAITABLE 0
1242 LOAD_CONST 2 (None)
1244 SEND 3 (to 1250)
1246 YIELD_VALUE
1248 JUMP_BACKWARD_NO_INTERRUPT 4 (to 1244)
1250 STORE_FAST 10 (inc_ctx)

1252 LOAD_FAST 10 (inc_ctx)
1254 LOAD_METHOD 14 (new_page)
1256 CALL 0
1258 GET_AWAITABLE 0
1260 LOAD_CONST 2 (None)
1262 SEND 3 (to 1268)
1264 YIELD_VALUE
1266 JUMP_BACKWARD_NO_INTERRUPT 4 (to 1262)
1268 STORE_FAST 11 (inc_page)

1270 LOAD_FAST 11 (inc_page)
1272 LOAD_METHOD 15 (goto)
1274 LOAD_FAST 13 (new_url)
1276 CALL 1
1278 GET_AWAITABLE 0
1280 LOAD_CONST 2 (None)
1282 SEND 3 (to 1288)
1284 YIELD_VALUE
1286 JUMP_BACKWARD_NO_INTERRUPT 4 (to 1282)
1288 POP_TOP

1290 LOAD_GLOBAL 15 (NULL + log_automation_step)
1292 LOAD_FAST 1 (logger)
1294 LOAD_CONST 7 ("OPEN_CONSOLE")
1296 LOAD_CONST 16 ("INCOGNITO_OPENED")
1298 LOAD_CONST 17 ("url")
1300 LOAD_FAST 11 (inc_page)
1302 LOAD_ATTR 8 (url)
1304 BUILD_MAP 1
1306 CALL 4
1308 POP_TOP

1310 NOP

1312 LOAD_FAST 14 (new_page_obj)
1314 POP_JUMP_FORWARD_IF_FALSE 26 (to 1334)

1316 LOAD_FAST 14 (new_page_obj)
1318 LOAD_METHOD 22 (close)
1320 CALL 0
1322 GET_AWAITABLE 0
1324 LOAD_CONST 2 (None)
1326 SEND 3 (to 1332)
1328 YIELD_VALUE
1330 JUMP_BACKWARD_NO_INTERRUPT 4 (to 1326)
1332 POP_TOP
1334 JUMP_FORWARD 16 (to 1358)
1336 PUSH_EXC_INFO

1338 LOAD_GLOBAL 4 (Exception)
1340 CHECK_EXC_MATCH
1342 POP_JUMP_FORWARD_IF_FALSE 3 (to 1350)
1344 POP_TOP

1346 POP_EXCEPT
1348 JUMP_FORWARD 4 (to 1358)

1350 RERAISE 0
1352 COPY 3
1354 POP_EXCEPT
1356 RERAISE 1

1358 LOAD_CONST 18 (True)
1360 LOAD_FAST 11 (inc_page)
1362 LOAD_ATTR 8 (url)
1364 LOAD_CONST 18 (True)
1366 LOAD_CONST 19 (('opened', 'url', 'incognito'))
1368 BUILD_CONST_KEY_MAP 3
1370 LOAD_FAST 10 (inc_ctx)
1372 LOAD_FAST 11 (inc_page)
1374 BUILD_TUPLE 3
1376 SWAP 2
1378 POP_TOP
1380 RETURN_VALUE
1382 JUMP_BACKWARD 1358 (to 138)
1384 PUSH_EXC_INFO

1386 LOAD_GLOBAL 4 (Exception)
1388 CHECK_EXC_MATCH
1390 POP_JUMP_FORWARD_IF_FALSE 4 (to 1398)
1392 POP_TOP

1394 POP_EXCEPT
1396 JUMP_BACKWARD 1371 (to 138)

1398 RERAISE 0
1400 COPY 3
1402 POP_EXCEPT
1404 RERAISE 1

1406 NOP

1408 LOAD_FAST 0 (page)
1410 LOAD_METHOD 0 (locator)
1412 LOAD_CONST 26 ("button, a[role='button'], a")
1414 CALL 1
1416 STORE_FAST 15 (btns)

1418 LOAD_FAST 15 (btns)
1420 LOAD_METHOD 23 (count)
1422 CALL 0
1424 GET_AWAITABLE 0
1426 LOAD_CONST 2 (None)
1428 SEND 3 (to 1434)
1430 YIELD_VALUE
1432 JUMP_BACKWARD_NO_INTERRUPT 4 (to 1428)
1434 STORE_FAST 16 (total)

1436 LOAD_GLOBAL 15 (NULL + log_automation_step)
1438 LOAD_FAST 1 (logger)
1440 LOAD_CONST 7 ("OPEN_CONSOLE")
1442 LOAD_CONST 27 ("CANDIDATES")
1444 LOAD_CONST 28 ("count")
1446 LOAD_FAST 16 (total)
1448 BUILD_MAP 1
1450 CALL 4
1452 POP_TOP

1454 LOAD_GLOBAL 49 (NULL + range)
1456 LOAD_FAST 16 (total)
1458 CALL 1
1460 GET_ITER
1462 FOR_ITER 809 (to 2220)
1464 STORE_FAST 17 (i)

1466 LOAD_FAST 15 (btns)
1468 LOAD_METHOD 25 (nth)
1470 LOAD_FAST 17 (i)
1472 CALL 1
1474 STORE_FAST 18 (cand)

1476 NOP

1478 LOAD_FAST 18 (cand)
1480 LOAD_METHOD 26 (text_content)
1482 CALL 0
1484 GET_AWAITABLE 0
1486 LOAD_CONST 2 (None)
1488 SEND 3 (to 1494)
1490 YIELD_VALUE
1492 JUMP_BACKWARD_NO_INTERRUPT 4 (to 1488)
1494 JUMP_IF_TRUE_OR_POP 1 (to 1498)
1496 LOAD_CONST 21 ("")
1498 LOAD_METHOD 12 (strip)
1500 CALL 0
1502 LOAD_METHOD 27 (lower)
1504 CALL 0
1506 STORE_FAST 19 (txt)
1508 JUMP_FORWARD 18 (to 1536)
1510 PUSH_EXC_INFO

1512 LOAD_GLOBAL 4 (Exception)
1514 CHECK_EXC_MATCH
1516 POP_JUMP_FORWARD_IF_FALSE 5 (to 1528)
1518 POP_TOP

1520 LOAD_CONST 21 ("")
1522 STORE_FAST 19 (txt)
1524 POP_EXCEPT
1526 JUMP_FORWARD 4 (to 1536)

1528 RERAISE 0
1530 COPY 3
1532 POP_EXCEPT
1534 RERAISE 1

1536 LOAD_FAST 19 (txt)
1538 POP_JUMP_FORWARD_IF_TRUE 1 (to 1542)

1540 JUMP_BACKWARD 111 (to 1462)

1542 LOAD_CONST 29 ("open")
1544 LOAD_FAST 19 (txt)
1546 CONTAINS_OP 0 (in)
1548 POP_JUMP_FORWARD_IF_FALSE 4 (to 1558)
1550 LOAD_CONST 30 ("console")
1552 LOAD_FAST 19 (txt)
1554 CONTAINS_OP 0 (in)
1556 POP_JUMP_FORWARD_IF_TRUE 10 (to 1574)
1558 LOAD_CONST 31 ("google cloud")
1560 LOAD_FAST 19 (txt)
1562 CONTAINS_OP 0 (in)
1564 POP_JUMP_FORWARD_IF_FALSE 685 (to 2218)
1566 LOAD_CONST 30 ("console")
1568 LOAD_FAST 19 (txt)
1570 CONTAINS_OP 0 (in)
1572 POP_JUMP_FORWARD_IF_FALSE 680 (to 2218)

1574 LOAD_CONST 2 (None)
1576 STORE_FAST 9 (href)

1578 NOP

1580 LOAD_FAST 18 (cand)
1582 LOAD_METHOD 11 (get_attribute)
1584 LOAD_CONST 14 ("href")
1586 CALL 1
1588 GET_AWAITABLE 0
1590 LOAD_CONST 2 (None)
1592 SEND 3 (to 1598)
1594 YIELD_VALUE
1596 JUMP_BACKWARD_NO_INTERRUPT 4 (to 1592)
1598 STORE_FAST 9 (href)
1600 JUMP_FORWARD 18 (to 1628)
1602 PUSH_EXC_INFO

1604 LOAD_GLOBAL 4 (Exception)
1606 CHECK_EXC_MATCH
1608 POP_JUMP_FORWARD_IF_FALSE 5 (to 1620)
1610 POP_TOP

1612 LOAD_CONST 2 (None)
1614 STORE_FAST 9 (href)
1616 POP_EXCEPT
1618 JUMP_FORWARD 4 (to 1628)

1620 RERAISE 0
1622 COPY 3
1624 POP_EXCEPT
1626 RERAISE 1

1628 LOAD_FAST 9 (href)
1630 POP_JUMP_FORWARD_IF_FALSE 142 (to 1744)
1632 LOAD_FAST 9 (href)
1634 LOAD_METHOD 12 (strip)
1636 CALL 0
1638 POP_JUMP_FORWARD_IF_FALSE 122 (to 1744)

1640 LOAD_FAST 2 (browser)
1642 LOAD_METHOD 13 (new_context)
1644 LOAD_CONST 2 (None)
1646 KW_NAMES 15 (('viewport',))
1648 CALL 1
1650 GET_AWAITABLE 0
1652 LOAD_CONST 2 (None)
1654 SEND 3 (to 1660)
1656 YIELD_VALUE
1658 JUMP_BACKWARD_NO_INTERRUPT 4 (to 1654)
1660 STORE_FAST 10 (inc_ctx)

1662 LOAD_FAST 10 (inc_ctx)
1664 LOAD_METHOD 14 (new_page)
1666 CALL 0
1668 GET_AWAITABLE 0
1670 LOAD_CONST 2 (None)
1672 SEND 3 (to 1678)
1674 YIELD_VALUE
1676 JUMP_BACKWARD_NO_INTERRUPT 4 (to 1672)
1678 STORE_FAST 11 (inc_page)

1680 LOAD_FAST 11 (inc_page)
1682 LOAD_METHOD 15 (goto)
1684 LOAD_FAST 9 (href)
1686 CALL 1
1688 GET_AWAITABLE 0
1690 LOAD_CONST 2 (None)
1692 SEND 3 (to 1698)
1694 YIELD_VALUE
1696 JUMP_BACKWARD_NO_INTERRUPT 4 (to 1692)
1698 POP_TOP

1700 LOAD_GLOBAL 15 (NULL + log_automation_step)
1702 LOAD_FAST 1 (logger)
1704 LOAD_CONST 7 ("OPEN_CONSOLE")
1706 LOAD_CONST 16 ("INCOGNITO_OPENED")
1708 LOAD_CONST 17 ("url")
1710 LOAD_FAST 11 (inc_page)
1712 LOAD_ATTR 8 (url)
1714 BUILD_MAP 1
1716 CALL 4
1718 POP_TOP

1720 LOAD_CONST 18 (True)
1722 LOAD_FAST 11 (inc_page)
1724 LOAD_ATTR 8 (url)
1726 LOAD_CONST 18 (True)
1728 LOAD_CONST 19 (('opened', 'url', 'incognito'))
1730 BUILD_CONST_KEY_MAP 3
1732 LOAD_FAST 10 (inc_ctx)
1734 LOAD_FAST 11 (inc_page)
1736 BUILD_TUPLE 3
1738 SWAP 2
1740 POP_TOP
1742 RETURN_VALUE

1744 LOAD_CONST 2 (None)
1746 STORE_FAST 12 (wait_task)

1748 NOP

1750 LOAD_GLOBAL 7 (NULL + asyncio)
1752 LOAD_ATTR 16 (create_task)
1754 LOAD_FAST 0 (page)
1756 LOAD_ATTR 17 (context)
1758 LOAD_METHOD 18 (wait_for_event)
1760 LOAD_CONST 20 ("page")
1762 CALL 1
1764 CALL 1
1766 STORE_FAST 12 (wait_task)
1768 JUMP_FORWARD 16 (to 1792)
1770 PUSH_EXC_INFO

1772 LOAD_GLOBAL 4 (Exception)
1774 CHECK_EXC_MATCH
1776 POP_JUMP_FORWARD_IF_FALSE 3 (to 1784)
1778 POP_TOP

1780 POP_EXCEPT
1782 JUMP_FORWARD 4 (to 1792)

1784 RERAISE 0
1786 COPY 3
1788 POP_EXCEPT
1790 RERAISE 1

1792 LOAD_CONST 2 (None)
1794 STORE_FAST 14 (new_page_obj)

1796 NOP

1798 LOAD_FAST 18 (cand)
1800 LOAD_METHOD 19 (click)
1802 CALL 0
1804 GET_AWAITABLE 0
1806 LOAD_CONST 2 (None)
1808 SEND 3 (to 1814)
1810 YIELD_VALUE
1812 JUMP_BACKWARD_NO_INTERRUPT 4 (to 1808)
1814 POP_TOP
1816 JUMP_FORWARD 63 (to 1888)
1818 PUSH_EXC_INFO

1820 LOAD_GLOBAL 4 (Exception)
1822 CHECK_EXC_MATCH
1824 POP_JUMP_FORWARD_IF_FALSE 50 (to 1880)
1826 POP_TOP

1828 NOP

1830 LOAD_FAST 18 (cand)
1832 LOAD_METHOD 28 (dispatch_event)
1834 LOAD_CONST 32 ("click")
1836 CALL 1
1838 GET_AWAITABLE 0
1840 LOAD_CONST 2 (None)
1842 SEND 3 (to 1848)
1844 YIELD_VALUE
1846 JUMP_BACKWARD_NO_INTERRUPT 4 (to 1842)
1848 POP_TOP
1850 JUMP_FORWARD 18 (to 1876)
1852 PUSH_EXC_INFO

1854 LOAD_GLOBAL 4 (Exception)
1856 CHECK_EXC_MATCH
1858 POP_JUMP_FORWARD_IF_FALSE 5 (to 1868)
1860 POP_TOP

1862 POP_EXCEPT
1864 POP_EXCEPT
1866 JUMP_BACKWARD 469 (to 1462)

1868 RERAISE 0
1870 COPY 3
1872 POP_EXCEPT
1874 RERAISE 1

1876 POP_EXCEPT
1878 JUMP_FORWARD 4 (to 1888)

1880 RERAISE 0
1882 COPY 3
1884 POP_EXCEPT
1886 RERAISE 1

1888 LOAD_CONST 21 ("")
1890 STORE_FAST 13 (new_url)

1892 LOAD_FAST 12 (wait_task)
1894 POP_JUMP_FORWARD_IF_FALSE 100 (to 2002)

1896 NOP

1898 LOAD_GLOBAL 7 (NULL + asyncio)
1900 LOAD_ATTR 20 (wait_for)
1902 LOAD_FAST 12 (wait_task)
1904 LOAD_CONST 22 (8.0)
1906 KW_NAMES 13 (('timeout',))
1908 CALL 2
1910 GET_AWAITABLE 0
1912 LOAD_CONST 2 (None)
1914 SEND 3 (to 1920)
1916 YIELD_VALUE
1918 JUMP_BACKWARD_NO_INTERRUPT 4 (to 1914)
1920 STORE_FAST 14 (new_page_obj)

1922 NOP

1924 LOAD_FAST 14 (new_page_obj)
1926 LOAD_METHOD 21 (wait_for_load_state)
1928 LOAD_CONST 23 ("domcontentloaded")
1930 CALL 1
1932 GET_AWAITABLE 0
1934 LOAD_CONST 2 (None)
1936 SEND 3 (to 1942)
1938 YIELD_VALUE
1940 JUMP_BACKWARD_NO_INTERRUPT 4 (to 1936)
1942 POP_TOP
1944 JUMP_FORWARD 16 (to 1968)
1946 PUSH_EXC_INFO

1948 LOAD_GLOBAL 4 (Exception)
1950 CHECK_EXC_MATCH
1952 POP_JUMP_FORWARD_IF_FALSE 3 (to 1960)
1954 POP_TOP

1956 POP_EXCEPT
1958 JUMP_FORWARD 4 (to 1968)

1960 RERAISE 0
1962 COPY 3
1964 POP_EXCEPT
1966 RERAISE 1

1968 LOAD_FAST 14 (new_page_obj)
1970 LOAD_ATTR 8 (url)
1972 STORE_FAST 13 (new_url)
1974 JUMP_FORWARD 18 (to 2002)
1976 PUSH_EXC_INFO

1978 LOAD_GLOBAL 4 (Exception)
1980 CHECK_EXC_MATCH
1982 POP_JUMP_FORWARD_IF_FALSE 5 (to 1994)
1984 POP_TOP

1986 LOAD_CONST 2 (None)
1988 STORE_FAST 14 (new_page_obj)
1990 POP_EXCEPT
1992 JUMP_FORWARD 4 (to 2002)

1994 RERAISE 0
1996 COPY 3
1998 POP_EXCEPT
2000 RERAISE 1

2002 LOAD_FAST 13 (new_url)
2004 POP_JUMP_FORWARD_IF_TRUE 54 (to 2062)

2006 NOP

2008 LOAD_FAST 0 (page)
2010 LOAD_METHOD 21 (wait_for_load_state)
2012 LOAD_CONST 23 ("domcontentloaded")
2014 LOAD_CONST 24 (8000)
2016 KW_NAMES 13 (('timeout',))
2018 CALL 2
2020 GET_AWAITABLE 0
2022 LOAD_CONST 2 (None)
2024 SEND 3 (to 2030)
2026 YIELD_VALUE
2028 JUMP_BACKWARD_NO_INTERRUPT 4 (to 2024)
2030 POP_TOP
2032 JUMP_FORWARD 16 (to 2056)
2034 PUSH_EXC_INFO

2036 LOAD_GLOBAL 4 (Exception)
2038 CHECK_EXC_MATCH
2040 POP_JUMP_FORWARD_IF_FALSE 3 (to 2048)
2042 POP_TOP

2044 POP_EXCEPT
2046 JUMP_FORWARD 4 (to 2056)

2048 RERAISE 0
2050 COPY 3
2052 POP_EXCEPT
2054 RERAISE 1

2056 LOAD_FAST 0 (page)
2058 LOAD_ATTR 8 (url)
2060 STORE_FAST 13 (new_url)

2062 LOAD_FAST 13 (new_url)
2064 POP_JUMP_FORWARD_IF_FALSE 168 (to 2218)

2066 LOAD_FAST 2 (browser)
2068 LOAD_METHOD 13 (new_context)
2070 LOAD_CONST 2 (None)
2072 KW_NAMES 15 (('viewport',))
2074 CALL 1
2076 GET_AWAITABLE 0
2078 LOAD_CONST 2 (None)
2080 SEND 3 (to 2086)
2082 YIELD_VALUE
2084 JUMP_BACKWARD_NO_INTERRUPT 4 (to 2080)
2086 STORE_FAST 10 (inc_ctx)

2088 LOAD_FAST 10 (inc_ctx)
2090 LOAD_METHOD 14 (new_page)
2092 CALL 0
2094 GET_AWAITABLE 0
2096 LOAD_CONST 2 (None)
2098 SEND 3 (to 2104)
2100 YIELD_VALUE
2102 JUMP_BACKWARD_NO_INTERRUPT 4 (to 2098)
2104 STORE_FAST 11 (inc_page)

2106 LOAD_FAST 11 (inc_page)
2108 LOAD_METHOD 15 (goto)
2110 LOAD_FAST 13 (new_url)
2112 CALL 1
2114 GET_AWAITABLE 0
2116 LOAD_CONST 2 (None)
2118 SEND 3 (to 2124)
2120 YIELD_VALUE
2122 JUMP_BACKWARD_NO_INTERRUPT 4 (to 2118)
2124 POP_TOP

2126 LOAD_GLOBAL 15 (NULL + log_automation_step)
2128 LOAD_FAST 1 (logger)
2130 LOAD_CONST 7 ("OPEN_CONSOLE")
2132 LOAD_CONST 16 ("INCOGNITO_OPENED")
2134 LOAD_CONST 17 ("url")
2136 LOAD_FAST 11 (inc_page)
2138 LOAD_ATTR 8 (url)
2140 BUILD_MAP 1
2142 CALL 4
2144 POP_TOP

2146 NOP

2148 LOAD_FAST 14 (new_page_obj)
2150 POP_JUMP_FORWARD_IF_FALSE 26 (to 2170)

2152 LOAD_FAST 14 (new_page_obj)
2154 LOAD_METHOD 22 (close)
2156 CALL 0
2158 GET_AWAITABLE 0
2160 LOAD_CONST 2 (None)
2162 SEND 3 (to 2168)
2164 YIELD_VALUE
2166 JUMP_BACKWARD_NO_INTERRUPT 4 (to 2162)
2168 POP_TOP
2170 JUMP_FORWARD 16 (to 2194)
2172 PUSH_EXC_INFO

2174 LOAD_GLOBAL 4 (Exception)
2176 CHECK_EXC_MATCH
2178 POP_JUMP_FORWARD_IF_FALSE 3 (to 2186)
2180 POP_TOP

2182 POP_EXCEPT
2184 JUMP_FORWARD 4 (to 2194)

2186 RERAISE 0
2188 COPY 3
2190 POP_EXCEPT
2192 RERAISE 1

2194 LOAD_CONST 18 (True)
2196 LOAD_FAST 11 (inc_page)
2198 LOAD_ATTR 8 (url)
2200 LOAD_CONST 18 (True)
2202 LOAD_CONST 19 (('opened', 'url', 'incognito'))
2204 BUILD_CONST_KEY_MAP 3
2206 LOAD_FAST 10 (inc_ctx)
2208 LOAD_FAST 11 (inc_page)
2210 BUILD_TUPLE 3
2212 SWAP 2
2214 POP_TOP
2216 RETURN_VALUE
2218 JUMP_BACKWARD 811 (to 1462)

2220 JUMP_FORWARD 16 (to 2244)
2222 PUSH_EXC_INFO

2224 LOAD_GLOBAL 4 (Exception)
2226 CHECK_EXC_MATCH
2228 POP_JUMP_FORWARD_IF_FALSE 3 (to 2236)
2230 POP_TOP

2232 POP_EXCEPT
2234 JUMP_FORWARD 4 (to 2244)

2236 RERAISE 0
2238 COPY 3
2240 POP_EXCEPT
2242 RERAISE 1

2244 NOP

2246 LOAD_FAST 0 (page)
2248 LOAD_METHOD 29 (wait_for_timeout)
2250 LOAD_CONST 33 (1500)
2252 CALL 1
2254 GET_AWAITABLE 0
2256 LOAD_CONST 2 (None)
2258 SEND 3 (to 2264)
2260 YIELD_VALUE
2262 JUMP_BACKWARD_NO_INTERRUPT 4 (to 2258)
2264 POP_TOP
2266 JUMP_FORWARD 16 (to 2290)
2268 PUSH_EXC_INFO

2270 LOAD_GLOBAL 4 (Exception)
2272 CHECK_EXC_MATCH
2274 POP_JUMP_FORWARD_IF_FALSE 3 (to 2282)
2276 POP_TOP

2278 POP_EXCEPT
2280 JUMP_FORWARD 4 (to 2290)

2282 RERAISE 0
2284 COPY 3
2286 POP_EXCEPT
2288 RERAISE 1

2290 LOAD_GLOBAL 7 (NULL + asyncio)
2292 LOAD_ATTR 4 (get_event_loop)
2294 CALL 0
2296 LOAD_METHOD 5 (time)
2298 CALL 0
2300 LOAD_FAST 5 (deadline)
2302 COMPARE_OP 0 (<)
2304 POP_JUMP_BACKWARD_IF_TRUE 2406 (to 104)

2306 LOAD_CONST 34 (False)
2308 LOAD_CONST 21 ("")
2310 LOAD_CONST 35 (('opened', 'url'))
2312 BUILD_CONST_KEY_MAP 2
2314 LOAD_CONST 2 (None)
2316 LOAD_CONST 2 (None)
2318 BUILD_TUPLE 3
2320 RETURN_VALUE


0 RETURN_GENERATOR
2 POP_TOP

4 LOAD_FAST 0 (inc_page)
6 POP_JUMP_FORWARD_IF_TRUE 5 (to 18)

8 LOAD_CONST 1 (False)
10 LOAD_CONST 2 ("no_incognito_page")
12 LOAD_CONST 3 (('handled', 'reason'))
14 BUILD_CONST_KEY_MAP 2
16 RETURN_VALUE

18 LOAD_GLOBAL 1 (NULL + asyncio)
20 LOAD_ATTR 1 (get_event_loop)
22 CALL 0
24 LOAD_METHOD 2 (time)
26 CALL 0
28 LOAD_FAST 2 (timeout_sec)
30 BINARY_OP 0
32 STORE_FAST 3 (deadline)

34 LOAD_CONST 4 (0)
36 STORE_FAST 4 (attempt)

38 LOAD_GLOBAL 1 (NULL + asyncio)
40 LOAD_ATTR 1 (get_event_loop)
42 CALL 0
44 LOAD_METHOD 2 (time)
46 CALL 0
48 LOAD_FAST 3 (deadline)
50 COMPARE_OP 0 (<)
52 POP_JUMP_FORWARD_IF_FALSE 1439 (to 1258)

54 LOAD_FAST 4 (attempt)
56 LOAD_CONST 5 (1)
58 BINARY_OP 13
60 STORE_FAST 4 (attempt)

62 NOP

64 LOAD_FAST 0 (inc_page)
66 LOAD_METHOD 3 (is_closed)
68 CALL 0
70 POP_JUMP_FORWARD_IF_FALSE 5 (to 82)

72 LOAD_CONST 1 (False)
74 LOAD_CONST 6 ("page_closed")
76 LOAD_CONST 3 (('handled', 'reason'))
78 BUILD_CONST_KEY_MAP 2
80 RETURN_VALUE

82 LOAD_FAST 0 (inc_page)
84 LOAD_ATTR 4 (url)
86 STORE_FAST 5 (current_url)

88 LOAD_GLOBAL 11 (NULL + urlparse)
90 LOAD_FAST 5 (current_url)
92 CALL 1
94 LOAD_ATTR 6 (netloc)
96 LOAD_METHOD 7 (lower)
98 CALL 0
100 STORE_FAST 6 (host)
102 JUMP_FORWARD 83 (to 184)
104 PUSH_EXC_INFO

106 LOAD_GLOBAL 16 (Exception)
108 CHECK_EXC_MATCH
110 POP_JUMP_FORWARD_IF_FALSE 70 (to 176)
112 STORE_FAST 7 (e)

114 LOAD_GLOBAL 19 (NULL + log_automation_step)
116 LOAD_FAST 1 (logger)
118 LOAD_CONST 7 ("TERMS")
120 LOAD_CONST 8 ("URL_ERROR")
122 LOAD_FAST 4 (attempt)
124 LOAD_GLOBAL 21 (NULL + str)
126 LOAD_FAST 7 (e)
128 CALL 1
130 LOAD_CONST 9 (('attempt', 'error'))
132 BUILD_CONST_KEY_MAP 2
134 CALL 4
136 POP_TOP

138 LOAD_GLOBAL 1 (NULL + asyncio)
140 LOAD_ATTR 11 (sleep)
142 LOAD_CONST 5 (1)
144 CALL 1
146 GET_AWAITABLE 0
148 LOAD_CONST 10 (None)
150 SEND 3 (to 156)
152 YIELD_VALUE
154 JUMP_BACKWARD_NO_INTERRUPT 4 (to 150)
156 POP_TOP

158 POP_EXCEPT
160 LOAD_CONST 10 (None)
162 STORE_FAST 7 (e)
164 DELETE_FAST 7 (e)
166 JUMP_BACKWARD 194 (to 38)
168 LOAD_CONST 10 (None)
170 STORE_FAST 7 (e)
172 DELETE_FAST 7 (e)
174 RERAISE 1

176 RERAISE 0
178 COPY 3
180 POP_EXCEPT
182 RERAISE 1

184 LOAD_GLOBAL 19 (NULL + log_automation_step)
186 LOAD_FAST 1 (logger)
188 LOAD_CONST 7 ("TERMS")
190 LOAD_CONST 11 ("CHECK")
192 LOAD_FAST 4 (attempt)
194 LOAD_FAST 5 (current_url)
196 LOAD_CONST 12 (('attempt', 'url'))
198 BUILD_CONST_KEY_MAP 2
200 CALL 4
202 POP_TOP

204 LOAD_CONST 13 ("accounts.google.com/speedbump")
206 LOAD_FAST 5 (current_url)
208 CONTAINS_OP 0 (in)
210 POP_JUMP_FORWARD_IF_FALSE 182 (to 384)

212 LOAD_GLOBAL 19 (NULL + log_automation_step)
214 LOAD_FAST 1 (logger)
216 LOAD_CONST 7 ("TERMS")
218 LOAD_CONST 14 ("HANDLING_SPEEDBUMP")
220 BUILD_MAP 0
222 CALL 4
224 POP_TOP

226 LOAD_CONST 15 ("Saya mengerti")
228 LOAD_CONST 16 ("I understand")
230 BUILD_LIST 2
232 STORE_FAST 8 (understand_texts)

234 LOAD_CONST 1 (False)
236 STORE_FAST 9 (clicked)

238 LOAD_FAST 8 (understand_texts)
240 GET_ITER
242 FOR_ITER 149 (to 376)
244 STORE_FAST 10 (text)

246 NOP

248 LOAD_FAST 0 (inc_page)
250 LOAD_METHOD 12 (get_by_role)
252 LOAD_CONST 17 ("button")
254 LOAD_FAST 10 (text)
256 KW_NAMES 18 (('name',))
258 CALL 2
260 STORE_FAST 11 (btn)

262 LOAD_FAST 11 (btn)
264 LOAD_METHOD 13 (is_visible)
266 LOAD_CONST 19 (1500)
268 KW_NAMES 20 (('timeout',))
270 CALL 1
272 GET_AWAITABLE 0
274 LOAD_CONST 10 (None)
276 SEND 3 (to 282)
278 YIELD_VALUE
280 JUMP_BACKWARD_NO_INTERRUPT 4 (to 276)
282 POP_JUMP_FORWARD_IF_FALSE 79 (to 352)

284 LOAD_FAST 11 (btn)
286 LOAD_METHOD 14 (click)
288 CALL 0
290 GET_AWAITABLE 0
292 LOAD_CONST 10 (None)
294 SEND 3 (to 300)
296 YIELD_VALUE
298 JUMP_BACKWARD_NO_INTERRUPT 4 (to 294)
300 POP_TOP

302 LOAD_GLOBAL 19 (NULL + log_automation_step)
304 LOAD_FAST 1 (logger)
306 LOAD_CONST 7 ("TERMS")
308 LOAD_CONST 21 ("UNDERSTAND_CLICKED")
310 LOAD_CONST 22 ("text")
312 LOAD_FAST 10 (text)
314 BUILD_MAP 1
316 CALL 4
318 POP_TOP

320 LOAD_FAST 0 (inc_page)
322 LOAD_METHOD 15 (wait_for_load_state)
324 LOAD_CONST 23 ("domcontentloaded")
326 LOAD_CONST 24 (7000)
328 KW_NAMES 20 (('timeout',))
330 CALL 2
332 GET_AWAITABLE 0
334 LOAD_CONST 10 (None)
336 SEND 3 (to 342)
338 YIELD_VALUE
340 JUMP_BACKWARD_NO_INTERRUPT 4 (to 336)
342 POP_TOP

344 LOAD_CONST 25 (True)
346 STORE_FAST 9 (clicked)

348 POP_TOP
350 JUMP_FORWARD 17 (to 376)

352 JUMP_BACKWARD 134 (to 242)
354 PUSH_EXC_INFO

356 LOAD_GLOBAL 16 (Exception)
358 CHECK_EXC_MATCH
360 POP_JUMP_FORWARD_IF_FALSE 3 (to 368)
362 POP_TOP

364 POP_EXCEPT
366 JUMP_BACKWARD 146 (to 242)

368 RERAISE 0
370 COPY 3
372 POP_EXCEPT
374 RERAISE 1

376 LOAD_FAST 9 (clicked)
378 POP_JUMP_FORWARD_IF_FALSE 2 (to 382)

380 JUMP_BACKWARD 407 (to 38)

382 JUMP_FORWARD 1004 (to 1222)

384 LOAD_CONST 26 ("console.cloud.google.com")
386 LOAD_FAST 6 (host)
388 CONTAINS_OP 0 (in)
390 POP_JUMP_FORWARD_IF_FALSE 999 (to 1222)

392 LOAD_GLOBAL 19 (NULL + log_automation_step)
394 LOAD_FAST 1 (logger)
396 LOAD_CONST 7 ("TERMS")
398 LOAD_CONST 27 ("HANDLING_CONSOLE_DIALOG")
400 BUILD_MAP 0
402 CALL 4
404 POP_TOP

406 LOAD_GLOBAL 33 (NULL + range)
408 LOAD_CONST 28 (5)
410 CALL 1
412 GET_ITER
414 FOR_ITER 959 (to 1212)
416 STORE_FAST 12 (_)

418 LOAD_CONST 1 (False)
420 STORE_FAST 13 (checkbox_checked)

422 NOP

424 LOAD_FAST 0 (inc_page)
426 LOAD_METHOD 17 (query_selector_all)
428 LOAD_CONST 29 ('iframe[title="RifIframeEle"]')
430 CALL 1
432 GET_AWAITABLE 0
434 LOAD_CONST 10 (None)
436 SEND 3 (to 442)
438 YIELD_VALUE
440 JUMP_BACKWARD_NO_INTERRUPT 4 (to 436)
442 STORE_FAST 14 (frames)

444 LOAD_FAST 14 (frames)
446 POP_JUMP_FORWARD_IF_FALSE 264 (to 654)

448 LOAD_GLOBAL 19 (NULL + log_automation_step)
450 LOAD_FAST 1 (logger)
452 LOAD_CONST 7 ("TERMS")
454 LOAD_CONST 30 ("IFRAME_SEARCH")
456 LOAD_CONST 31 ("count")
458 LOAD_GLOBAL 37 (NULL + len)
460 LOAD_FAST 14 (frames)
462 CALL 1
464 BUILD_MAP 1
466 CALL 4
468 POP_TOP

470 LOAD_FAST 14 (frames)
472 GET_ITER
474 FOR_ITER 228 (to 654)
476 STORE_FAST 15 (fr_element)

478 NOP

480 LOAD_FAST 15 (fr_element)
482 LOAD_METHOD 19 (content_frame)
484 CALL 0
486 GET_AWAITABLE 0
488 LOAD_CONST 10 (None)
490 SEND 3 (to 496)
492 YIELD_VALUE
494 JUMP_BACKWARD_NO_INTERRUPT 4 (to 490)
496 STORE_FAST 16 (f)

498 LOAD_FAST 16 (f)
500 POP_JUMP_FORWARD_IF_TRUE 1 (to 504)

502 JUMP_BACKWARD 32 (to 474)

504 LOAD_FAST 16 (f)
506 LOAD_METHOD 12 (get_by_role)
508 LOAD_CONST 32 ("checkbox")
510 LOAD_GLOBAL 41 (NULL + re)
512 LOAD_ATTR 21 (compile)
514 LOAD_CONST 33 ("I agree to the Google Cloud")
516 LOAD_GLOBAL 40 (re)
518 LOAD_ATTR 22 (I)
520 CALL 2
522 KW_NAMES 18 (('name',))
524 CALL 2

526 LOAD_FAST 16 (f)
528 LOAD_METHOD 12 (get_by_role)
530 LOAD_CONST 32 ("checkbox")
532 CALL 1

534 LOAD_FAST 16 (f)
536 LOAD_METHOD 23 (locator)
538 LOAD_CONST 34 ("input[type='checkbox']")
540 CALL 1

542 BUILD_LIST 3
544 STORE_FAST 17 (checkbox_selectors)

546 LOAD_FAST 17 (checkbox_selectors)
548 GET_ITER
550 FOR_ITER 80 (to 622)
552 STORE_FAST 18 (selector)

554 LOAD_FAST 18 (selector)
556 LOAD_METHOD 13 (is_visible)
558 LOAD_CONST 35 (1000)
560 KW_NAMES 20 (('timeout',))
562 CALL 1
564 GET_AWAITABLE 0
566 LOAD_CONST 10 (None)
568 SEND 3 (to 574)
570 YIELD_VALUE
572 JUMP_BACKWARD_NO_INTERRUPT 4 (to 568)
574 POP_JUMP_FORWARD_IF_FALSE 50 (to 620)

576 LOAD_GLOBAL 19 (NULL + log_automation_step)
578 LOAD_FAST 1 (logger)
580 LOAD_CONST 7 ("TERMS")
582 LOAD_CONST 36 ("CHECKBOX_FOUND")
584 LOAD_CONST 37 ("via")
586 LOAD_CONST 38 ("iframe")
588 BUILD_MAP 1
590 CALL 4
592 POP_TOP

594 LOAD_FAST 18 (selector)
596 LOAD_METHOD 24 (check)
598 CALL 0
600 GET_AWAITABLE 0
602 LOAD_CONST 10 (None)
604 SEND 3 (to 610)
606 YIELD_VALUE
608 JUMP_BACKWARD_NO_INTERRUPT 4 (to 604)
610 POP_TOP

612 LOAD_CONST 25 (True)
614 STORE_FAST 13 (checkbox_checked)

616 POP_TOP
618 JUMP_FORWARD 1 (to 622)

620 JUMP_BACKWARD 81 (to 550)

622 LOAD_FAST 13 (checkbox_checked)
624 POP_JUMP_FORWARD_IF_FALSE 2 (to 630)

626 POP_TOP
628 JUMP_FORWARD 17 (to 654)

630 JUMP_BACKWARD 213 (to 474)
632 PUSH_EXC_INFO

634 LOAD_GLOBAL 16 (Exception)
636 CHECK_EXC_MATCH
638 POP_JUMP_FORWARD_IF_FALSE 3 (to 646)
640 POP_TOP

642 POP_EXCEPT
644 JUMP_BACKWARD 225 (to 474)

646 RERAISE 0
648 COPY 3
650 POP_EXCEPT
652 RERAISE 1
654 JUMP_FORWARD 56 (to 714)
656 PUSH_EXC_INFO

658 LOAD_GLOBAL 16 (Exception)
660 CHECK_EXC_MATCH
662 POP_JUMP_FORWARD_IF_FALSE 43 (to 706)
664 STORE_FAST 7 (e)

666 LOAD_GLOBAL 19 (NULL + log_automation_step)
668 LOAD_FAST 1 (logger)
670 LOAD_CONST 7 ("TERMS")
672 LOAD_CONST 39 ("IFRAME_SEARCH_ERROR")
674 LOAD_CONST 40 ("error")
676 LOAD_GLOBAL 21 (NULL + str)
678 LOAD_FAST 7 (e)
680 CALL 1
682 BUILD_MAP 1
684 CALL 4
686 POP_TOP
688 POP_EXCEPT
690 LOAD_CONST 10 (None)
692 STORE_FAST 7 (e)
694 DELETE_FAST 7 (e)
696 JUMP_FORWARD 8 (to 714)
698 LOAD_CONST 10 (None)
700 STORE_FAST 7 (e)
702 DELETE_FAST 7 (e)
704 RERAISE 1

706 RERAISE 0
708 COPY 3
710 POP_EXCEPT
712 RERAISE 1

714 LOAD_FAST 13 (checkbox_checked)
716 POP_JUMP_FORWARD_IF_TRUE 254 (to 916)

718 NOP

720 LOAD_GLOBAL 19 (NULL + log_automation_step)
722 LOAD_FAST 1 (logger)
724 LOAD_CONST 7 ("TERMS")
726 LOAD_CONST 41 ("DIRECT_SEARCH")
728 BUILD_MAP 0
730 CALL 4
732 POP_TOP

734 LOAD_FAST 0 (inc_page)
736 LOAD_METHOD 12 (get_by_role)
738 LOAD_CONST 32 ("checkbox")
740 LOAD_GLOBAL 41 (NULL + re)
742 LOAD_ATTR 21 (compile)
744 LOAD_CONST 33 ("I agree to the Google Cloud")
746 LOAD_GLOBAL 40 (re)
748 LOAD_ATTR 22 (I)
750 CALL 2
752 KW_NAMES 18 (('name',))
754 CALL 2

756 LOAD_FAST 0 (inc_page)
758 LOAD_METHOD 12 (get_by_role)
760 LOAD_CONST 32 ("checkbox")
762 LOAD_CONST 42 ("I agree to the Google Cloud Platform Terms of Service")
764 KW_NAMES 18 (('name',))
766 CALL 2

768 LOAD_FAST 0 (inc_page)
770 LOAD_METHOD 12 (get_by_role)
772 LOAD_CONST 32 ("checkbox")
774 CALL 1

776 BUILD_LIST 3
778 STORE_FAST 19 (direct_selectors)

780 LOAD_FAST 19 (direct_selectors)
782 GET_ITER
784 FOR_ITER 80 (to 856)
786 STORE_FAST 18 (selector)

788 LOAD_FAST 18 (selector)
790 LOAD_METHOD 13 (is_visible)
792 LOAD_CONST 35 (1000)
794 KW_NAMES 20 (('timeout',))
796 CALL 1
798 GET_AWAITABLE 0
800 LOAD_CONST 10 (None)
802 SEND 3 (to 808)
804 YIELD_VALUE
806 JUMP_BACKWARD_NO_INTERRUPT 4 (to 802)
808 POP_JUMP_FORWARD_IF_FALSE 50 (to 854)

810 LOAD_GLOBAL 19 (NULL + log_automation_step)
812 LOAD_FAST 1 (logger)
814 LOAD_CONST 7 ("TERMS")
816 LOAD_CONST 36 ("CHECKBOX_FOUND")
818 LOAD_CONST 37 ("via")
820 LOAD_CONST 43 ("direct")
822 BUILD_MAP 1
824 CALL 4
826 POP_TOP

828 LOAD_FAST 18 (selector)
830 LOAD_METHOD 24 (check)
832 CALL 0
834 GET_AWAITABLE 0
836 LOAD_CONST 10 (None)
838 SEND 3 (to 844)
840 YIELD_VALUE
842 JUMP_BACKWARD_NO_INTERRUPT 4 (to 838)
844 POP_TOP

846 LOAD_CONST 25 (True)
848 STORE_FAST 13 (checkbox_checked)

850 POP_TOP
852 JUMP_FORWARD 1 (to 856)

854 JUMP_BACKWARD 81 (to 784)
856 JUMP_FORWARD 56 (to 916)
858 PUSH_EXC_INFO

860 LOAD_GLOBAL 16 (Exception)
862 CHECK_EXC_MATCH
864 POP_JUMP_FORWARD_IF_FALSE 43 (to 908)
866 STORE_FAST 7 (e)

868 LOAD_GLOBAL 19 (NULL + log_automation_step)
870 LOAD_FAST 1 (logger)
872 LOAD_CONST 7 ("TERMS")
874 LOAD_CONST 44 ("DIRECT_SEARCH_ERROR")
876 LOAD_CONST 40 ("error")
878 LOAD_GLOBAL 21 (NULL + str)
880 LOAD_FAST 7 (e)
882 CALL 1
884 BUILD_MAP 1
886 CALL 4
888 POP_TOP
890 POP_EXCEPT
892 LOAD_CONST 10 (None)
894 STORE_FAST 7 (e)
896 DELETE_FAST 7 (e)
898 JUMP_FORWARD 8 (to 916)
900 LOAD_CONST 10 (None)
902 STORE_FAST 7 (e)
904 DELETE_FAST 7 (e)
906 RERAISE 1

908 RERAISE 0
910 COPY 3
912 POP_EXCEPT
914 RERAISE 1

916 LOAD_FAST 13 (checkbox_checked)
918 POP_JUMP_FORWARD_IF_TRUE 46 (to 956)

920 LOAD_GLOBAL 19 (NULL + log_automation_step)
922 LOAD_FAST 1 (logger)
924 LOAD_CONST 7 ("TERMS")
926 LOAD_CONST 45 ("CHECKBOX_NOT_FOUND_RETRY")
928 BUILD_MAP 0
930 CALL 4
932 POP_TOP

934 LOAD_GLOBAL 1 (NULL + asyncio)
936 LOAD_ATTR 11 (sleep)
938 LOAD_CONST 5 (1)
940 CALL 1
942 GET_AWAITABLE 0
944 LOAD_CONST 10 (None)
946 SEND 3 (to 952)
948 YIELD_VALUE
950 JUMP_BACKWARD_NO_INTERRUPT 4 (to 946)
952 POP_TOP

954 JUMP_BACKWARD 661 (to 414)

956 LOAD_GLOBAL 19 (NULL + log_automation_step)
958 LOAD_FAST 1 (logger)
960 LOAD_CONST 7 ("TERMS")
962 LOAD_CONST 46 ("CHECKBOX_CLICKED")
964 BUILD_MAP 0
966 CALL 4
968 POP_TOP

970 BUILD_LIST 0
972 LOAD_CONST 47 (('Agree and continue', 'Agree & Continue', 'Setuju dan lanjutkan', 'Setuju & Lanjutkan', 'Continue', 'Lanjutkan', 'Accept'))
974 LIST_EXTEND 1
976 STORE_FAST 20 (agree_texts)

978 LOAD_CONST 10 (None)
980 STORE_FAST 21 (agree_button)

982 LOAD_FAST 20 (agree_texts)
984 GET_ITER
986 FOR_ITER 103 (to 1070)
988 STORE_FAST 10 (text)

990 NOP

992 LOAD_FAST 0 (inc_page)
994 LOAD_METHOD 12 (get_by_role)
996 LOAD_CONST 17 ("button")
998 LOAD_GLOBAL 41 (NULL + re)
1000 LOAD_ATTR 21 (compile)
1002 LOAD_FAST 10 (text)
1004 LOAD_GLOBAL 40 (re)
1006 LOAD_ATTR 22 (I)
1008 CALL 2
1010 KW_NAMES 18 (('name',))
1012 CALL 2
1014 STORE_FAST 11 (btn)

1016 LOAD_FAST 11 (btn)
1018 LOAD_METHOD 13 (is_visible)
1020 LOAD_CONST 48 (500)
1022 KW_NAMES 20 (('timeout',))
1024 CALL 1
1026 GET_AWAITABLE 0
1028 LOAD_CONST 10 (None)
1030 SEND 3 (to 1036)
1032 YIELD_VALUE
1034 JUMP_BACKWARD_NO_INTERRUPT 4 (to 1030)
1036 POP_JUMP_FORWARD_IF_FALSE 4 (to 1046)

1038 LOAD_FAST 11 (btn)
1040 STORE_FAST 21 (agree_button)

1042 POP_TOP
1044 JUMP_FORWARD 17 (to 1070)

1046 JUMP_BACKWARD 88 (to 986)
1048 PUSH_EXC_INFO

1050 LOAD_GLOBAL 16 (Exception)
1052 CHECK_EXC_MATCH
1054 POP_JUMP_FORWARD_IF_FALSE 3 (to 1062)
1056 POP_TOP

1058 POP_EXCEPT
1060 JUMP_BACKWARD 100 (to 986)

1062 RERAISE 0
1064 COPY 3
1066 POP_EXCEPT
1068 RERAISE 1

1070 LOAD_FAST 21 (agree_button)
1072 POP_JUMP_FORWARD_IF_FALSE 148 (to 1196)

1074 LOAD_GLOBAL 19 (NULL + log_automation_step)
1076 LOAD_FAST 1 (logger)
1078 LOAD_CONST 7 ("TERMS")
1080 LOAD_CONST 49 ("AGREE_BUTTON_FOUND")
1082 BUILD_MAP 0
1084 CALL 4
1086 POP_TOP

1088 LOAD_GLOBAL 33 (NULL + range)
1090 LOAD_CONST 50 (10)
1092 CALL 1
1094 GET_ITER
1096 FOR_ITER 58 (to 1148)
1098 STORE_FAST 12 (_)

1100 LOAD_FAST 21 (agree_button)
1102 LOAD_METHOD 25 (is_enabled)
1104 LOAD_CONST 35 (1000)
1106 KW_NAMES 20 (('timeout',))
1108 CALL 1
1110 GET_AWAITABLE 0
1112 LOAD_CONST 10 (None)
1114 SEND 3 (to 1120)
1116 YIELD_VALUE
1118 JUMP_BACKWARD_NO_INTERRUPT 4 (to 1114)
1120 POP_JUMP_FORWARD_IF_FALSE 2 (to 1126)

1122 POP_TOP
1124 JUMP_FORWARD 27 (to 1148)

1126 LOAD_GLOBAL 1 (NULL + asyncio)
1128 LOAD_ATTR 11 (sleep)
1130 LOAD_CONST 51 (0.5)
1132 CALL 1
1134 GET_AWAITABLE 0
1136 LOAD_CONST 10 (None)
1138 SEND 3 (to 1144)
1140 YIELD_VALUE
1142 JUMP_BACKWARD_NO_INTERRUPT 4 (to 1138)
1144 POP_TOP
1146 JUMP_BACKWARD 59 (to 1096)

1148 LOAD_FAST 21 (agree_button)
1150 LOAD_METHOD 14 (click)
1152 CALL 0
1154 GET_AWAITABLE 0
1156 LOAD_CONST 10 (None)
1158 SEND 3 (to 1164)
1160 YIELD_VALUE
1162 JUMP_BACKWARD_NO_INTERRUPT 4 (to 1158)
1164 POP_TOP

1166 LOAD_GLOBAL 19 (NULL + log_automation_step)
1168 LOAD_FAST 1 (logger)
1170 LOAD_CONST 7 ("TERMS")
1172 LOAD_CONST 52 ("AGREE_BUTTON_CLICKED")
1174 BUILD_MAP 0
1176 CALL 4
1178 POP_TOP

1180 LOAD_CONST 25 (True)
1182 LOAD_FAST 0 (inc_page)
1184 LOAD_ATTR 4 (url)
1186 LOAD_CONST 53 (('handled', 'url'))
1188 BUILD_CONST_KEY_MAP 2
1190 SWAP 2
1192 POP_TOP
1194 RETURN_VALUE

1196 LOAD_GLOBAL 19 (NULL + log_automation_step)
1198 LOAD_FAST 1 (logger)
1200 LOAD_CONST 7 ("TERMS")
1202 LOAD_CONST 54 ("AGREE_BUTTON_NOT_FOUND")
1204 BUILD_MAP 0
1206 CALL 4
1208 POP_TOP
1210 JUMP_BACKWARD 961 (to 414)

1212 LOAD_CONST 1 (False)
1214 LOAD_CONST 55 ("console_dialog_timeout")
1216 LOAD_CONST 3 (('handled', 'reason'))
1218 BUILD_CONST_KEY_MAP 2
1220 RETURN_VALUE

1222 LOAD_GLOBAL 1 (NULL + asyncio)
1224 LOAD_ATTR 11 (sleep)
1226 LOAD_CONST 5 (1)
1228 CALL 1
1230 GET_AWAITABLE 0
1232 LOAD_CONST 10 (None)
1234 SEND 3 (to 1240)
1236 YIELD_VALUE
1238 JUMP_BACKWARD_NO_INTERRUPT 4 (to 1234)
1240 POP_TOP

1242 LOAD_GLOBAL 1 (NULL + asyncio)
1244 LOAD_ATTR 1 (get_event_loop)
1246 CALL 0
1248 LOAD_METHOD 2 (time)
1250 CALL 0
1252 LOAD_FAST 3 (deadline)
1254 COMPARE_OP 0 (<)
1256 POP_JUMP_BACKWARD_IF_TRUE 1439 (to 54)

1258 LOAD_CONST 1 (False)
1260 LOAD_CONST 56 ("timeout")
1262 LOAD_CONST 3 (('handled', 'reason'))
1264 BUILD_CONST_KEY_MAP 2
1266 RETURN_VALUE


0 RETURN_GENERATOR
2 POP_TOP

4 LOAD_CONST 1 ("")
6 STORE_FAST 4 (api_key)

8 NOP

10 LOAD_CONST 2 ("https://console.cloud.google.com/marketplace/product/google/generativelanguage.googleapis.com?project=")
12 LOAD_FAST 2 (project_id)
14 FORMAT_VALUE 0
16 BUILD_STRING 2
18 STORE_FAST 5 (marketplace_url)

20 LOAD_FAST 0 (inc_page)
22 LOAD_METHOD 0 (goto)
24 LOAD_FAST 5 (marketplace_url)
26 LOAD_CONST 3 ("domcontentloaded")
28 LOAD_CONST 4 (45000)
30 KW_NAMES 5 (('wait_until', 'timeout'))
32 CALL 3
34 GET_AWAITABLE 0
36 LOAD_CONST 6 (None)
38 SEND 3 (to 44)
40 YIELD_VALUE
42 JUMP_BACKWARD_NO_INTERRUPT 4 (to 38)
44 POP_TOP

46 NOP

48 LOAD_FAST 0 (inc_page)
50 LOAD_METHOD 1 (get_by_role)
52 LOAD_CONST 7 ("button")
54 LOAD_GLOBAL 5 (NULL + re)
56 LOAD_ATTR 3 (compile)
58 LOAD_CONST 8 ("Enable|Manage")
60 LOAD_GLOBAL 4 (re)
62 LOAD_ATTR 4 (I)
64 CALL 2
66 KW_NAMES 9 (('name',))
68 CALL 2
70 STORE_FAST 6 (enable_btn)

72 LOAD_FAST 6 (enable_btn)
74 LOAD_METHOD 5 (wait_for)
76 LOAD_CONST 10 ("visible")
78 LOAD_CONST 11 (30000)
80 KW_NAMES 12 (('state', 'timeout'))
82 CALL 2
84 GET_AWAITABLE 0
86 LOAD_CONST 6 (None)
88 SEND 3 (to 94)
90 YIELD_VALUE
92 JUMP_BACKWARD_NO_INTERRUPT 4 (to 88)
94 POP_TOP

96 LOAD_CONST 13 ("enable")
98 LOAD_FAST 6 (enable_btn)
100 LOAD_METHOD 6 (text_content)
102 CALL 0
104 GET_AWAITABLE 0
106 LOAD_CONST 6 (None)
108 SEND 3 (to 114)
110 YIELD_VALUE
112 JUMP_BACKWARD_NO_INTERRUPT 4 (to 108)
114 JUMP_IF_TRUE_OR_POP 1 (to 118)
116 LOAD_CONST 1 ("")
118 LOAD_METHOD 7 (lower)
120 CALL 0
122 CONTAINS_OP 0 (in)
124 POP_JUMP_FORWARD_IF_FALSE 53 (to 164)

126 LOAD_FAST 6 (enable_btn)
128 LOAD_METHOD 8 (click)
130 CALL 0
132 GET_AWAITABLE 0
134 LOAD_CONST 6 (None)
136 SEND 3 (to 142)
138 YIELD_VALUE
140 JUMP_BACKWARD_NO_INTERRUPT 4 (to 136)
142 POP_TOP

144 LOAD_FAST 0 (inc_page)
146 LOAD_METHOD 9 (wait_for_timeout)
148 LOAD_CONST 14 (5000)
150 CALL 1
152 GET_AWAITABLE 0
154 LOAD_CONST 6 (None)
156 SEND 3 (to 162)
158 YIELD_VALUE
160 JUMP_BACKWARD_NO_INTERRUPT 4 (to 156)
162 POP_TOP
164 JUMP_FORWARD 33 (to 200)
166 PUSH_EXC_INFO

168 LOAD_GLOBAL 20 (Exception)
170 CHECK_EXC_MATCH
172 POP_JUMP_FORWARD_IF_FALSE 20 (to 192)
174 POP_TOP

176 LOAD_GLOBAL 23 (NULL + log_automation_step)
178 LOAD_FAST 1 (logger)
180 LOAD_CONST 15 ("API_ENABLE")
182 LOAD_CONST 16 ("ENABLE_BUTTON_FAILED_OR_SKIPPED")
184 CALL 3
186 POP_TOP
188 POP_EXCEPT
190 JUMP_FORWARD 4 (to 200)

192 RERAISE 0
194 COPY 3
196 POP_EXCEPT
198 RERAISE 1

200 LOAD_CONST 17 ("https://console.cloud.google.com/apis/credentials?project=")
202 LOAD_FAST 2 (project_id)
204 FORMAT_VALUE 0
206 BUILD_STRING 2
208 STORE_FAST 7 (cred_url)

210 LOAD_FAST 0 (inc_page)
212 LOAD_METHOD 0 (goto)
214 LOAD_FAST 7 (cred_url)
216 LOAD_CONST 3 ("domcontentloaded")
218 LOAD_CONST 4 (45000)
220 KW_NAMES 5 (('wait_until', 'timeout'))
222 CALL 3
224 GET_AWAITABLE 0
226 LOAD_CONST 6 (None)
228 SEND 3 (to 234)
230 YIELD_VALUE
232 JUMP_BACKWARD_NO_INTERRUPT 4 (to 228)
234 POP_TOP

236 LOAD_FAST 0 (inc_page)
238 LOAD_METHOD 9 (wait_for_timeout)
240 LOAD_CONST 14 (5000)
242 CALL 1
244 GET_AWAITABLE 0
246 LOAD_CONST 6 (None)
248 SEND 3 (to 254)
250 YIELD_VALUE
252 JUMP_BACKWARD_NO_INTERRUPT 4 (to 248)
254 POP_TOP

256 LOAD_CONST 18 (False)
258 STORE_FAST 8 (dropdown_clicked)

260 LOAD_CONST 19 ('button[cfccalloutsteptarget="credential-create-button"]')
262 STORE_FAST 9 (dropdown_selector)

264 LOAD_GLOBAL 25 (NULL + range)
266 LOAD_CONST 20 (3)
268 CALL 1
270 GET_ITER
272 FOR_ITER 304 (to 520)
274 STORE_FAST 10 (_)

276 NOP

278 LOAD_FAST 0 (inc_page)
280 LOAD_METHOD 13 (locator)
282 LOAD_FAST 9 (dropdown_selector)
284 CALL 1
286 STORE_FAST 11 (dropdown_btn)

288 LOAD_FAST 11 (dropdown_btn)
290 LOAD_METHOD 14 (is_visible)
292 LOAD_CONST 21 (3000)
294 KW_NAMES 22 (('timeout',))
296 CALL 1
298 GET_AWAITABLE 0
300 LOAD_CONST 6 (None)
302 SEND 3 (to 308)
304 YIELD_VALUE
306 JUMP_BACKWARD_NO_INTERRUPT 4 (to 302)
308 POP_JUMP_FORWARD_IF_FALSE 30 (to 336)

310 LOAD_FAST 11 (dropdown_btn)
312 LOAD_METHOD 8 (click)
314 CALL 0
316 GET_AWAITABLE 0
318 LOAD_CONST 6 (None)
320 SEND 3 (to 326)
322 YIELD_VALUE
324 JUMP_BACKWARD_NO_INTERRUPT 4 (to 320)
326 POP_TOP
328 LOAD_CONST 23 (True)
330 STORE_FAST 8 (dropdown_clicked)
332 POP_TOP
334 JUMP_FORWARD 223 (to 520)

336 JUMP_FORWARD 16 (to 360)
338 PUSH_EXC_INFO

340 LOAD_GLOBAL 20 (Exception)
342 CHECK_EXC_MATCH
344 POP_JUMP_FORWARD_IF_FALSE 3 (to 352)
346 POP_TOP

348 POP_EXCEPT
350 JUMP_FORWARD 4 (to 360)

352 RERAISE 0
354 COPY 3
356 POP_EXCEPT
358 RERAISE 1

360 NOP

362 LOAD_FAST 0 (inc_page)
364 LOAD_METHOD 13 (locator)
366 LOAD_CONST 24 ('iframe[title="RifIframeEle"]')
368 CALL 1
370 LOAD_ATTR 15 (first)
372 STORE_FAST 12 (iframe)

374 LOAD_FAST 12 (iframe)
376 LOAD_METHOD 14 (is_visible)
378 LOAD_CONST 25 (2000)
380 KW_NAMES 22 (('timeout',))
382 CALL 1
384 GET_AWAITABLE 0
386 LOAD_CONST 6 (None)
388 SEND 3 (to 394)
390 YIELD_VALUE
392 JUMP_BACKWARD_NO_INTERRUPT 4 (to 388)
394 POP_JUMP_FORWARD_IF_FALSE 101 (to 466)

396 LOAD_FAST 12 (iframe)
398 LOAD_METHOD 16 (content_frame)
400 CALL 0
402 STORE_FAST 13 (frame)

404 LOAD_FAST 13 (frame)
406 POP_JUMP_FORWARD_IF_FALSE 79 (to 466)

408 LOAD_FAST 13 (frame)
410 LOAD_METHOD 13 (locator)
412 LOAD_FAST 9 (dropdown_selector)
414 CALL 1
416 STORE_FAST 14 (dropdown_btn_iframe)

418 LOAD_FAST 14 (dropdown_btn_iframe)
420 LOAD_METHOD 14 (is_visible)
422 LOAD_CONST 25 (2000)
424 KW_NAMES 22 (('timeout',))
426 CALL 1
428 GET_AWAITABLE 0
430 LOAD_CONST 6 (None)
432 SEND 3 (to 438)
434 YIELD_VALUE
436 JUMP_BACKWARD_NO_INTERRUPT 4 (to 432)
438 POP_JUMP_FORWARD_IF_FALSE 30 (to 466)

440 LOAD_FAST 14 (dropdown_btn_iframe)
442 LOAD_METHOD 8 (click)
444 CALL 0
446 GET_AWAITABLE 0
448 LOAD_CONST 6 (None)
450 SEND 3 (to 456)
452 YIELD_VALUE
454 JUMP_BACKWARD_NO_INTERRUPT 4 (to 450)
456 POP_TOP
458 LOAD_CONST 23 (True)
460 STORE_FAST 8 (dropdown_clicked)
462 POP_TOP
464 JUMP_FORWARD 50 (to 520)
466 JUMP_FORWARD 16 (to 490)
468 PUSH_EXC_INFO

470 LOAD_GLOBAL 20 (Exception)
472 CHECK_EXC_MATCH
474 POP_JUMP_FORWARD_IF_FALSE 3 (to 482)
476 POP_TOP

478 POP_EXCEPT
480 JUMP_FORWARD 4 (to 490)

482 RERAISE 0
484 COPY 3
486 POP_EXCEPT
488 RERAISE 1

490 LOAD_FAST 8 (dropdown_clicked)
492 POP_JUMP_FORWARD_IF_FALSE 2 (to 498)

494 POP_TOP
496 JUMP_FORWARD 29 (to 520)

498 LOAD_FAST 0 (inc_page)
500 LOAD_METHOD 9 (wait_for_timeout)
502 LOAD_CONST 25 (2000)
504 CALL 1
506 GET_AWAITABLE 0
508 LOAD_CONST 6 (None)
510 SEND 3 (to 516)
512 YIELD_VALUE
514 JUMP_BACKWARD_NO_INTERRUPT 4 (to 510)
516 POP_TOP
518 JUMP_BACKWARD 306 (to 272)

520 LOAD_FAST 8 (dropdown_clicked)
522 POP_JUMP_FORWARD_IF_TRUE 22 (to 546)

524 LOAD_GLOBAL 23 (NULL + log_automation_step)
526 LOAD_FAST 1 (logger)
528 LOAD_CONST 26 ("CREDENTIALS")
530 LOAD_CONST 27 ("DROPDOWN_BUTTON_NOT_FOUND")
532 CALL 3
534 POP_TOP
536 LOAD_CONST 18 (False)
538 LOAD_CONST 1 ("")
540 LOAD_CONST 28 (('success', 'api_key'))
542 BUILD_CONST_KEY_MAP 2
544 RETURN_VALUE

546 LOAD_GLOBAL 23 (NULL + log_automation_step)
548 LOAD_FAST 1 (logger)
550 LOAD_CONST 26 ("CREDENTIALS")
552 LOAD_CONST 29 ("DROPDOWN_BUTTON_CLICKED")
554 CALL 3
556 POP_TOP

558 LOAD_FAST 0 (inc_page)
560 LOAD_METHOD 9 (wait_for_timeout)
562 LOAD_CONST 30 (1500)
564 CALL 1
566 GET_AWAITABLE 0
568 LOAD_CONST 6 (None)
570 SEND 3 (to 576)
572 YIELD_VALUE
574 JUMP_BACKWARD_NO_INTERRUPT 4 (to 570)
576 POP_TOP

578 NOP

580 LOAD_FAST 0 (inc_page)
582 LOAD_METHOD 1 (get_by_role)
584 LOAD_CONST 31 ("menuitem")
586 LOAD_CONST 32 ("API key")
588 KW_NAMES 9 (('name',))
590 CALL 2
592 LOAD_ATTR 15 (first)
594 LOAD_METHOD 8 (click)
596 LOAD_CONST 14 (5000)
598 KW_NAMES 22 (('timeout',))
600 CALL 1
602 GET_AWAITABLE 0
604 LOAD_CONST 6 (None)
606 SEND 3 (to 612)
608 YIELD_VALUE
610 JUMP_BACKWARD_NO_INTERRUPT 4 (to 606)
612 POP_TOP

614 LOAD_GLOBAL 23 (NULL + log_automation_step)
616 LOAD_FAST 1 (logger)
618 LOAD_CONST 26 ("CREDENTIALS")
620 LOAD_CONST 33 ("API_KEY_MENU_ITEM_CLICKED")
622 CALL 3
624 POP_TOP
626 JUMP_FORWARD 61 (to 696)
628 PUSH_EXC_INFO

630 LOAD_GLOBAL 20 (Exception)
632 CHECK_EXC_MATCH
634 POP_JUMP_FORWARD_IF_FALSE 48 (to 688)
636 STORE_FAST 15 (e)

638 LOAD_GLOBAL 23 (NULL + log_automation_step)
640 LOAD_FAST 1 (logger)
642 LOAD_CONST 26 ("CREDENTIALS")
644 LOAD_CONST 34 ("API_KEY_MENU_ITEM_FAILED")
646 LOAD_CONST 35 ("error")
648 LOAD_GLOBAL 35 (NULL + str)
650 LOAD_FAST 15 (e)
652 CALL 1
654 BUILD_MAP 1
656 CALL 4
658 POP_TOP
660 LOAD_CONST 18 (False)
662 LOAD_CONST 1 ("")
664 LOAD_CONST 28 (('success', 'api_key'))
666 BUILD_CONST_KEY_MAP 2
668 SWAP 2
670 POP_EXCEPT
672 LOAD_CONST 6 (None)
674 STORE_FAST 15 (e)
676 DELETE_FAST 15 (e)
678 RETURN_VALUE
680 LOAD_CONST 6 (None)
682 STORE_FAST 15 (e)
684 DELETE_FAST 15 (e)
686 RERAISE 1

688 RERAISE 0
690 COPY 3
692 POP_EXCEPT
694 RERAISE 1

696 NOP

698 LOAD_FAST 0 (inc_page)
700 LOAD_METHOD 13 (locator)
702 LOAD_CONST 36 ("text=/API key created/i")
704 CALL 1
706 LOAD_METHOD 13 (locator)
708 LOAD_CONST 37 ("..")
710 CALL 1
712 LOAD_METHOD 13 (locator)
714 LOAD_CONST 37 ("..")
716 CALL 1
718 STORE_FAST 16 (modal_locator)

720 LOAD_FAST 16 (modal_locator)
722 LOAD_METHOD 5 (wait_for)
724 LOAD_CONST 10 ("visible")
726 LOAD_CONST 38 (60000)
728 KW_NAMES 12 (('state', 'timeout'))
730 CALL 2
732 GET_AWAITABLE 0
734 LOAD_CONST 6 (None)
736 SEND 3 (to 742)
738 YIELD_VALUE
740 JUMP_BACKWARD_NO_INTERRUPT 4 (to 736)
742 POP_TOP

744 LOAD_GLOBAL 23 (NULL + log_automation_step)
746 LOAD_FAST 1 (logger)
748 LOAD_CONST 39 ("API_KEY")
750 LOAD_CONST 40 ("MODAL_DETECTED")
752 CALL 3
754 POP_TOP
756 JUMP_FORWARD 38 (to 802)
758 PUSH_EXC_INFO

760 LOAD_GLOBAL 20 (Exception)
762 CHECK_EXC_MATCH
764 POP_JUMP_FORWARD_IF_FALSE 25 (to 794)
766 POP_TOP

768 LOAD_GLOBAL 23 (NULL + log_automation_step)
770 LOAD_FAST 1 (logger)
772 LOAD_CONST 39 ("API_KEY")
774 LOAD_CONST 41 ("MODAL_NOT_FOUND")
776 CALL 3
778 POP_TOP
780 LOAD_CONST 18 (False)
782 LOAD_CONST 1 ("")
784 LOAD_CONST 28 (('success', 'api_key'))
786 BUILD_CONST_KEY_MAP 2
788 SWAP 2
790 POP_EXCEPT
792 RETURN_VALUE

794 RERAISE 0
796 COPY 3
798 POP_EXCEPT
800 RERAISE 1

802 NOP

804 LOAD_FAST 16 (modal_locator)
806 LOAD_METHOD 13 (locator)
808 LOAD_CONST 42 ("input.cfc-code-snippet-input")
810 CALL 1
812 STORE_FAST 17 (input_selector)

814 LOAD_FAST 17 (input_selector)
816 LOAD_METHOD 5 (wait_for)
818 LOAD_CONST 10 ("visible")
820 LOAD_CONST 43 (10000)
822 KW_NAMES 12 (('state', 'timeout'))
824 CALL 2
826 GET_AWAITABLE 0
828 LOAD_CONST 6 (None)
830 SEND 3 (to 836)
832 YIELD_VALUE
834 JUMP_BACKWARD_NO_INTERRUPT 4 (to 830)
836 POP_TOP

838 LOAD_GLOBAL 25 (NULL + range)
840 LOAD_CONST 44 (10)
842 CALL 1
844 GET_ITER
846 FOR_ITER 103 (to 928)
848 STORE_FAST 10 (_)

850 LOAD_FAST 17 (input_selector)
852 LOAD_METHOD 18 (input_value)
854 LOAD_CONST 45 (1000)
856 KW_NAMES 22 (('timeout',))
858 CALL 1
860 GET_AWAITABLE 0
862 LOAD_CONST 6 (None)
864 SEND 3 (to 870)
866 YIELD_VALUE
868 JUMP_BACKWARD_NO_INTERRUPT 4 (to 864)
870 STORE_FAST 18 (val)

872 LOAD_FAST 18 (val)
874 POP_JUMP_FORWARD_IF_FALSE 44 (to 906)
876 LOAD_FAST 18 (val)
878 LOAD_METHOD 19 (startswith)
880 LOAD_CONST 46 ("AIza")
882 CALL 1
884 POP_JUMP_FORWARD_IF_FALSE 23 (to 906)
886 LOAD_GLOBAL 41 (NULL + len)
888 LOAD_FAST 18 (val)
890 CALL 1
892 LOAD_CONST 47 (35)
894 COMPARE_OP 4 (>)
896 POP_JUMP_FORWARD_IF_FALSE 4 (to 906)

898 LOAD_FAST 18 (val)
900 STORE_FAST 4 (api_key)

902 POP_TOP
904 JUMP_FORWARD 28 (to 928)

906 LOAD_FAST 0 (inc_page)
908 LOAD_METHOD 9 (wait_for_timeout)
910 LOAD_CONST 45 (1000)
912 CALL 1
914 GET_AWAITABLE 0
916 LOAD_CONST 6 (None)
918 SEND 3 (to 924)
920 YIELD_VALUE
922 JUMP_BACKWARD_NO_INTERRUPT 4 (to 918)
924 POP_TOP
926 JUMP_BACKWARD 104 (to 846)
928 JUMP_FORWARD 56 (to 988)
930 PUSH_EXC_INFO

932 LOAD_GLOBAL 20 (Exception)
934 CHECK_EXC_MATCH
936 POP_JUMP_FORWARD_IF_FALSE 43 (to 980)
938 STORE_FAST 15 (e)

940 LOAD_GLOBAL 23 (NULL + log_automation_step)
942 LOAD_FAST 1 (logger)
944 LOAD_CONST 39 ("API_KEY")
946 LOAD_CONST 48 ("EXTRACT_INPUT_READ_FAILED")
948 LOAD_CONST 35 ("error")
950 LOAD_GLOBAL 35 (NULL + str)
952 LOAD_FAST 15 (e)
954 CALL 1
956 BUILD_MAP 1
958 CALL 4
960 POP_TOP
962 POP_EXCEPT
964 LOAD_CONST 6 (None)
966 STORE_FAST 15 (e)
968 DELETE_FAST 15 (e)
970 JUMP_FORWARD 8 (to 988)
972 LOAD_CONST 6 (None)
974 STORE_FAST 15 (e)
976 DELETE_FAST 15 (e)
978 RERAISE 1

980 RERAISE 0
982 COPY 3
984 POP_EXCEPT
986 RERAISE 1

988 LOAD_FAST 4 (api_key)
990 POP_JUMP_FORWARD_IF_TRUE 22 (to 1014)

992 LOAD_GLOBAL 23 (NULL + log_automation_step)
994 LOAD_FAST 1 (logger)
996 LOAD_CONST 39 ("API_KEY")
998 LOAD_CONST 49 ("EXTRACT_FAILED_FINAL")
1000 CALL 3
1002 POP_TOP
1004 LOAD_CONST 18 (False)
1006 LOAD_CONST 1 ("")
1008 LOAD_CONST 28 (('success', 'api_key'))
1010 BUILD_CONST_KEY_MAP 2
1012 RETURN_VALUE

1014 LOAD_GLOBAL 23 (NULL + log_automation_step)
1016 LOAD_FAST 1 (logger)
1018 LOAD_CONST 39 ("API_KEY")
1020 LOAD_CONST 50 ("SUCCESS")
1022 LOAD_CONST 51 ("api_key")
1024 LOAD_FAST 4 (api_key)
1026 BUILD_MAP 1
1028 CALL 4
1030 POP_TOP

1032 LOAD_CONST 23 (True)
1034 LOAD_FAST 4 (api_key)
1036 LOAD_CONST 28 (('success', 'api_key'))
1038 BUILD_CONST_KEY_MAP 2
1040 RETURN_VALUE
1042 PUSH_EXC_INFO

1044 LOAD_GLOBAL 20 (Exception)
1046 CHECK_EXC_MATCH
1048 POP_JUMP_FORWARD_IF_FALSE 48 (to 1102)
1050 STORE_FAST 15 (e)

1052 LOAD_GLOBAL 23 (NULL + log_automation_step)
1054 LOAD_FAST 1 (logger)
1056 LOAD_CONST 39 ("API_KEY")
1058 LOAD_CONST 52 ("FATAL_ERROR")
1060 LOAD_CONST 35 ("error")
1062 LOAD_GLOBAL 35 (NULL + str)
1064 LOAD_FAST 15 (e)
1066 CALL 1
1068 BUILD_MAP 1
1070 CALL 4
1072 POP_TOP

1074 LOAD_CONST 18 (False)
1076 LOAD_CONST 1 ("")
1078 LOAD_CONST 28 (('success', 'api_key'))
1080 BUILD_CONST_KEY_MAP 2
1082 SWAP 2
1084 POP_EXCEPT
1086 LOAD_CONST 6 (None)
1088 STORE_FAST 15 (e)
1090 DELETE_FAST 15 (e)
1092 RETURN_VALUE
1094 LOAD_CONST 6 (None)
1096 STORE_FAST 15 (e)
1098 DELETE_FAST 15 (e)
1100 RERAISE 1

1102 RERAISE 0
1104 COPY 3
1106 POP_EXCEPT
1108 RERAISE 1