Sorry: IndentationError: unexpected indent (indented_0.py, line 48)

<module>: Success: Equal

***<module>.confirm_via_link_action: Failure: Compilation Error

***<module>.confirm_via_link_action.<genexpr>, None: Failure: Missing bytecode

<module>._is_confirmation_success: Success: Equal

<module>._is_confirmation_success.<genexpr>: Success: Equal





0 LOAD_CONST 0 ("\nAksi konfirmasi email dan login untuk Cloud Skills Boost.\nDipanggil oleh CloudSkillAutomation agar file utama tetap ringkas.\n")
2 STORE_NAME 0 (__doc__)

4 LOAD_CONST 1 (0)
6 LOAD_CONST 2 (('Optional', 'Dict'))
8 IMPORT_NAME 1 (typing)
10 IMPORT_FROM 2 (Optional)
12 STORE_NAME 2 (Optional)
14 IMPORT_FROM 3 (Dict)
16 STORE_NAME 3 (Dict)
18 POP_TOP

20 LOAD_CONST 1 (0)
22 LOAD_CONST 3 (('Page', 'BrowserContext'))
24 IMPORT_NAME 4 (playwright.async_api)
26 IMPORT_FROM 5 (Page)
28 STORE_NAME 5 (Page)
30 IMPORT_FROM 6 (BrowserContext)
32 STORE_NAME 6 (BrowserContext)
34 POP_TOP

36 LOAD_CONST 1 (0)
38 LOAD_CONST 4 (('log_automation_step',))
40 IMPORT_NAME 7 (utils.logger)
42 IMPORT_FROM 8 (log_automation_step)
44 STORE_NAME 8 (log_automation_step)
46 POP_TOP

48 NOP

50 LOAD_CONST 14 ((None,))

52 LOAD_CONST 6 ("context")
54 LOAD_NAME 6 (BrowserContext)

56 LOAD_CONST 7 ("page")
58 LOAD_NAME 5 (Page)

60 LOAD_CONST 8 ("url")
62 LOAD_NAME 9 (str)

64 LOAD_CONST 9 ("password")
66 LOAD_NAME 9 (str)

68 LOAD_CONST 10 ("email")
70 LOAD_NAME 2 (Optional)
72 LOAD_NAME 9 (str)
74 BINARY_SUBSCR

76 LOAD_CONST 11 ("return")
78 LOAD_NAME 3 (Dict)

80 BUILD_TUPLE 12
82 LOAD_CONST 12 (code object confirm_via_link_action)
84 MAKE_FUNCTION 5 (default, annotation)
86 STORE_NAME 10 (confirm_via_link_action)

88 LOAD_CONST 7 ("page")
90 LOAD_NAME 5 (Page)
92 LOAD_CONST 11 ("return")
94 LOAD_NAME 11 (bool)
96 BUILD_TUPLE 4
98 LOAD_CONST 13 (code object _is_confirmation_success)
100 MAKE_FUNCTION 4 (annotation)
102 STORE_NAME 12 (_is_confirmation_success)
104 LOAD_CONST 5 (None)
106 RETURN_VALUE


0 RETURN_GENERATOR
2 POP_TOP

4 LOAD_GLOBAL 1 (NULL + log_automation_step)
6 LOAD_FAST 2 (logger)
8 LOAD_CONST 1 ("EMAIL_CONFIRM")
10 LOAD_CONST 2 ("NAVIGATE")
12 LOAD_CONST 3 ("url")
14 LOAD_FAST 3 (url)
16 BUILD_MAP 1
18 CALL 4
20 POP_TOP

22 NOP

24 LOAD_FAST 1 (page)
26 LOAD_METHOD 1 (goto)
28 LOAD_FAST 3 (url)
30 CALL 1
32 GET_AWAITABLE 0
34 LOAD_CONST 4 (None)
36 SEND 3 (to 42)
38 YIELD_VALUE
40 JUMP_BACKWARD_NO_INTERRUPT 4 (to 36)
42 POP_TOP

44 LOAD_FAST 1 (page)
46 LOAD_METHOD 2 (wait_for_load_state)
48 LOAD_CONST 5 ("domcontentloaded")
50 CALL 1
52 GET_AWAITABLE 0
54 LOAD_CONST 4 (None)
56 SEND 3 (to 62)
58 YIELD_VALUE
60 JUMP_BACKWARD_NO_INTERRUPT 4 (to 56)
62 POP_TOP
64 JUMP_FORWARD 237 (to 276)
66 PUSH_EXC_INFO

68 LOAD_GLOBAL 6 (Exception)
70 CHECK_EXC_MATCH
72 POP_JUMP_FORWARD_IF_FALSE 224 (to 268)
74 STORE_FAST 6 (e)

76 LOAD_GLOBAL 1 (NULL + log_automation_step)
78 LOAD_FAST 2 (logger)
80 LOAD_CONST 1 ("EMAIL_CONFIRM")
82 LOAD_CONST 6 ("NAVIGATE_RETRY")
84 LOAD_CONST 7 ("error")
86 LOAD_GLOBAL 9 (NULL + str)
88 LOAD_FAST 6 (e)
90 CALL 1
92 BUILD_MAP 1
94 CALL 4
96 POP_TOP

98 NOP

100 LOAD_FAST 1 (page)
102 LOAD_METHOD 5 (is_closed)
104 CALL 0
106 POP_JUMP_FORWARD_IF_FALSE 26 (to 126)

108 LOAD_FAST 0 (context)
110 LOAD_METHOD 6 (new_page)
112 CALL 0
114 GET_AWAITABLE 0
116 LOAD_CONST 4 (None)
118 SEND 3 (to 124)
120 YIELD_VALUE
122 JUMP_BACKWARD_NO_INTERRUPT 4 (to 118)
124 STORE_FAST 1 (page)

126 LOAD_FAST 1 (page)
128 LOAD_METHOD 1 (goto)
130 LOAD_FAST 3 (url)
132 CALL 1
134 GET_AWAITABLE 0
136 LOAD_CONST 4 (None)
138 SEND 3 (to 144)
140 YIELD_VALUE
142 JUMP_BACKWARD_NO_INTERRUPT 4 (to 138)
144 POP_TOP

146 LOAD_FAST 1 (page)
148 LOAD_METHOD 2 (wait_for_load_state)
150 LOAD_CONST 5 ("domcontentloaded")
152 CALL 1
154 GET_AWAITABLE 0
156 LOAD_CONST 4 (None)
158 SEND 3 (to 164)
160 YIELD_VALUE
162 JUMP_BACKWARD_NO_INTERRUPT 4 (to 158)
164 POP_TOP
166 JUMP_FORWARD 79 (to 250)
168 PUSH_EXC_INFO

170 LOAD_GLOBAL 6 (Exception)
172 CHECK_EXC_MATCH
174 POP_JUMP_FORWARD_IF_FALSE 66 (to 242)
176 STORE_FAST 7 (e2)

178 LOAD_GLOBAL 1 (NULL + log_automation_step)
180 LOAD_FAST 2 (logger)
182 LOAD_CONST 1 ("EMAIL_CONFIRM")
184 LOAD_CONST 8 ("NAVIGATE_RETRY_FAILED")
186 LOAD_CONST 7 ("error")
188 LOAD_GLOBAL 9 (NULL + str)
190 LOAD_FAST 7 (e2)
192 CALL 1
194 BUILD_MAP 1
196 CALL 4
198 POP_TOP

200 LOAD_CONST 9 (False)
202 LOAD_GLOBAL 9 (NULL + str)
204 LOAD_FAST 7 (e2)
206 CALL 1
208 LOAD_CONST 10 (('success', 'error'))
210 BUILD_CONST_KEY_MAP 2
212 SWAP 2
214 POP_EXCEPT
216 LOAD_CONST 4 (None)
218 STORE_FAST 7 (e2)
220 DELETE_FAST 7 (e2)
222 SWAP 2
224 POP_EXCEPT
226 LOAD_CONST 4 (None)
228 STORE_FAST 6 (e)
230 DELETE_FAST 6 (e)
232 RETURN_VALUE
234 LOAD_CONST 4 (None)
236 STORE_FAST 7 (e2)
238 DELETE_FAST 7 (e2)
240 RERAISE 1

242 RERAISE 0
244 COPY 3
246 POP_EXCEPT
248 RERAISE 1

250 POP_EXCEPT
252 LOAD_CONST 4 (None)
254 STORE_FAST 6 (e)
256 DELETE_FAST 6 (e)
258 JUMP_FORWARD 8 (to 276)
260 LOAD_CONST 4 (None)
262 STORE_FAST 6 (e)
264 DELETE_FAST 6 (e)
266 RERAISE 1

268 RERAISE 0
270 COPY 3
272 POP_EXCEPT
274 RERAISE 1

276 LOAD_CONST 9 (False)
278 STORE_FAST 8 (confirmed)

280 NOP

282 LOAD_GLOBAL 15 (NULL + _is_confirmation_success)
284 LOAD_FAST 1 (page)
286 CALL 1
288 GET_AWAITABLE 0
290 LOAD_CONST 4 (None)
292 SEND 3 (to 298)
294 YIELD_VALUE
296 JUMP_BACKWARD_NO_INTERRUPT 4 (to 292)
298 POP_JUMP_FORWARD_IF_FALSE 19 (to 316)

300 LOAD_GLOBAL 1 (NULL + log_automation_step)
302 LOAD_FAST 2 (logger)
304 LOAD_CONST 1 ("EMAIL_CONFIRM")
306 LOAD_CONST 11 ("CONFIRMATION_OK")
308 CALL 3
310 POP_TOP

312 LOAD_CONST 12 (True)
314 STORE_FAST 8 (confirmed)
316 JUMP_FORWARD 16 (to 340)
318 PUSH_EXC_INFO

320 LOAD_GLOBAL 6 (Exception)
322 CHECK_EXC_MATCH
324 POP_JUMP_FORWARD_IF_FALSE 3 (to 332)
326 POP_TOP

328 POP_EXCEPT
330 JUMP_FORWARD 4 (to 340)

332 RERAISE 0
334 COPY 3
336 POP_EXCEPT
338 RERAISE 1

340 NOP

342 LOAD_FAST 1 (page)
344 LOAD_METHOD 8 (query_selector)
346 LOAD_CONST 13 ("input[type='password']")
348 CALL 1
350 GET_AWAITABLE 0
352 LOAD_CONST 4 (None)
354 SEND 3 (to 360)
356 YIELD_VALUE
358 JUMP_BACKWARD_NO_INTERRUPT 4 (to 354)
360 STORE_FAST 9 (has_pwd)
362 JUMP_FORWARD 18 (to 390)
364 PUSH_EXC_INFO

366 LOAD_GLOBAL 6 (Exception)
368 CHECK_EXC_MATCH
370 POP_JUMP_FORWARD_IF_FALSE 5 (to 382)
372 POP_TOP

374 LOAD_CONST 4 (None)
376 STORE_FAST 9 (has_pwd)
378 POP_EXCEPT
380 JUMP_FORWARD 4 (to 390)

382 RERAISE 0
384 COPY 3
386 POP_EXCEPT
388 RERAISE 1

390 LOAD_FAST 8 (confirmed)
392 POP_JUMP_FORWARD_IF_FALSE 91 (to 476)
394 LOAD_FAST 9 (has_pwd)
396 POP_JUMP_FORWARD_IF_TRUE 89 (to 476)

398 NOP

400 LOAD_FAST 1 (page)
402 LOAD_METHOD 1 (goto)
404 LOAD_CONST 14 ("https://www.cloudskillsboost.google/users/sign_in")
406 CALL 1
408 GET_AWAITABLE 0
410 LOAD_CONST 4 (None)
412 SEND 3 (to 418)
414 YIELD_VALUE
416 JUMP_BACKWARD_NO_INTERRUPT 4 (to 412)
418 POP_TOP

420 LOAD_FAST 1 (page)
422 LOAD_METHOD 2 (wait_for_load_state)
424 LOAD_CONST 5 ("domcontentloaded")
426 CALL 1
428 GET_AWAITABLE 0
430 LOAD_CONST 4 (None)
432 SEND 3 (to 438)
434 YIELD_VALUE
436 JUMP_BACKWARD_NO_INTERRUPT 4 (to 432)
438 POP_TOP

440 LOAD_GLOBAL 1 (NULL + log_automation_step)
442 LOAD_FAST 2 (logger)
444 LOAD_CONST 1 ("EMAIL_CONFIRM")
446 LOAD_CONST 15 ("NAVIGATE_TO_SIGN_IN_AFTER_CONFIRM")
448 CALL 3
450 POP_TOP
452 JUMP_FORWARD 16 (to 476)
454 PUSH_EXC_INFO

456 LOAD_GLOBAL 6 (Exception)
458 CHECK_EXC_MATCH
460 POP_JUMP_FORWARD_IF_FALSE 3 (to 468)
462 POP_TOP

464 POP_EXCEPT
466 JUMP_FORWARD 4 (to 476)

468 RERAISE 0
470 COPY 3
472 POP_EXCEPT
474 RERAISE 1

476 NOP

478 LOAD_FAST 1 (page)
480 LOAD_METHOD 9 (wait_for_selector)
482 LOAD_CONST 13 ("input[type='password']")
484 LOAD_CONST 16 (30000)
486 KW_NAMES 17 (('timeout',))
488 CALL 2
490 GET_AWAITABLE 0
492 LOAD_CONST 4 (None)
494 SEND 3 (to 500)
496 YIELD_VALUE
498 JUMP_BACKWARD_NO_INTERRUPT 4 (to 494)
500 POP_TOP

502 LOAD_GLOBAL 1 (NULL + log_automation_step)
504 LOAD_FAST 2 (logger)
506 LOAD_CONST 1 ("EMAIL_CONFIRM")
508 LOAD_CONST 18 ("LOGIN_FORM_DETECTED")
510 CALL 3
512 POP_TOP

514 NOP

516 LOAD_FAST 5 (email)
518 POP_JUMP_FORWARD_IF_FALSE 118 (to 600)

520 LOAD_FAST 1 (page)
522 LOAD_METHOD 8 (query_selector)
524 LOAD_CONST 19 ("input[type='email'], input[name='email']")
526 CALL 1
528 GET_AWAITABLE 0
530 LOAD_CONST 4 (None)
532 SEND 3 (to 538)
534 YIELD_VALUE
536 JUMP_BACKWARD_NO_INTERRUPT 4 (to 532)
538 STORE_FAST 10 (email_loc)

540 LOAD_FAST 10 (email_loc)
542 POP_JUMP_FORWARD_IF_FALSE 89 (to 600)

544 LOAD_FAST 10 (email_loc)
546 LOAD_METHOD 10 (fill)
548 LOAD_CONST 20 ("")
550 CALL 1
552 GET_AWAITABLE 0
554 LOAD_CONST 4 (None)
556 SEND 3 (to 562)
558 YIELD_VALUE
560 JUMP_BACKWARD_NO_INTERRUPT 4 (to 556)
562 POP_TOP

564 LOAD_FAST 10 (email_loc)
566 LOAD_METHOD 10 (fill)
568 LOAD_FAST 5 (email)
570 LOAD_METHOD 11 (strip)
572 CALL 0
574 CALL 1
576 GET_AWAITABLE 0
578 LOAD_CONST 4 (None)
580 SEND 3 (to 586)
582 YIELD_VALUE
584 JUMP_BACKWARD_NO_INTERRUPT 4 (to 580)
586 POP_TOP

588 LOAD_GLOBAL 1 (NULL + log_automation_step)
590 LOAD_FAST 2 (logger)
592 LOAD_CONST 1 ("EMAIL_CONFIRM")
594 LOAD_CONST 21 ("EMAIL_FILLED_FORCE")
596 CALL 3
598 POP_TOP
600 JUMP_FORWARD 16 (to 624)
602 PUSH_EXC_INFO

604 LOAD_GLOBAL 6 (Exception)
606 CHECK_EXC_MATCH
608 POP_JUMP_FORWARD_IF_FALSE 3 (to 616)
610 POP_TOP

612 POP_EXCEPT
614 JUMP_FORWARD 4 (to 624)

616 RERAISE 0
618 COPY 3
620 POP_EXCEPT
622 RERAISE 1

624 LOAD_FAST 1 (page)
626 LOAD_METHOD 12 (locator)
628 LOAD_CONST 13 ("input[type='password']")
630 CALL 1
632 LOAD_ATTR 13 (first)
634 STORE_FAST 11 (pwd_loc)

636 LOAD_FAST 11 (pwd_loc)
638 LOAD_METHOD 10 (fill)
640 LOAD_CONST 20 ("")
642 CALL 1
644 GET_AWAITABLE 0
646 LOAD_CONST 4 (None)
648 SEND 3 (to 654)
650 YIELD_VALUE
652 JUMP_BACKWARD_NO_INTERRUPT 4 (to 648)
654 POP_TOP

656 LOAD_FAST 11 (pwd_loc)
658 LOAD_METHOD 14 (type)
660 LOAD_FAST 4 (password)
662 JUMP_IF_TRUE_OR_POP 1 (to 666)
664 LOAD_CONST 20 ("")
666 LOAD_METHOD 11 (strip)
668 CALL 0
670 LOAD_CONST 22 (20)
672 KW_NAMES 23 (('delay',))
674 CALL 2
676 GET_AWAITABLE 0
678 LOAD_CONST 4 (None)
680 SEND 3 (to 686)
682 YIELD_VALUE
684 JUMP_BACKWARD_NO_INTERRUPT 4 (to 680)
686 POP_TOP

688 LOAD_GLOBAL 1 (NULL + log_automation_step)
690 LOAD_FAST 2 (logger)
692 LOAD_CONST 1 ("EMAIL_CONFIRM")
694 LOAD_CONST 24 ("CREDENTIALS_USED")
696 LOAD_CONST 25 ("email")
698 LOAD_FAST 5 (email)
700 JUMP_IF_TRUE_OR_POP 1 (to 704)
702 LOAD_CONST 26 ("(prefilled)")
704 BUILD_MAP 1
706 CALL 4
708 POP_TOP

710 LOAD_CONST 9 (False)
712 STORE_FAST 12 (submitted)

714 LOAD_CONST 27 (("button[type='submit']", "input[type='submit']", "button:has-text('Sign in')", "button:has-text('Sign In')", "button:has-text('Log in')", "button:has-text('Log In')"))
716 GET_ITER
718 FOR_ITER 105 (to 808)
720 STORE_FAST 13 (sel)

722 NOP

724 LOAD_FAST 1 (page)
726 LOAD_METHOD 12 (locator)
728 LOAD_FAST 13 (sel)
730 CALL 1
732 LOAD_ATTR 13 (first)
734 STORE_FAST 14 (btn)

736 LOAD_FAST 14 (btn)
738 LOAD_METHOD 15 (count)
740 CALL 0
742 GET_AWAITABLE 0
744 LOAD_CONST 4 (None)
746 SEND 3 (to 752)
748 YIELD_VALUE
750 JUMP_BACKWARD_NO_INTERRUPT 4 (to 746)
752 LOAD_CONST 28 (0)
754 COMPARE_OP 4 (>)
756 POP_JUMP_FORWARD_IF_FALSE 30 (to 784)

758 LOAD_FAST 14 (btn)
760 LOAD_METHOD 16 (click)
762 CALL 0
764 GET_AWAITABLE 0
766 LOAD_CONST 4 (None)
768 SEND 3 (to 774)
770 YIELD_VALUE
772 JUMP_BACKWARD_NO_INTERRUPT 4 (to 768)
774 POP_TOP

776 LOAD_CONST 12 (True)
778 STORE_FAST 12 (submitted)

780 POP_TOP
782 JUMP_FORWARD 17 (to 808)

784 JUMP_BACKWARD 90 (to 718)
786 PUSH_EXC_INFO

788 LOAD_GLOBAL 6 (Exception)
790 CHECK_EXC_MATCH
792 POP_JUMP_FORWARD_IF_FALSE 3 (to 800)
794 POP_TOP

796 POP_EXCEPT
798 JUMP_BACKWARD 102 (to 718)

800 RERAISE 0
802 COPY 3
804 POP_EXCEPT
806 RERAISE 1

808 LOAD_FAST 12 (submitted)
810 POP_JUMP_FORWARD_IF_TRUE 47 (to 862)

812 NOP

814 LOAD_FAST 11 (pwd_loc)
816 LOAD_METHOD 17 (press)
818 LOAD_CONST 29 ("Enter")
820 CALL 1
822 GET_AWAITABLE 0
824 LOAD_CONST 4 (None)
826 SEND 3 (to 832)
828 YIELD_VALUE
830 JUMP_BACKWARD_NO_INTERRUPT 4 (to 826)
832 POP_TOP

834 LOAD_CONST 12 (True)
836 STORE_FAST 12 (submitted)
838 JUMP_FORWARD 16 (to 862)
840 PUSH_EXC_INFO

842 LOAD_GLOBAL 6 (Exception)
844 CHECK_EXC_MATCH
846 POP_JUMP_FORWARD_IF_FALSE 3 (to 854)
848 POP_TOP

850 POP_EXCEPT
852 JUMP_FORWARD 4 (to 862)

854 RERAISE 0
856 COPY 3
858 POP_EXCEPT
860 RERAISE 1

862 LOAD_FAST 1 (page)
864 LOAD_METHOD 2 (wait_for_load_state)
866 LOAD_CONST 30 ("networkidle")
868 LOAD_CONST 31 (20000)
870 KW_NAMES 17 (('timeout',))
872 CALL 2
874 GET_AWAITABLE 0
876 LOAD_CONST 4 (None)
878 SEND 3 (to 884)
880 YIELD_VALUE
882 JUMP_BACKWARD_NO_INTERRUPT 4 (to 878)
884 POP_TOP

886 LOAD_GLOBAL 1 (NULL + log_automation_step)
888 LOAD_FAST 2 (logger)
890 LOAD_CONST 1 ("EMAIL_CONFIRM")
892 LOAD_CONST 32 ("SUBMITTED")
894 CALL 3
896 POP_TOP

898 NOP

900 BUILD_LIST 0
902 LOAD_CONST 33 (("div[role='alert']", '.alert', '.errors', '.error'))
904 LIST_EXTEND 1
906 STORE_FAST 15 (candidates)

908 BUILD_LIST 0
910 LOAD_CONST 34 (('invalid', 'incorrect', 'does not match', "doesn't match", 'mismatch', 'not found'))
912 LIST_EXTEND 1
914 STORE_FAST 16 (error_keywords)

916 LOAD_FAST 15 (candidates)
918 GET_ITER
920 FOR_ITER 208 (to 1122)
922 STORE_FAST 13 (sel)

924 NOP

926 LOAD_FAST 1 (page)
928 LOAD_METHOD 8 (query_selector)
930 LOAD_FAST 13 (sel)
932 CALL 1
934 GET_AWAITABLE 0
936 LOAD_CONST 4 (None)
938 SEND 3 (to 944)
940 YIELD_VALUE
942 JUMP_BACKWARD_NO_INTERRUPT 4 (to 938)
944 STORE_FAST 17 (el)
946 JUMP_FORWARD 18 (to 974)
948 PUSH_EXC_INFO

950 LOAD_GLOBAL 6 (Exception)
952 CHECK_EXC_MATCH
954 POP_JUMP_FORWARD_IF_FALSE 5 (to 966)
956 POP_TOP

958 LOAD_CONST 4 (None)
960 STORE_FAST 17 (el)
962 POP_EXCEPT
964 JUMP_FORWARD 4 (to 974)

966 RERAISE 0
968 COPY 3
970 POP_EXCEPT
972 RERAISE 1

974 LOAD_FAST 17 (el)
976 POP_JUMP_FORWARD_IF_TRUE 1 (to 980)

978 JUMP_BACKWARD 52 (to 920)

980 NOP

982 LOAD_FAST 17 (el)
984 LOAD_METHOD 18 (text_content)
986 CALL 0
988 GET_AWAITABLE 0
990 LOAD_CONST 4 (None)
992 SEND 3 (to 998)
994 YIELD_VALUE
996 JUMP_BACKWARD_NO_INTERRUPT 4 (to 992)
998 JUMP_IF_TRUE_OR_POP 1 (to 1002)
1000 LOAD_CONST 20 ("")
1002 LOAD_METHOD 11 (strip)
1004 CALL 0
1006 LOAD_METHOD 19 (lower)
1008 CALL 0
1010 STORE_DEREF 19 (txt)
1012 JUMP_FORWARD 18 (to 1040)
1014 PUSH_EXC_INFO

1016 LOAD_GLOBAL 6 (Exception)
1018 CHECK_EXC_MATCH
1020 POP_JUMP_FORWARD_IF_FALSE 5 (to 1032)
1022 POP_TOP

1024 LOAD_CONST 20 ("")
1026 STORE_DEREF 19 (txt)
1028 POP_EXCEPT
1030 JUMP_FORWARD 4 (to 1040)

1032 RERAISE 0
1034 COPY 3
1036 POP_EXCEPT
1038 RERAISE 1

1040 LOAD_CONST 35 ("successfully confirmed")
1042 LOAD_DEREF 19 (txt)
1044 CONTAINS_OP 0 (in)
1046 POP_JUMP_FORWARD_IF_TRUE 4 (to 1056)
1048 LOAD_CONST 36 ("account has been confirmed")
1050 LOAD_DEREF 19 (txt)
1052 CONTAINS_OP 0 (in)
1054 POP_JUMP_FORWARD_IF_FALSE 1 (to 1058)

1056 JUMP_BACKWARD 145 (to 920)

1058 LOAD_GLOBAL 41 (NULL + any)
1060 LOAD_CLOSURE 19 (txt)
1062 BUILD_TUPLE 1
1064 LOAD_CONST 37 (code object <genexpr>)
1066 MAKE_FUNCTION 8 (closure)
1068 LOAD_FAST 16 (error_keywords)
1070 GET_ITER
1072 CALL 0
1074 CALL 1
1076 POP_JUMP_FORWARD_IF_FALSE 36 (to 1120)

1078 LOAD_GLOBAL 1 (NULL + log_automation_step)
1080 LOAD_FAST 2 (logger)
1082 LOAD_CONST 1 ("EMAIL_CONFIRM")
1084 LOAD_CONST 38 ("LOGIN_FAILED")
1086 LOAD_FAST 13 (sel)
1088 LOAD_DEREF 19 (txt)
1090 LOAD_CONST 4 (None)
1092 LOAD_CONST 39 (200)
1094 BUILD_SLICE 2
1096 BINARY_SUBSCR
1098 LOAD_CONST 40 (('selector', 'text'))
1100 BUILD_CONST_KEY_MAP 2
1102 CALL 4
1104 POP_TOP

1106 LOAD_CONST 9 (False)
1108 LOAD_CONST 41 ("Invalid email or password")
1110 LOAD_CONST 10 (('success', 'error'))
1112 BUILD_CONST_KEY_MAP 2
1114 SWAP 2
1116 POP_TOP
1118 RETURN_VALUE

1120 JUMP_BACKWARD 209 (to 920)

1122 JUMP_FORWARD 16 (to 1146)
1124 PUSH_EXC_INFO

1126 LOAD_GLOBAL 6 (Exception)
1128 CHECK_EXC_MATCH
1130 POP_JUMP_FORWARD_IF_FALSE 3 (to 1138)
1132 POP_TOP

1134 POP_EXCEPT
1136 JUMP_FORWARD 4 (to 1146)

1138 RERAISE 0
1140 COPY 3
1142 POP_EXCEPT
1144 RERAISE 1
1146 JUMP_FORWARD 33 (to 1182)
1148 PUSH_EXC_INFO

1150 LOAD_GLOBAL 6 (Exception)
1152 CHECK_EXC_MATCH
1154 POP_JUMP_FORWARD_IF_FALSE 20 (to 1174)
1156 POP_TOP

1158 LOAD_GLOBAL 1 (NULL + log_automation_step)
1160 LOAD_FAST 2 (logger)
1162 LOAD_CONST 1 ("EMAIL_CONFIRM")
1164 LOAD_CONST 42 ("NO_LOGIN_FORM")
1166 CALL 3
1168 POP_TOP
1170 POP_EXCEPT
1172 JUMP_FORWARD 4 (to 1182)

1174 RERAISE 0
1176 COPY 3
1178 POP_EXCEPT
1180 RERAISE 1

1182 LOAD_FAST 1 (page)
1184 LOAD_ATTR 21 (url)
1186 STORE_FAST 18 (current_url)

1188 LOAD_GLOBAL 1 (NULL + log_automation_step)
1190 LOAD_FAST 2 (logger)
1192 LOAD_CONST 1 ("EMAIL_CONFIRM")
1194 LOAD_CONST 43 ("SUCCESS")
1196 LOAD_CONST 3 ("url")
1198 LOAD_FAST 18 (current_url)
1200 BUILD_MAP 1
1202 CALL 4
1204 POP_TOP

1206 LOAD_CONST 12 (True)
1208 LOAD_FAST 18 (current_url)
1210 LOAD_CONST 44 (('success', 'url'))
1212 BUILD_CONST_KEY_MAP 2
1214 RETURN_VALUE

0 COPY_FREE_VARS 1

2 RETURN_GENERATOR
4 POP_TOP
6 LOAD_FAST 0 (.0)
8 FOR_ITER 8 (to 24)
10 STORE_FAST 1 (k)
12 LOAD_FAST 1 (k)
14 LOAD_DEREF 2 (txt)
16 CONTAINS_OP 0 (in)
18 YIELD_VALUE
20 POP_TOP
22 JUMP_BACKWARD 9 (to 8)
24 LOAD_CONST 0 (None)
26 RETURN_VALUE


0 RETURN_GENERATOR
2 POP_TOP

4 BUILD_LIST 0
6 LOAD_CONST 1 (('successfully confirmed', 'your account was successfully confirmed', 'your account has been confirmed', 'email address has been successfully confirmed'))
8 LIST_EXTEND 1
10 STORE_FAST 1 (patterns)

12 BUILD_LIST 0
14 LOAD_CONST 2 (("div[role='alert']", '.alert.alert-success', '.notice', '.flash--success', '#notice', "[class*='success']"))
16 LIST_EXTEND 1
18 STORE_FAST 2 (containers)

20 LOAD_FAST 2 (containers)
22 GET_ITER
24 FOR_ITER 149 (to 172)
26 STORE_FAST 3 (sel)

28 NOP

30 LOAD_FAST 0 (page)
32 LOAD_METHOD 0 (query_selector)
34 LOAD_FAST 3 (sel)
36 CALL 1
38 GET_AWAITABLE 0
40 LOAD_CONST 0 (None)
42 SEND 3 (to 48)
44 YIELD_VALUE
46 JUMP_BACKWARD_NO_INTERRUPT 4 (to 42)
48 STORE_FAST 4 (el)
50 JUMP_FORWARD 18 (to 78)
52 PUSH_EXC_INFO

54 LOAD_GLOBAL 2 (Exception)
56 CHECK_EXC_MATCH
58 POP_JUMP_FORWARD_IF_FALSE 5 (to 70)
60 POP_TOP

62 LOAD_CONST 0 (None)
64 STORE_FAST 4 (el)
66 POP_EXCEPT
68 JUMP_FORWARD 4 (to 78)

70 RERAISE 0
72 COPY 3
74 POP_EXCEPT
76 RERAISE 1

78 LOAD_FAST 4 (el)
80 POP_JUMP_FORWARD_IF_TRUE 1 (to 84)

82 JUMP_BACKWARD 52 (to 24)

84 NOP

86 LOAD_FAST 4 (el)
88 LOAD_METHOD 2 (text_content)
90 CALL 0
92 GET_AWAITABLE 0
94 LOAD_CONST 0 (None)
96 SEND 3 (to 102)
98 YIELD_VALUE
100 JUMP_BACKWARD_NO_INTERRUPT 4 (to 96)
102 JUMP_IF_TRUE_OR_POP 1 (to 106)
104 LOAD_CONST 3 ("")
106 LOAD_METHOD 3 (strip)
108 CALL 0
110 LOAD_METHOD 4 (lower)
112 CALL 0
114 STORE_FAST 5 (txt)
116 JUMP_FORWARD 18 (to 144)
118 PUSH_EXC_INFO

120 LOAD_GLOBAL 2 (Exception)
122 CHECK_EXC_MATCH
124 POP_JUMP_FORWARD_IF_FALSE 5 (to 136)
126 POP_TOP

128 LOAD_CONST 3 ("")
130 STORE_FAST 5 (txt)
132 POP_EXCEPT
134 JUMP_FORWARD 4 (to 144)

136 RERAISE 0
138 COPY 3
140 POP_EXCEPT
142 RERAISE 1

144 LOAD_FAST 1 (patterns)
146 GET_ITER
148 FOR_ITER 10 (to 170)
150 STORE_FAST 6 (pat)

152 LOAD_FAST 6 (pat)
154 LOAD_FAST 5 (txt)
156 CONTAINS_OP 0 (in)
158 POP_JUMP_FORWARD_IF_FALSE 4 (to 168)

160 POP_TOP
162 POP_TOP
164 LOAD_CONST 4 (True)
166 RETURN_VALUE

168 JUMP_BACKWARD 11 (to 148)

170 JUMP_BACKWARD 150 (to 24)

172 NOP

174 LOAD_FAST 0 (page)
176 LOAD_METHOD 2 (text_content)
178 LOAD_CONST 5 ("body")
180 CALL 1
182 GET_AWAITABLE 0
184 LOAD_CONST 0 (None)
186 SEND 3 (to 192)
188 YIELD_VALUE
190 JUMP_BACKWARD_NO_INTERRUPT 4 (to 186)
192 JUMP_IF_TRUE_OR_POP 1 (to 196)
194 LOAD_CONST 3 ("")
196 LOAD_METHOD 4 (lower)
198 CALL 0
200 STORE_DEREF 7 (body_txt)

202 LOAD_GLOBAL 11 (NULL + any)
204 LOAD_CLOSURE 7 (body_txt)
206 BUILD_TUPLE 1
208 LOAD_CONST 6 (code object <genexpr>)
210 MAKE_FUNCTION 8 (closure)
212 LOAD_FAST 1 (patterns)
214 GET_ITER
216 CALL 0
218 CALL 1
220 RETURN_VALUE
222 PUSH_EXC_INFO

224 LOAD_GLOBAL 2 (Exception)
226 CHECK_EXC_MATCH
228 POP_JUMP_FORWARD_IF_FALSE 4 (to 238)
230 POP_TOP

232 POP_EXCEPT
234 LOAD_CONST 7 (False)
236 RETURN_VALUE

238 RERAISE 0
240 COPY 3
242 POP_EXCEPT
244 RERAISE 1

0 COPY_FREE_VARS 1

2 RETURN_GENERATOR
4 POP_TOP
6 LOAD_FAST 0 (.0)
8 FOR_ITER 8 (to 24)
10 STORE_FAST 1 (pat)
12 LOAD_FAST 1 (pat)
14 LOAD_DEREF 2 (body_txt)
16 CONTAINS_OP 0 (in)
18 YIELD_VALUE
20 POP_TOP
22 JUMP_BACKWARD 9 (to 8)
24 LOAD_CONST 0 (None)
26 RETURN_VALUE